Workbook

Sheet RÉCAPITULATIF
A1: ALYZIA | RÉCAPITULATIF
A3: COMPTE RENDU DE SUPERVISION • SEPTEMBRE 2026 • TOUTES COMPAGNIES
A5: DOSSIERS | D5: BAGAGES ATTENDUS | G5: SAUVÉS | J5: CHARGÉS | M5: NON CHARGÉS | P5: ANNULÉS | S5: TAGS EN DOUBLE
A6: =SUM(B14:B27) -> 1735 | D6: =SUM(D14:D27) -> 106188 | G6: =SUM(E14:E27) -> 773 | J6: =SUM(F14:F27) -> 369 | M6: =SUM(G14:G27) -> 593 | P6: =SUM(H14:H27) -> 0 | S6: =MAX(BASE!$Q$6:$Q$1740) -> 26
A8: TAUX DE TRAITEMENT | D8: DOSSIERS TRAITÉS | G8: % SAUVÉS | J8: % CHARGÉS | M8: % NON CHARGÉS | P8: % ANNULÉS | S8: LIGNES CONCERNÉES
A9: =IFERROR((G6+J6+M6+P6)/A6,0) -> 1 | D9: =SUM(G6,J6,M6,P6) -> 1735 | G9: =G6/$A$6 -> 0.44553314 | J9: =J6/$A$6 -> 0.21268012 | M9: =M6/$A$6 -> 0.34178674 | P9: =P6/$A$6 -> 0 | S9: =COUNTIF(BASE!$P$6:$P$1740,">1") -> 52
A12: RÉPARTITION PAR COMPAGNIE | AA12: COMPAGNIE | AB12: SAUVÉS | AC12: CHARGÉS | AD12: NON CHARGÉS | AE12: ANNULÉS
A13: CIE | B13: DOSSIERS | C13: BAG. TRAITÉS | D13: ATTENDUS | E13: SAUVÉS | F13: CHARGÉS | G13: NON CHARGÉS | H13: ANNULÉS | I13: TAUX SAUVÉS | AA13: AI | AB13: =SUMIF($A$14:$A$27,AA13,$E$14:$E$27) -> 93 | AC13: =SUMIF($A$14:$A$27,AA13,$F$14:$F$27) -> 13 | AD13: =SUMIF($A$14:$A$27,AA13,$G$14:$G$27) -> 60 | AE13: =SUMIF($A$14:$A$27,AA13,$H$14:$H$27) -> 0
A14: SK | B14: =COUNTIF(BASE!$B$6:$B$1740,A14) -> 133 | C14: =SUMIF(BASE!$B$6:$B$1740,A14,BASE!$F$6:$F$1740) -> 133 | D14: 4758 | E14: =COUNTIFS(BASE!$B$6:$B$1740,A14,BASE!$M$6:$M$1740,"SAUVÉ") -> 62 | F14: =COUNTIFS(BASE!$B$6:$B$1740,A14,BASE!$M$6:$M$1740,"CHARGÉ") -> 13 | G14: =COUNTIFS(BASE!$B$6:$B$1740,A14,BASE!$M$6:$M$1740,"NON CHARGÉ") -> 58 | H14: =COUNTIFS(BASE!$B$6:$B$1740,A14,BASE!$M$6:$M$1740,"ANNULÉ") -> 0 | I14: =IFERROR(E14/B14,0) -> 0.46616541 | AA14: AT | AB14: =SUMIF($A$14:$A$27,AA14,$E$14:$E$27) -> 94 | AC14: =SUMIF($A$14:$A$27,AA14,$F$14:$F$27) -> 45 | AD14: =SUMIF($A$14:$A$27,AA14,$G$14:$G$27) -> 45 | AE14: =SUMIF($A$14:$A$27,AA14,$H$14:$H$27) -> 0
A15: AI | B15: =COUNTIF(BASE!$B$6:$B$1740,A15) -> 166 | C15: =SUMIF(BASE!$B$6:$B$1740,A15,BASE!$F$6:$F$1740) -> 166 | D15: =SUM('SYNTHÈSE PAR DATE'!J6:J35) -> 9011 | E15: =COUNTIFS(BASE!$B$6:$B$1740,A15,BASE!$M$6:$M$1740,"SAUVÉ") -> 93 | F15: =COUNTIFS(BASE!$B$6:$B$1740,A15,BASE!$M$6:$M$1740,"CHARGÉ") -> 13 | G15: =COUNTIFS(BASE!$B$6:$B$1740,A15,BASE!$M$6:$M$1740,"NON CHARGÉ") -> 60 | H15: =COUNTIFS(BASE!$B$6:$B$1740,A15,BASE!$M$6:$M$1740,"ANNULÉ") -> 0 | I15: =IFERROR(E15/B15,0) -> 0.56024096 | AA15: AV | AB15: =SUMIF($A$14:$A$27,AA15,$E$14:$E$27) -> 49 | AC15: =SUMIF($A$14:$A$27,AA15,$F$14:$F$27) -> 16 | AD15: =SUMIF($A$14:$A$27,AA15,$G$14:$G$27) -> 36 | AE15: =SUMIF($A$14:$A$27,AA15,$H$14:$H$27) -> 0
A16: EI | B16: =COUNTIF(BASE!$B$6:$B$1740,A16) -> 302 | C16: =SUMIF(BASE!$B$6:$B$1740,A16,BASE!$F$6:$F$1740) -> 302 | D16: =SUM('SYNTHÈSE PAR DATE'!K6:K35) -> 17510 | E16: =COUNTIFS(BASE!$B$6:$B$1740,A16,BASE!$M$6:$M$1740,"SAUVÉ") -> 44 | F16: =COUNTIFS(BASE!$B$6:$B$1740,A16,BASE!$M$6:$M$1740,"CHARGÉ") -> 82 | G16: =COUNTIFS(BASE!$B$6:$B$1740,A16,BASE!$M$6:$M$1740,"NON CHARGÉ") -> 176 | H16: =COUNTIFS(BASE!$B$6:$B$1740,A16,BASE!$M$6:$M$1740,"ANNULÉ") -> 0 | I16: =IFERROR(E16/B16,0) -> 0.14569536 | AA16: DE | AB16: =SUMIF($A$14:$A$27,AA16,$E$14:$E$27) -> 53 | AC16: =SUMIF($A$14:$A$27,AA16,$F$14:$F$27) -> 49 | AD16: =SUMIF($A$14:$A$27,AA16,$G$14:$G$27) -> 19 | AE16: =SUMIF($A$14:$A$27,AA16,$H$14:$H$27) -> 0
A17: LA | B17: =COUNTIF(BASE!$B$6:$B$1740,A17) -> 85 | C17: =SUMIF(BASE!$B$6:$B$1740,A17,BASE!$F$6:$F$1740) -> 85 | D17: =SUM('SYNTHÈSE PAR DATE'!L6:L35) -> 7669 | E17: =COUNTIFS(BASE!$B$6:$B$1740,A17,BASE!$M$6:$M$1740,"SAUVÉ") -> 17 | F17: =COUNTIFS(BASE!$B$6:$B$1740,A17,BASE!$M$6:$M$1740,"CHARGÉ") -> 39 | G17: =COUNTIFS(BASE!$B$6:$B$1740,A17,BASE!$M$6:$M$1740,"NON CHARGÉ") -> 29 | H17: =COUNTIFS(BASE!$B$6:$B$1740,A17,BASE!$M$6:$M$1740,"ANNULÉ") -> 0 | I17: =IFERROR(E17/B17,0) -> 0.2 | AA17: EI | AB17: =SUMIF($A$14:$A$27,AA17,$E$14:$E$27) -> 44 | AC17: =SUMIF($A$14:$A$27,AA17,$F$14:$F$27) -> 82 | AD17: =SUMIF($A$14:$A$27,AA17,$G$14:$G$27) -> 176 | AE17: =SUMIF($A$14:$A$27,AA17,$H$14:$H$27) -> 0
A18: HF | B18: =COUNTIF(BASE!$B$6:$B$1740,A18) -> 30 | C18: =SUMIF(BASE!$B$6:$B$1740,A18,BASE!$F$6:$F$1740) -> 30 | D18: =SUM('SYNTHÈSE PAR DATE'!M6:M35) -> 13252 | E18: =COUNTIFS(BASE!$B$6:$B$1740,A18,BASE!$M$6:$M$1740,"SAUVÉ") -> 8 | F18: =COUNTIFS(BASE!$B$6:$B$1740,A18,BASE!$M$6:$M$1740,"CHARGÉ") -> 16 | G18: =COUNTIFS(BASE!$B$6:$B$1740,A18,BASE!$M$6:$M$1740,"NON CHARGÉ") -> 6 | H18: =COUNTIFS(BASE!$B$6:$B$1740,A18,BASE!$M$6:$M$1740,"ANNULÉ") -> 0 | I18: =IFERROR(E18/B18,0) -> 0.26666667 | AA18: FI | AB18: =SUMIF($A$14:$A$27,AA18,$E$14:$E$27) -> 88 | AC18: =SUMIF($A$14:$A$27,AA18,$F$14:$F$27) -> 25 | AD18: =SUMIF($A$14:$A$27,AA18,$G$14:$G$27) -> 61 | AE18: =SUMIF($A$14:$A$27,AA18,$H$14:$H$27) -> 0
A19: SB | B19: =COUNTIF(BASE!$B$6:$B$1740,A19) -> 55 | C19: =SUMIF(BASE!$B$6:$B$1740,A19,BASE!$F$6:$F$1740) -> 55 | D19: =SUM('SYNTHÈSE PAR DATE'!N6:N35) -> 3602 | E19: =COUNTIFS(BASE!$B$6:$B$1740,A19,BASE!$M$6:$M$1740,"SAUVÉ") -> 38 | F19: =COUNTIFS(BASE!$B$6:$B$1740,A19,BASE!$M$6:$M$1740,"CHARGÉ") -> 7 | G19: =COUNTIFS(BASE!$B$6:$B$1740,A19,BASE!$M$6:$M$1740,"NON CHARGÉ") -> 10 | H19: =COUNTIFS(BASE!$B$6:$B$1740,A19,BASE!$M$6:$M$1740,"ANNULÉ") -> 0 | I19: =IFERROR(E19/B19,0) -> 0.69090909 | AA19: HF | AB19: =SUMIF($A$14:$A$27,AA19,$E$14:$E$27) -> 8 | AC19: =SUMIF($A$14:$A$27,AA19,$F$14:$F$27) -> 16 | AD19: =SUMIF($A$14:$A$27,AA19,$G$14:$G$27) -> 6 | AE19: =SUMIF($A$14:$A$27,AA19,$H$14:$H$27) -> 0
A20: DE | B20: =COUNTIF(BASE!$B$6:$B$1740,A20) -> 121 | C20: =SUMIF(BASE!$B$6:$B$1740,A20,BASE!$F$6:$F$1740) -> 121 | D20: =SUM('SYNTHÈSE PAR DATE'!O6:O35) -> 5215 | E20: =COUNTIFS(BASE!$B$6:$B$1740,A20,BASE!$M$6:$M$1740,"SAUVÉ") -> 53 | F20: =COUNTIFS(BASE!$B$6:$B$1740,A20,BASE!$M$6:$M$1740,"CHARGÉ") -> 49 | G20: =COUNTIFS(BASE!$B$6:$B$1740,A20,BASE!$M$6:$M$1740,"NON CHARGÉ") -> 19 | H20: =COUNTIFS(BASE!$B$6:$B$1740,A20,BASE!$M$6:$M$1740,"ANNULÉ") -> 0 | I20: =IFERROR(E20/B20,0) -> 0.43801653 | AA20: JU | AB20: =SUMIF($A$14:$A$27,AA20,$E$14:$E$27) -> 149 | AC20: =SUMIF($A$14:$A$27,AA20,$F$14:$F$27) -> 16 | AD20: =SUMIF($A$14:$A$27,AA20,$G$14:$G$27) -> 32 | AE20: =SUMIF($A$14:$A$27,AA20,$H$14:$H$27) -> 0
A21: MH | B21: =COUNTIF(BASE!$B$6:$B$1740,A21) -> 40 | C21: =SUMIF(BASE!$B$6:$B$1740,A21,BASE!$F$6:$F$1740) -> 40 | D21: =SUM('SYNTHÈSE PAR DATE'!P6:P35) -> 6770 | E21: =COUNTIFS(BASE!$B$6:$B$1740,A21,BASE!$M$6:$M$1740,"SAUVÉ") -> 12 | F21: =COUNTIFS(BASE!$B$6:$B$1740,A21,BASE!$M$6:$M$1740,"CHARGÉ") -> 4 | G21: =COUNTIFS(BASE!$B$6:$B$1740,A21,BASE!$M$6:$M$1740,"NON CHARGÉ") -> 24 | H21: =COUNTIFS(BASE!$B$6:$B$1740,A21,BASE!$M$6:$M$1740,"ANNULÉ") -> 0 | I21: =IFERROR(E21/B21,0) -> 0.3 | AA21: LA | AB21: =SUMIF($A$14:$A$27,AA21,$E$14:$E$27) -> 17 | AC21: =SUMIF($A$14:$A$27,AA21,$F$14:$F$27) -> 39 | AD21: =SUMIF($A$14:$A$27,AA21,$G$14:$G$27) -> 29 | AE21: =SUMIF($A$14:$A$27,AA21,$H$14:$H$27) -> 0
A22: RJ | B22: =COUNTIF(BASE!$B$6:$B$1740,A22) -> 45 | C22: =SUMIF(BASE!$B$6:$B$1740,A22,BASE!$F$6:$F$1740) -> 45 | D22: =SUM('SYNTHÈSE PAR DATE'!Q6:Q35) -> 4421 | E22: =COUNTIFS(BASE!$B$6:$B$1740,A22,BASE!$M$6:$M$1740,"SAUVÉ") -> 19 | F22: =COUNTIFS(BASE!$B$6:$B$1740,A22,BASE!$M$6:$M$1740,"CHARGÉ") -> 12 | G22: =COUNTIFS(BASE!$B$6:$B$1740,A22,BASE!$M$6:$M$1740,"NON CHARGÉ") -> 14 | H22: =COUNTIFS(BASE!$B$6:$B$1740,A22,BASE!$M$6:$M$1740,"ANNULÉ") -> 0 | I22: =IFERROR(E22/B22,0) -> 0.42222222 | AA22: LO | AB22: =SUMIF($A$14:$A$27,AA22,$E$14:$E$27) -> 47 | AC22: =SUMIF($A$14:$A$27,AA22,$F$14:$F$27) -> 32 | AD22: =SUMIF($A$14:$A$27,AA22,$G$14:$G$27) -> 23 | AE22: =SUMIF($A$14:$A$27,AA22,$H$14:$H$27) -> 0
A23: AV | B23: =COUNTIF(BASE!$B$6:$B$1740,A23) -> 101 | C23: =SUMIF(BASE!$B$6:$B$1740,A23,BASE!$F$6:$F$1740) -> 101 | D23: =SUM('SYNTHÈSE PAR DATE'!R6:R35) -> 5214 | E23: =COUNTIFS(BASE!$B$6:$B$1740,A23,BASE!$M$6:$M$1740,"SAUVÉ") -> 49 | F23: =COUNTIFS(BASE!$B$6:$B$1740,A23,BASE!$M$6:$M$1740,"CHARGÉ") -> 16 | G23: =COUNTIFS(BASE!$B$6:$B$1740,A23,BASE!$M$6:$M$1740,"NON CHARGÉ") -> 36 | H23: =COUNTIFS(BASE!$B$6:$B$1740,A23,BASE!$M$6:$M$1740,"ANNULÉ") -> 0 | I23: =IFERROR(E23/B23,0) -> 0.48514851 | AA23: MH | AB23: =SUMIF($A$14:$A$27,AA23,$E$14:$E$27) -> 12 | AC23: =SUMIF($A$14:$A$27,AA23,$F$14:$F$27) -> 4 | AD23: =SUMIF($A$14:$A$27,AA23,$G$14:$G$27) -> 24 | AE23: =SUMIF($A$14:$A$27,AA23,$H$14:$H$27) -> 0
A24: FI | B24: =COUNTIF(BASE!$B$6:$B$1740,A24) -> 174 | C24: =SUMIF(BASE!$B$6:$B$1740,A24,BASE!$F$6:$F$1740) -> 174 | D24: =SUM('SYNTHÈSE PAR DATE'!S6:S35) -> 9141 | E24: =COUNTIFS(BASE!$B$6:$B$1740,A24,BASE!$M$6:$M$1740,"SAUVÉ") -> 88 | F24: =COUNTIFS(BASE!$B$6:$B$1740,A24,BASE!$M$6:$M$1740,"CHARGÉ") -> 25 | G24: =COUNTIFS(BASE!$B$6:$B$1740,A24,BASE!$M$6:$M$1740,"NON CHARGÉ") -> 61 | H24: =COUNTIFS(BASE!$B$6:$B$1740,A24,BASE!$M$6:$M$1740,"ANNULÉ") -> 0 | I24: =IFERROR(E24/B24,0) -> 0.50574713 | AA24: RJ | AB24: =SUMIF($A$14:$A$27,AA24,$E$14:$E$27) -> 19 | AC24: =SUMIF($A$14:$A$27,AA24,$F$14:$F$27) -> 12 | AD24: =SUMIF($A$14:$A$27,AA24,$G$14:$G$27) -> 14 | AE24: =SUMIF($A$14:$A$27,AA24,$H$14:$H$27) -> 0
A25: AT | B25: =COUNTIF(BASE!$B$6:$B$1740,A25) -> 184 | C25: =SUMIF(BASE!$B$6:$B$1740,A25,BASE!$F$6:$F$1740) -> 184 | D25: =SUM('SYNTHÈSE PAR DATE'!T6:T35) -> 10427 | E25: =COUNTIFS(BASE!$B$6:$B$1740,A25,BASE!$M$6:$M$1740,"SAUVÉ") -> 94 | F25: =COUNTIFS(BASE!$B$6:$B$1740,A25,BASE!$M$6:$M$1740,"CHARGÉ") -> 45 | G25: =COUNTIFS(BASE!$B$6:$B$1740,A25,BASE!$M$6:$M$1740,"NON CHARGÉ") -> 45 | H25: =COUNTIFS(BASE!$B$6:$B$1740,A25,BASE!$M$6:$M$1740,"ANNULÉ") -> 0 | I25: =IFERROR(E25/B25,0) -> 0.51086957 | AA25: SB | AB25: =SUMIF($A$14:$A$27,AA25,$E$14:$E$27) -> 38 | AC25: =SUMIF($A$14:$A$27,AA25,$F$14:$F$27) -> 7 | AD25: =SUMIF($A$14:$A$27,AA25,$G$14:$G$27) -> 10 | AE25: =SUMIF($A$14:$A$27,AA25,$H$14:$H$27) -> 0
A26: JU | B26: =COUNTIF(BASE!$B$6:$B$1740,A26) -> 197 | C26: =SUMIF(BASE!$B$6:$B$1740,A26,BASE!$F$6:$F$1740) -> 197 | D26: =SUM('SYNTHÈSE PAR DATE'!U6:U35) -> 4332 | E26: =COUNTIFS(BASE!$B$6:$B$1740,A26,BASE!$M$6:$M$1740,"SAUVÉ") -> 149 | F26: =COUNTIFS(BASE!$B$6:$B$1740,A26,BASE!$M$6:$M$1740,"CHARGÉ") -> 16 | G26: =COUNTIFS(BASE!$B$6:$B$1740,A26,BASE!$M$6:$M$1740,"NON CHARGÉ") -> 32 | H26: =COUNTIFS(BASE!$B$6:$B$1740,A26,BASE!$M$6:$M$1740,"ANNULÉ") -> 0 | I26: =IFERROR(E26/B26,0) -> 0.75634518 | AA26: SK | AB26: =SUMIF($A$14:$A$27,AA26,$E$14:$E$27) -> 62 | AC26: =SUMIF($A$14:$A$27,AA26,$F$14:$F$27) -> 13 | AD26: =SUMIF($A$14:$A$27,AA26,$G$14:$G$27) -> 58 | AE26: =SUMIF($A$14:$A$27,AA26,$H$14:$H$27) -> 0
A27: LO | B27: =COUNTIF(BASE!$B$6:$B$1740,A27) -> 102 | C27: =SUMIF(BASE!$B$6:$B$1740,A27,BASE!$F$6:$F$1740) -> 102 | D27: =SUM('SYNTHÈSE PAR DATE'!V6:V35) -> 4866 | E27: =COUNTIFS(BASE!$B$6:$B$1740,A27,BASE!$M$6:$M$1740,"SAUVÉ") -> 47 | F27: =COUNTIFS(BASE!$B$6:$B$1740,A27,BASE!$M$6:$M$1740,"CHARGÉ") -> 32 | G27: =COUNTIFS(BASE!$B$6:$B$1740,A27,BASE!$M$6:$M$1740,"NON CHARGÉ") -> 23 | H27: =COUNTIFS(BASE!$B$6:$B$1740,A27,BASE!$M$6:$M$1740,"ANNULÉ") -> 0 | I27: =IFERROR(E27/B27,0) -> 0.46078431
A28: TOTAL | B28: =SUM(B14:B27) -> 1735 | C28: =SUM(C14:C27) -> 1735 | D28: =SUM(D14:D27) -> 106188 | E28: =SUM(E14:E27) -> 773 | F28: =SUM(F14:F27) -> 369 | G28: =SUM(G14:G27) -> 593 | H28: =SUM(H14:H27) -> 0 | I28: =IFERROR(E28/B28,0) -> 0.44553314
A71: STATUT | B71: DOSSIERS
A72: Chargés | B72: =J6 -> 369
A73: Sauvés | B73: =G6 -> 773
A74: Non chargés | B74: =M6 -> 593
A75: Annulés | B75: =P6 -> 0
A110: TAGS EN DOUBLE — À VÉRIFIER (VRAI DOUBLON · STATUT DIFFÉRENT · LÉGITIME)
A111: ="VRAI DOUBLON : "&COUNTIF(BASE!$R$6:$R$1740,"VRAI DOUBLON")&" • STATUT DIFFÉRENT : "&COUNTIF(BASE!$R$6:$R$1740,"STATUT DIFFÉRENT")&" • LÉGITIME : "&COUNTIF(BASE!$R$6:$R$1740,"LÉGITIME") -> VRAI DOUBLON : 9 • STATUT DIFFÉRENT : 1 • LÉGITIME : 16
A112: CIE | B112: DATE | D112: N° VOL | F112: N° TAG | H112: OCC. | I112: TYPE
A113: =IFERROR(INDEX(BASE!$B$6:$B$1740,MATCH(ROWS($A$113:$A113),BASE!$Q$6:$Q$1740,0)),"") -> AT | B113: =IFERROR(INDEX(BASE!$A$6:$A$1740,MATCH(ROWS($A$113:$A113),BASE!$Q$6:$Q$1740,0)),"") -> 01/09/2026 | D113: =IFERROR(INDEX(BASE!$C$6:$C$1740,MATCH(ROWS($A$113:$A113),BASE!$Q$6:$Q$1740,0)),"") -> AT639 | F113: =IFERROR(INDEX(BASE!$E$6:$E$1740,MATCH(ROWS($A$113:$A113),BASE!$Q$6:$Q$1740,0)),"") -> AT844408 | H113: =IFERROR(INDEX(BASE!$P$6:$P$1740,MATCH(ROWS($A$113:$A113),BASE!$Q$6:$Q$1740,0)),"") -> 2 | I113: =IFERROR(INDEX(BASE!$R$6:$R$1740,MATCH(ROWS($A$113:$A113),BASE!$Q$6:$Q$1740,0)),"") -> VRAI DOUBLON
A114: =IFERROR(INDEX(BASE!$B$6:$B$1740,MATCH(ROWS($A$113:$A114),BASE!$Q$6:$Q$1740,0)),"") -> AT | B114: =IFERROR(INDEX(BASE!$A$6:$A$1740,MATCH(ROWS($A$113:$A114),BASE!$Q$6:$Q$1740,0)),"") -> 01/09/2026 | D114: =IFERROR(INDEX(BASE!$C$6:$C$1740,MATCH(ROWS($A$113:$A114),BASE!$Q$6:$Q$1740,0)),"") -> AT639 | F114: =IFERROR(INDEX(BASE!$E$6:$E$1740,MATCH(ROWS($A$113:$A114),BASE!$Q$6:$Q$1740,0)),"") -> AT844125 | H114: =IFERROR(INDEX(BASE!$P$6:$P$1740,MATCH(ROWS($A$113:$A114),BASE!$Q$6:$Q$1740,0)),"") -> 2 | I114: =IFERROR(INDEX(BASE!$R$6:$R$1740,MATCH(ROWS($A$113:$A114),BASE!$Q$6:$Q$1740,0)),"") -> VRAI DOUBLON
A115: =IFERROR(INDEX(BASE!$B$6:$B$1740,MATCH(ROWS($A$113:$A115),BASE!$Q$6:$Q$1740,0)),"") -> AI | B115: =IFERROR(INDEX(BASE!$A$6:$A$1740,MATCH(ROWS($A$113:$A115),BASE!$Q$6:$Q$1740,0)),"") -> 02/09/2026 | D115: =IFERROR(INDEX(BASE!$C$6:$C$1740,MATCH(ROWS($A$113:$A115),BASE!$Q$6:$Q$1740,0)),"") -> AI148 | F115: =IFERROR(INDEX(BASE!$E$6:$E$1740,MATCH(ROWS($A$113:$A115),BASE!$Q$6:$Q$1740,0)),"") -> AC487587 | H115: =IFERROR(INDEX(BASE!$P$6:$P$1740,MATCH(ROWS($A$113:$A115),BASE!$Q$6:$Q$1740,0)),"") -> 2 | I115: =IFERROR(INDEX(BASE!$R$6:$R$1740,MATCH(ROWS($A$113:$A115),BASE!$Q$6:$Q$1740,0)),"") -> VRAI DOUBLON
A116: =IFERROR(INDEX(BASE!$B$6:$B$1740,MATCH(ROWS($A$113:$A116),BASE!$Q$6:$Q$1740,0)),"") -> AI | B116: =IFERROR(INDEX(BASE!$A$6:$A$1740,MATCH(ROWS($A$113:$A116),BASE!$Q$6:$Q$1740,0)),"") -> 03/09/2026 | D116: =IFERROR(INDEX(BASE!$C$6:$C$1740,MATCH(ROWS($A$113:$A116),BASE!$Q$6:$Q$1740,0)),"") -> AI148 | F116: =IFERROR(INDEX(BASE!$E$6:$E$1740,MATCH(ROWS($A$113:$A116),BASE!$Q$6:$Q$1740,0)),"") -> AC552692 | H116: =IFERROR(INDEX(BASE!$P$6:$P$1740,MATCH(ROWS($A$113:$A116),BASE!$Q$6:$Q$1740,0)),"") -> 2 | I116: =IFERROR(INDEX(BASE!$R$6:$R$1740,MATCH(ROWS($A$113:$A116),BASE!$Q$6:$Q$1740,0)),"") -> LÉGITIME
A117: =IFERROR(INDEX(BASE!$B$6:$B$1740,MATCH(ROWS($A$113:$A117),BASE!$Q$6:$Q$1740,0)),"") -> AI | B117: =IFERROR(INDEX(BASE!$A$6:$A$1740,MATCH(ROWS($A$113:$A117),BASE!$Q$6:$Q$1740,0)),"") -> 03/09/2026 | D117: =IFERROR(INDEX(BASE!$C$6:$C$1740,MATCH(ROWS($A$113:$A117),BASE!$Q$6:$Q$1740,0)),"") -> AI148 | F117: =IFERROR(INDEX(BASE!$E$6:$E$1740,MATCH(ROWS($A$113:$A117),BASE!$Q$6:$Q$1740,0)),"") -> AC552694 | H117: =IFERROR(INDEX(BASE!$P$6:$P$1740,MATCH(ROWS($A$113:$A117),BASE!$Q$6:$Q$1740,0)),"") -> 2 | I117: =IFERROR(INDEX(BASE!$R$6:$R$1740,MATCH(ROWS($A$113:$A117),BASE!$Q$6:$Q$1740,0)),"") -> LÉGITIME
A118: =IFERROR(INDEX(BASE!$B$6:$B$1740,MATCH(ROWS($A$113:$A118),BASE!$Q$6:$Q$1740,0)),"") -> AI | B118: =IFERROR(INDEX(BASE!$A$6:$A$1740,MATCH(ROWS($A$113:$A118),BASE!$Q$6:$Q$1740,0)),"") -> 03/09/2026 | D118: =IFERROR(INDEX(BASE!$C$6:$C$1740,MATCH(ROWS($A$113:$A118),BASE!$Q$6:$Q$1740,0)),"") -> AI148 | F118: =IFERROR(INDEX(BASE!$E$6:$E$1740,MATCH(ROWS($A$113:$A118),BASE!$Q$6:$Q$1740,0)),"") -> AC552722 | H118: =IFERROR(INDEX(BASE!$P$6:$P$1740,MATCH(ROWS($A$113:$A118),BASE!$Q$6:$Q$1740,0)),"") -> 2 | I118: =IFERROR(INDEX(BASE!$R$6:$R$1740,MATCH(ROWS($A$113:$A118),BASE!$Q$6:$Q$1740,0)),"") -> LÉGITIME
A119: =IFERROR(INDEX(BASE!$B$6:$B$1740,MATCH(ROWS($A$113:$A119),BASE!$Q$6:$Q$1740,0)),"") -> AI | B119: =IFERROR(INDEX(BASE!$A$6:$A$1740,MATCH(ROWS($A$113:$A119),BASE!$Q$6:$Q$1740,0)),"") -> 03/09/2026 | D119: =IFERROR(INDEX(BASE!$C$6:$C$1740,MATCH(ROWS($A$113:$A119),BASE!$Q$6:$Q$1740,0)),"") -> AI148 | F119: =IFERROR(INDEX(BASE!$E$6:$E$1740,MATCH(ROWS($A$113:$A119),BASE!$Q$6:$Q$1740,0)),"") -> AC552723 | H119: =IFERROR(INDEX(BASE!$P$6:$P$1740,MATCH(ROWS($A$113:$A119),BASE!$Q$6:$Q$1740,0)),"") -> 2 | I119: =IFERROR(INDEX(BASE!$R$6:$R$1740,MATCH(ROWS($A$113:$A119),BASE!$Q$6:$Q$1740,0)),"") -> LÉGITIME
A120: =IFERROR(INDEX(BASE!$B$6:$B$1740,MATCH(ROWS($A$113:$A120),BASE!$Q$6:$Q$1740,0)),"") -> AI | B120: =IFERROR(INDEX(BASE!$A$6:$A$1740,MATCH(ROWS($A$113:$A120),BASE!$Q$6:$Q$1740,0)),"") -> 03/09/2026 | D120: =IFERROR(INDEX(BASE!$C$6:$C$1740,MATCH(ROWS($A$113:$A120),BASE!$Q$6:$Q$1740,0)),"") -> AI148 | F120: =IFERROR(INDEX(BASE!$E$6:$E$1740,MATCH(ROWS($A$113:$A120),BASE!$Q$6:$Q$1740,0)),"") -> AC552724 | H120: =IFERROR(INDEX(BASE!$P$6:$P$1740,MATCH(ROWS($A$113:$A120),BASE!$Q$6:$Q$1740,0)),"") -> 2 | I120: =IFERROR(INDEX(BASE!$R$6:$R$1740,MATCH(ROWS($A$113:$A120),BASE!$Q$6:$Q$1740,0)),"") -> LÉGITIME
A121: =IFERROR(INDEX(BASE!$B$6:$B$1740,MATCH(ROWS($A$113:$A121),BASE!$Q$6:$Q$1740,0)),"") -> SK | B121: =IFERROR(INDEX(BASE!$A$6:$A$1740,MATCH(ROWS($A$113:$A121),BASE!$Q$6:$Q$1740,0)),"") -> 04/09/2026 | D121: =IFERROR(INDEX(BASE!$C$6:$C$1740,MATCH(ROWS($A$113:$A121),BASE!$Q$6:$Q$1740,0)),"") -> SK568 | F121: =IFERROR(INDEX(BASE!$E$6:$E$1740,MATCH(ROWS($A$113:$A121),BASE!$Q$6:$Q$1740,0)),"") -> AF286191 | H121: =IFERROR(INDEX(BASE!$P$6:$P$1740,MATCH(ROWS($A$113:$A121),BASE!$Q$6:$Q$1740,0)),"") -> 2 | I121: =IFERROR(INDEX(BASE!$R$6:$R$1740,MATCH(ROWS($A$113:$A121),BASE!$Q$6:$Q$1740,0)),"") -> VRAI DOUBLON
A122: =IFERROR(INDEX(BASE!$B$6:$B$1740,MATCH(ROWS($A$113:$A122),BASE!$Q$6:$Q$1740,0)),"") -> JU | B122: =IFERROR(INDEX(BASE!$A$6:$A$1740,MATCH(ROWS($A$113:$A122),BASE!$Q$6:$Q$1740,0)),"") -> 06/09/2026 | D122: =IFERROR(INDEX(BASE!$C$6:$C$1740,MATCH(ROWS($A$113:$A122),BASE!$Q$6:$Q$1740,0)),"") -> JU241 | F122: =IFERROR(INDEX(BASE!$E$6:$E$1740,MATCH(ROWS($A$113:$A122),BASE!$Q$6:$Q$1740,0)),"") -> XH965947 | H122: =IFERROR(INDEX(BASE!$P$6:$P$1740,MATCH(ROWS($A$113:$A122),BASE!$Q$6:$Q$1740,0)),"") -> 2 | I122: =IFERROR(INDEX(BASE!$R$6:$R$1740,MATCH(ROWS($A$113:$A122),BASE!$Q$6:$Q$1740,0)),"") -> STATUT DIFFÉRENT
A123: =IFERROR(INDEX(BASE!$B$6:$B$1740,MATCH(ROWS($A$113:$A123),BASE!$Q$6:$Q$1740,0)),"") -> AI | B123: =IFERROR(INDEX(BASE!$A$6:$A$1740,MATCH(ROWS($A$113:$A123),BASE!$Q$6:$Q$1740,0)),"") -> 13/09/2026 | D123: =IFERROR(INDEX(BASE!$C$6:$C$1740,MATCH(ROWS($A$113:$A123),BASE!$Q$6:$Q$1740,0)),"") -> AI142 | F123: =IFERROR(INDEX(BASE!$E$6:$E$1740,MATCH(ROWS($A$113:$A123),BASE!$Q$6:$Q$1740,0)),"") -> AI753335 | H123: =IFERROR(INDEX(BASE!$P$6:$P$1740,MATCH(ROWS($A$113:$A123),BASE!$Q$6:$Q$1740,0)),"") -> 2 | I123: =IFERROR(INDEX(BASE!$R$6:$R$1740,MATCH(ROWS($A$113:$A123),BASE!$Q$6:$Q$1740,0)),"") -> VRAI DOUBLON
A124: =IFERROR(INDEX(BASE!$B$6:$B$1740,MATCH(ROWS($A$113:$A124),BASE!$Q$6:$Q$1740,0)),"") -> AI | B124: =IFERROR(INDEX(BASE!$A$6:$A$1740,MATCH(ROWS($A$113:$A124),BASE!$Q$6:$Q$1740,0)),"") -> 13/09/2026 | D124: =IFERROR(INDEX(BASE!$C$6:$C$1740,MATCH(ROWS($A$113:$A124),BASE!$Q$6:$Q$1740,0)),"") -> AI142 | F124: =IFERROR(INDEX(BASE!$E$6:$E$1740,MATCH(ROWS($A$113:$A124),BASE!$Q$6:$Q$1740,0)),"") -> AI750382 | H124: =IFERROR(INDEX(BASE!$P$6:$P$1740,MATCH(ROWS($A$113:$A124),BASE!$Q$6:$Q$1740,0)),"") -> 2 | I124: =IFERROR(INDEX(BASE!$R$6:$R$1740,MATCH(ROWS($A$113:$A124),BASE!$Q$6:$Q$1740,0)),"") -> VRAI DOUBLON
... A150: =IFERROR(INDEX(BASE!$B$6:$B$1740,MATCH(ROWS($A$113:$A150),BASE!$Q$6:$Q$1740,0)),"") | B150: =IFERROR(INDEX(BASE!$A$6:$A$1740,MATCH(ROWS($A$113:$A150),BASE!$Q$6:$Q$1740,0)),"") | D150: =IFERROR(INDEX(BASE!$C$6:$C$1740,MATCH(ROWS($A$113:$A150),BASE!$Q$6:$Q$1740,0)),"") | F150: =IFERROR(INDEX(BASE!$E$6:$E$1740,MATCH(ROWS($A$113:$A150),BASE!$Q$6:$Q$1740,0)),"") | H150: =IFERROR(INDEX(BASE!$P$6:$P$1740,MATCH(ROWS($A$113:$A150),BASE!$Q$6:$Q$1740,0)),"") | I150: =IFERROR(INDEX(BASE!$R$6:$R$1740,MATCH(ROWS($A$113:$A150),BASE!$Q$6:$Q$1740,0)),"")

Sheet DOSSIERS
A1: ALYZIA | DOSSIERS
A3: COMPTE RENDU DE SUPERVISION • SEPTEMBRE 2026 • TOUTES COMPAGNIES
A4: FILTRES EXCEL ▼ • Sélectionnez DATE, CIE, N° VOL, N° TAG ou STATUT dans les en-têtes. Toutes les journées sont regroupées ici.
A5: DATE | B5: CIE | C5: N° VOL | D5: HEURE DÉPART | E5: N° TAG | F5: NOMBRE BAGAGES | G5: VOL APPORT | H5: HEURE ARRIVÉE | I5: LOCALISATION | J5: REMARQUES | K5: ANOMALIE | L5: COMMENTAIRE/ACTION | M5: STATUT | N5: FAULT STATION
A6: 01/09/2026 | B6: AI | C6: AI148 | D6: 12:45 | E6: AC384224 | F6: 1 | G6: AC870 | H6: 10:08 | I6: ONLY BSM | L6: AUCUNE INJ SUR CDG / CHECK DONE AVEC GEH IDEM BAGS NON LISTE SUR LEUR LOAD SHEET AC870/31AUG//AHL DELAI 26474 | M6: NON CHARGÉ | N6: 21 - Bag left at station origin / correctly labelled
A7: 01/09/2026 | B7: AI | C7: AI148 | D7: 12:45 | E7: AC384225 | F7: 1 | G7: AC870 | H7: 10:08 | I7: ONLY BSM | L7: AUCUNE INJ SUR CDG / CHECK DONE AVEC GEH IDEM BAGS NON LISTE SUR LEUR LOAD SHEET AC870/31AUG//AHL DELAI 26474 | M7: NON CHARGÉ | N7: 21 - Bag left at station origin / correctly labelled
A8: 01/09/2026 | B8: AI | C8: AI142 | D8: 20:45 | E8: AF027425 | F8: 1 | G8: AF0009 | H8: 12:29 | I8: TBM DEPOSE HF DEPUIS 14H01 | K8: PAS DE MVT 18H55 | L8: PRIS EN CHARGE PAR BAGRUNNER ET DEPOSE SUR LA JETEE DEPART A 19H01 | M8: SAUVÉ
A9: 01/09/2026 | B9: AI | C9: AI142 | D9: 20:45 | E9: LO394849 | F9: 1 | G9: LO335 | H9: 19:02 | I9: T2C EJECTION C04 19H56 | K9: HOT CNX | L9: APPEL SUP GALERIE T2 A 20H06 ET SIGNALE POUR LE RECUPERER | M9: SAUVÉ
A10: 01/09/2026 | B10: AI | C10: AI142 | D10: 20:45 | E10: LO394856 | F10: 1 | G10: LO335 | H10: 19:02 | I10: T2C EJECTION C04 19H49 | K10: HOT CNX | L10: APPEL SUP GALERIE T2 A 20H06 ET SIGNALE POUR LE RECUPERER | M10: SAUVÉ
A11: 01/09/2026 | B11: AI | C11: AI142 | D11: 20:45 | E11: AF065477 | F11: 1 | G11: AF1159 | H11: 18:57 | I11: T2C INJECTION 19H54 | K11: PAS DE MVT 20H06 | L11: APPEL SUP GALERIE T2 A 20H06/DEMANDE DE VERIFIER EN REBUT DU C/BAG TROUVE EN REBUT C05 | M11: SAUVÉ
A12: 01/09/2026 | B12: AI | C12: AI142 | D12: 20:45 | E12: AF065418 | F12: 1 | G12: AF1159 | H12: 18:57 | I12: T2C EJECTION C04 19H56 | K12: HOT CNX | L12: APPEL SUP GALERIE T2 A 20H06 ET SIGNALE POUR LE RECUPERER | M12: SAUVÉ
A13: 01/09/2026 | B13: AT | C13: AT639 | D13: 22:00 | E13: AT844406 | F13: 1 | G13: LOCAL | I13: AUCUNE TRACE 21H20 | K13: BSM CREATION 20H31 | L13: APPEL LEADER AT A 21H20 CAR AUCUNE TRACE DU BAG/INJECTE SUITE A NOTRE APPEL/APPEL SUP GAL T2 A 21H30 ET SIGNALE QUE BAGS SUR TAPIS B01 | M13: SAUVÉ
A14: 01/09/2026 | B14: AT | C14: AT639 | D14: 22:00 | E14: AT844408 | F14: 1 | G14: LOCAL | I14: AUCUNE TRACE 21H20 | K14: BSM CREATION 20H31 | L14: APPEL LEADER AT A 21H20 CAR AUCUNE TRACE DU BAG/INJECTE SUITE A NOTRE APPEL/APPEL SUP GAL T2 A 21H30 ET SIGNALE QUE BAGS SUR TAPIS B01 | M14: SAUVÉ
A15: 01/09/2026 | B15: AT | C15: AT639 | D15: 22:00 | E15: AT844125 | F15: 1 | G15: LOCAL | I15: T2B CHECK IN BANQUE 25 20H06 | J15: HBAG | K15: BSM CREATION 20H06 | L15: APPEL LEADER AT A 21H20 CAR AUCUNE TRACE DU BAG/DIT QU'IL S'AGIT D'UN BAG CABINE SUREMENT PRIS A BORD PAR PAX | M15: CHARGÉ
A16: 01/09/2026 | B16: AV | C16: AV55 | D16: 08:55 | E16: AF878238 | F16: 1 | G16: AF1043/31AUG | H16: 21:51 | I16: TME HF 22H33 | K16: PAS DE MVT | L16: VU AVEC PILOTE AF 06H57/ APPEL GTB 07H00 PR VERIF INFRA/ TJS A CE NIVEAU VA ETRE DEPOSE AU TBM | M16: SAUVÉ
A17: 01/09/2026 | B17: AV | C17: AV55 | D17: 08:55 | E17: AF878043 | F17: 1 | G17: AF1043/31AUG | H17: 21:51 | I17: PAS DE LOC | K17: PAS DE LOC | L17: BIKE / VU AVEC PILOTE AF 06H57/ APPEL GTB 07H00 PR VERIF INFRA/ NEG / NEG QSE/ NEG A18/ NEG TBM/ NEG SBA//J+1 AHL PEIAV31185 | M17: NON CHARGÉ | N17: 54 - Interline bags not made available by inbound carrier per local agreement
A18: 01/09/2026 | B18: DE | C18: DE4264 | D18: 11:10 | E18: MK609826 | F18: 1 | G18: UNK | I18: 2E VERS TBM | K18: PAS DE MVT | L18: COB ADP CTC PR PREVENIR/DMD INTERVENTION BAGRUNNER 09H56 | M18: SAUVÉ
A19: 01/09/2026 | B19: DE | C19: DE4264 | D19: 11:10 | E19: MK609825 | F19: 1 | G19: UNK | I19: 2E VERS TBM | K19: PAS DE MVT | L19: COB ADP CTC PR PREVENIR/DMD INTERVENTION BAGRUNNER 09H57 | M19: SAUVÉ
A20: 01/09/2026 | B20: DE | C20: DE4264 | D20: 11:10 | E20: MK609827 | F20: 1 | G20: MK14 | H20: 08:20 | I20: PAS DE LOC//1ER LOC 16H08 2F | K20: 2F RETARD TRAITEMENT | L20: NEG TOUS SYSTEMES//J+1 AHL SEADE14645 | M20: NON CHARGÉ | N20: 53 - Interline MCT not available ( MCT initialement OK)
A21: 01/09/2026 | B21: DE | C21: DE4214 | D21: 16:45 | E21: DE372126 | F21: 1 | G21: LOCAL | I21: T3 EJECTION | L21: APPEL GALLERIE T3 16H02 / RETOUR CONFIRMANT QUE PLUS DE LOCAUX RESTANTS SUR JETEE DEPART | M21: CHARGÉ
A22: 01/09/2026 | B22: EI | C22: EI527 | D22: 17:00 | E22: EI129754 | F22: 1 | G22: RUSH | I22: AUCUNE TRACE | K22: BSM ONLY | L22: APPEL DIRBY T1 A 16H41 MAIS INJOIGNABLE | M22: NON CHARGÉ | N22: 21 - Bag left at station origin / correctly labelled
A23: 01/09/2026 | B23: EI | C23: EI527 | D23: 17:00 | E23: EI129755 | F23: 1 | G23: RUSH | I23: AUCUNE TRACE | K23: BSM ONLY | L23: APPEL DIRBY T1 A 16H41 MAIS INJOIGNABLE | M23: NON CHARGÉ | N23: 21 - Bag left at station origin / correctly labelled
A24: 01/09/2026 | B24: EI | C24: EI527 | D24: 17:00 | E24: EI129756 | F24: 1 | G24: RUSH | I24: AUCUNE TRACE | K24: BSM ONLY | L24: APPEL DIRBY T1 A 16H41 MAIS INJOIGNABLE | M24: NON CHARGÉ | N24: 21 - Bag left at station origin / correctly labelled
A25: 01/09/2026 | B25: EI | C25: EI527 | D25: 17:00 | E25: EI129757 | F25: 1 | G25: RUSH | I25: AUCUNE TRACE | K25: BSM ONLY | L25: APPEL DIRBY T1 A 16H41 MAIS INJOIGNABLE | M25: NON CHARGÉ | N25: 21 - Bag left at station origin / correctly labelled
A26: 01/09/2026 | B26: FI | C26: FI543 | D26: 14:00 | E26: LY872771 | F26: 1 | G26: LY221 | H26: 11:29 | I26: 2D HORS FORMAT | L26: APPEL TMB EN SLB 12H45 POUR DEMANDE A FAIRE DESCENDRE LE TRANSIT / RECU EN 2D HORS FORMAT H-15MN TOO LATE FWD FI547/01SEP | M26: NON CHARGÉ | N26: 54 - Interline bags not made available by inbound carrier per local agreement
A27: 01/09/2026 | B27: FI | C27: FI543 | D27: 14:00 | E27: LY872382 | F27: 1 | G27: LY221 | H27: 11:29 | I27: T2B EJECTION | L27: ENVOI BAG RUNNER CHECK DONE AU 2B MAIS PAS DE BAG VUE 12H45+13H00//AHL KEFFI16680 | M27: NON CHARGÉ | N27: 21 - Bag left at station origin / correctly labelled
A28: 01/09/2026 | B28: FI | C28: FI543 | D28: 14:00 | E28: AF040653 | F28: 1 | G28: AF7363 | I28: T1 HORS DFORMAT | K28: REFUSE PAR COORDO | L28: BAG NON CHARGE PAS DE RAISON RECU MAIS REFUSE PAR COORDO / SIZING OU CONDITIONNEMENT//FWD FI547/01SEP | M28: NON CHARGÉ | N28: 63 - Airport security
A29: 01/09/2026 | B29: FI | C29: FI543 | D29: 14:00 | E29: AF040488 | F29: 1 | G29: AF7363 | H29: 11:22 | I29: TBM T1-T2 | K29: RECU TARDIF | L29: PERTE DE TRACE APRES 2E TRI 11H47 / CHARGE EN NAVETTE TBM 14H08 POUR DEPOSE SAT 1 TOO LATE //FWD FI547/01SEP | M29: NON CHARGÉ | N29: 54 - Interline bags not made available by inbound carrier per local agreement
A30: 01/09/2026 | B30: FI | C30: FI547 | D30: 17:15 | E30: AF045927 | F30: 1 | G30: AF1179 | H30: 14:52 | I30: T1 EJECTION SJ06 16H50 | K30: HOT CNX | L30: APPEL GALERIE T1 A 18H00 ET SIGNALE | M30: SAUVÉ
A31: 01/09/2026 | B31: FI | C31: FI547 | D31: 17:15 | E31: G3268359 | F31: 1 | G31: AF0459 | H31: 11:42 | I31: CARROUSEL ARRIVEE 32 A 12H18 | K31: 2E SLB T2E 18H50 | L31: APPEL SALON AF 2E A 17H45/DMD SI BAG P/UP PAR PAX/NEG/RAPPEL AF 2E 18H57/DMD D'INJECTER LE BAG/APPEL GAL T1 20H32 ET SIGNALE EN WJ41 /RAPPEL 21H231 | M31: SAUVÉ
A32: 01/09/2026 | B32: JU | C32: JU241 | D32: 10:00 | E32: AF894926 | F32: 1 | G32: AF4199 | I32: TBM NAVETTE 09H59 | K32: RETARD TRAITEMENT | L32: TROP TARD PR INTERVENIR //J+1 AHL BEGJU36836 FWD JU241/02SEP | M32: NON CHARGÉ | N32: 64 - Unserviceable equipment / belt / sortation system
A33: 01/09/2026 | B33: JU | C33: JU243 | D33: 20:35 | E33: AA180770 | F33: 1 | G33: AA0042 | H33: 06:46 | I33: RUSH /2A HORS FORMAT 18H48 | K33: DEPOSE AU MAUVAIS ENDROIT | L33: SEULE TRACE APPARUE AU 2A HORS FORMAT A 18H48/ENVOI BAGRUNNER POUR VERIFIER A 19H56/NEG AU HF ET CYNO 2A | M33: NON CHARGÉ | N33: 21 - Bag left at station origin / correctly labelled
A34: 01/09/2026 | B34: LA | C34: LA8133 | D34: 13:00 | E34: LA327427 | F34: 1 | G34: LOCAL | I34: ONLY BSM | L34: POSSIBLE CABIN BAG / ENVOI BAG RUNNER POST DEPART 13H05 POUR VERIF T2C//J+1 PAS DE DOSSIER | M34: CHARGÉ
A35: 01/09/2026 | B35: RJ | C35: RJ118 | D35: 15:50 | E35: SK144375 | F35: 1 | G35: SK837 | H35: 11:59 | I35: TBM MC80 | L35: CONFIRME PAR AGENT TBM + AGENT PISTE BAG CERTAINEMENT CHARGE SANS SCAN / //J+1 FWD RJ118/02SEP | M35: NON CHARGÉ | N35: 63 - Airport security
A36: 01/09/2026 | B36: SK | C36: SK574 | D36: 10:30 | E36: AF881381 | F36: 1 | G36: AF345 | H36: 07:42 | I36: PAS DE LOC | K36: PAS DE LOC | L36: APPEL TBM80 10H01 POUR DEPOSER SOUS BORD | M36: SAUVÉ
A37: 01/09/2026 | B37: SK | C37: SK574 | D37: 10:30 | E37: AF012090 | F37: 1 | G37: AF345 | I37: PAS DE LOC | K37: PAS DE LOC | L37: NEG TOUS SYSTEMES //J+1 AHL ARNSK28352 | M37: NON CHARGÉ | N37: 21 - Bag left at station origin / correctly labelled
A38: 01/09/2026 | B38: SK | C38: SK566 | D38: 11:15 | E38: AF880683 | F38: 1 | G38: AF4199 | I38: DECHARGE NAVETTE 10H47 | K38: PAS DE MVT | L38: APPEL TBM80 11H01 PR SAVOIR OU ONT ÉTÉ DEPOSE LES BAGS/ PAS DE REPONSE DE LA GALERIE/ COORDO CONFIRME NE RIEN AVOIR SS BORD//FWD SK560/SK1273/01SEP | M38: NON CHARGÉ | N38: 54 - Interline bags not made available by inbound carrier per local agreement
A39: 01/09/2026 | B39: SK | C39: SK566 | D39: 11:15 | E39: AF883560 | F39: 1 | G39: AF4199 | I39: DECHARGE NAVETTE 10H47 | K39: PAS DE MVT | L39: APPEL TBM80 11H01 PR SAVOIR OU ONT ÉTÉ DEPOSE LES BAGS/ PAS DE REPONSE DE LA GALERIE/ COORDO CONFIRME NE RIEN AVOIR SS BORD FWD SK560/01SEP | M39: NON CHARGÉ | N39: 54 - Interline bags not made available by inbound carrier per local agreement
A40: 01/09/2026 | B40: SK | C40: SK566 | D40: 11:15 | E40: AF883636 | F40: 1 | G40: AF4199 | I40: DECHARGE NAVETTE 10H47 | K40: PAS DE MVT | L40: APPEL TBM80 11H01 PR SAVOIR OU ONT ÉTÉ DEPOSE LES BAGS/ PAS DE REPONSE DE LA GALERIE/ COORDO CONFIRME NE RIEN AVOIR SS BORD FWD SK560/01SEP | M40: NON CHARGÉ | N40: 54 - Interline bags not made available by inbound carrier per local agreement
A41: 01/09/2026 | B41: SK | C41: SK566 | D41: 11:15 | E41: AM294092 | F41: 1 | G41: AM44 | H41: 09:03 | I41: DECHARGE NAVETTE 10H47 | K41: PAS DE MVT | L41: APPEL TBM80 11H01 PR SAVOIR OU ONT ÉTÉ DEPOSE LES BAGS/ PAS DE REPONSE DE LA GALERIE/ COORDO CONFIRME NE RIEN AVOIR SS BORD FWD SK560/01SEP | M41: NON CHARGÉ | N41: 54 - Interline bags not made available by inbound carrier per local agreement
A42: 01/09/2026 | B42: SK | C42: SK566 | D42: 11:15 | E42: AF894421 | F42: 1 | G42: AF4199 | I42: EJECTION TBM80 10H24 | K42: PAS DE MVT | L42: APPEL TBM80 11H01 PR SAVOIR OU ONT ÉTÉ DEPOSE LES BAGS/ PAS DE REPONSE DE LA GALERIE/ COORDO CONFIRME NE RIEN AVOIR SS BORD//FWD SK560/SK1273/01SEP | M42: NON CHARGÉ | N42: 54 - Interline bags not made available by inbound carrier per local agreement
A43: 01/09/2026 | B43: SK | C43: SK834 | D43: 12:20 | E43: AF883973 | F43: 1 | G43: AF703 | I43: TBM80 11H49 | L43: APPEL TBM80 / PAS DE REPONSE/ GALERIE PAS DE REPONSE/ BAG RUNNER N A PAS TROUVE AU TBM | M43: CHARGÉ
A44: 01/09/2026 | B44: SK | C44: SK834 | D44: 12:20 | E44: LH739429 | F44: 1 | G44: AF099 | H44: 05:34 | I44: ONLY BSM | K44: REROUTED BAG | L44: AUCUNE INJ SUR CDG / IDEM DIRBY NEG PAS A LEUR NIVEAU J+1 PAS DE DOSSIER | M44: NON CHARGÉ | N44: 21 - Bag left at station origin / correctly labelled
A45: 01/09/2026 | B45: SK | C45: SK568 | D45: 14:00 | E45: AF893394 | F45: 1 | G45: AF0091 | H45: 10:35 | I45: ONLY BSM | L45: PAS D INJ SUR CDG / NEG REQUETEUR + BAG RADAR / POSSIBLE CABIN BAG //J+1 PAS DE DOSISIER SUREMENT PRIS EN PORTE | M45: CHARGÉ
A46: 01/09/2026 | B46: SK | C46: SK568 | D46: 14:00 | E46: DL893979 | F46: 1 | I46: ONLY BSM | J46: RRTE | L46: X 2 BAGS PAS D INJECTION SUR CDG / NEG REQUETEUR + BAG RADAR / VOL D APPORT NON CONNU//+J1 PAS DE DOSSIER | M46: NON CHARGÉ | N46: 21 - Bag left at station origin / correctly labelled
A47: 01/09/2026 | B47: SK | C47: SK568 | D47: 14:00 | E47: DL992699 | F47: 1 | I47: ONLY BSM | J47: RRTE | L47: X 2 BAGS PAS D INJECTION SUR CDG / NEG REQUETEUR + BAG RADAR / VOL D APPORT NON CONNU//+J1 PAS DE DOSSIER | M47: NON CHARGÉ | N47: 21 - Bag left at station origin / correctly labelled
A48: 01/09/2026 | B48: SK | C48: SK568 | D48: 14:00 | E48: LA113911 | F48: 1 | G48: AF459 | H48: 11:42 | I48: ONLY BSM | K48: REROUTED BAGS | L48: X 2 BAGS PAS DINJ SUR CDG / RIEN LOCALISE AU T2C //J+1 AHL CPHSK47497 | M48: NON CHARGÉ | N48: 21 - Bag left at station origin / correctly labelled
A49: 01/09/2026 | B49: SK | C49: SK568 | D49: 14:00 | E49: LA113912 | F49: 1 | G49: AF459 | H49: 11:42 | I49: ONLY BSM | K49: REROUTED BAGS | L49: X2 BAGS PAS DINJ SUR CDG / IDEM RIEN RESTANT AU T2C//J+1 AHL CPHSK47497 | M49: NON CHARGÉ | N49: 21 - Bag left at station origin / correctly labelled
A50: 01/09/2026 | B50: SK | C50: SK836 | D50: 20:30 | E50: LA114861 | F50: 1 | G50: LA8132 | H50: 10:50 | I50: T2C TRI SECURISATION 13H04 | K50: PAS DE MVT 17H45 | L50: APPEL AGENT LL TMB MNB 2A A 18H18/BAG EN A18/DEMANDE DE LE DEPOSER SUR LE VOL | M50: SAUVÉ
A51: 01/09/2026 | B51: SK | C51: SK580 | D51: 20:10 | E51: AF016127 | F51: 1 | G51: AF0531 | H51: 16:56 | I51: JETEE 113 CYNO 17H55 | K51: PAS DE MVT 18H58 | L51: APPEL LA JETEE 113 A 18H58/DEMANDE DE LE DEPOSER AU TBM/PRIS EN CHARGE PAR BAGRUNNER 19H08 ET DEPOSE SUR LA JETEE DEPART A 19H19 | M51: SAUVÉ
A52: 01/09/2026 | B52: SK | C52: SK560 | D52: 20:15 | E52: SK171324 | F52: 1 | G52: LOCAL | I52: JETEE 2B 18H45 | K52: REFUS/BAG INACTIF | L52: APPEL LEADER SK A 18H49 ET DEMANDE D'ACTIVER LE TAG | M52: SAUVÉ
A53: 01/09/2026 | B53: SK | C53: SK836 | D53: 20:30 | E53: AF064046 | F53: 1 | G53: AF7339 | H53: 16:55 | I53: TBM MC80 18H36 | K53: DECHARGE MAIS STILL TBM | L53: PRIS EN CHARGE PAR BAGRUNNER A 19H08 ET DEPOSE SUR LA JETEE DEPART A 19H12 | M53: SAUVÉ
A54: 01/09/2026 | B54: SK | C54: SK580 | D54: 20:10 | E54: SK171276 | F54: 1 | G54: LOCAL | I54: 2B HORS FORMAT 18H26 | K54: PAS DE MVT | L54: ENVOI BAGRUNNER A 19H20 POUR VERIFIER/SIGNALE A L'AGENT CHARGE DU DEPART | M54: SAUVÉ
A55: 01/09/2026 | B55: SK | C55: SK580 | D55: 20:10 | E55: SK173563 | F55: 1 | G55: LOCAL | I55: 2B HORS FORMAT 18H40 | K55: PAS DE MVT | L55: ENVOI BAGRUNNER A 19H20 POUR VERIFIER/SIGNALE A L'AGENT CHARGE DU DEPART | M55: SAUVÉ
A56: 01/09/2026 | B56: SK | C56: SK580 | D56: 20:10 | E56: XH965526 | F56: 1 | G56: RUSH | I56: T2B EJECTION B02 16H44 | K56: PAS DE MVT | L56: ENVOI BAGRUNNER A 19H20 POUR VERIF/SIGNALE A L'AGENT GAL DEPART/RUSH TROUVE AU 2D HF 19H50/CHARGE ET DECHARGE PAR LA PISTE/RAISON INCONNUE | M56: NON CHARGÉ | N56: 21 - Bag left at station origin / correctly labelled
A57: 01/09/2026 | B57: SK | C57: SK560 | D57: 20:15 | E57: SK174151 | F57: 1 | G57: LOCAL | I57: T2B EJECTION B02 19H10 | K57: PAS DE MVT | L57: BAG SIGNALE PAR BAGRUNNER A 19H18 A L'AGENT GAL DU VOL POUR LE RECUPERER | M57: SAUVÉ
A58: 01/09/2026 | B58: AT | C58: AT639 | D58: 22:00 | E58: AT844408 | F58: 1 | G58: LOCAL | I58: AUCUNE TRACE 21H20 | K58: BSM CREATION 20H31 | L58: APPEL LEADER AT A 21H20 CAR AUCUNE TRACE DU BAG/INJECTE SUITE A NOTRE APPEL/APPEL SUP GAL T2 A 21H30 ET SIGNALE QUE BAGS SUR TAPIS B01 | M58: SAUVÉ
A59: 01/09/2026 | B59: AT | C59: AT639 | D59: 22:00 | E59: AT844125 | F59: 1 | G59: LOCAL | I59: T2B CHECK IN BANQUE 25 20H06 | J59: HBAG | K59: BSM CREATION 20H06 | L59: APPEL LEADER AT A 21H20 CAR AUCUNE TRACE DU BAG/DIT QU'IL S'AGIT D'UN BAG CABINE SUREMENT PRIS A BORD PAR PAX/ | M59: CHARGÉ
A60: 02/09/2026 | B60: AI | C60: AI148 | D60: 12:45 | E60: AC467770 | F60: 1 | G60: AC874 | H60: 07:19 | I60: PAS DE LOC | K60: PAS DE LOC | L60: VERIF AVC AC/ PAS DE TRACE O/B/ SOIT PAS A CDG SOIT HORS FORMAT PAS SCANNE/J+1 MISCNX A YUL/ DELAI26499 FO AC895/AC42/02SEP | M60: NON CHARGÉ | N60: 56 - Online - own carrier - MCT not available
A61: 02/09/2026 | B61: AI | C61: AI148 | D61: 12:45 | E61: AC476231 | F61: 1 | G61: AC870 | H61: 10:25 | I61: PAS DE LOC | K61: PAS DE LOC | L61: VERIF AVC AC/ PAS DE TRACE O/B/ HF 2A 12H48/ PROBABLE DECHARGE EN SLB/ RECUP ET DEPOSE LL/J+1 DELAI26504 FO AI142/02SEP | M61: NON CHARGÉ | N61: 41 - Delivered to wrong area
A62: 02/09/2026 | B62: AI | C62: AI148 | D62: 12:45 | E62: AC479302 | F62: 1 | G62: AC870 | H62: 10:25 | I62: PAS DE LOC | K62: PAS DE LOC | L62: VERIF AVC EH/ PAS DE TRACE DE CHARGEMENT SUR AC /J+1 DELAI26506 AUCUNE LOCALISATION SUR CDG | M62: NON CHARGÉ | N62: 21 - Bag left at station origin / correctly labelled
A63: 02/09/2026 | B63: AI | C63: AI148 | D63: 12:45 | E63: AC463822 | F63: 1 | G63: AC874 | H63: 07:19 | I63: DECHARGE NAVETTE | K63: ERREUR DE TRAITEMENT | L63: PAS DE NAVETTE PR LE 2C/ ENVOI BAG RUNNER VERIF →TBM →A →C 12H11/ PLUS DE TRACE JUSQU A 17H53 BAG PRESENTE SUR LE VOL AI142 /J+1 DELAI26501 EN ATTENTE DE FWD | M63: NON CHARGÉ | N63: 64 - Unserviceable equipment / belt / sortation system
A64: 02/09/2026 | B64: AI | C64: AI148 | D64: 12:45 | E64: AC492720 | F64: 1 | G64: AC872 | H64: 11:47 | I64: PAS DE LOC | K64: PAS DE LOC | L64: NEG TOUS SYSTEMES/J+1 NON CHARGE A YYZ /DELAI26503 FO AC42/02SEP | M64: NON CHARGÉ | N64: 56 - Online - own carrier - MCT not available
A65: 02/09/2026 | B65: AI | C65: AI148 | D65: 12:45 | E65: AC475332 | F65: 1 | G65: AC870 | H65: 10:25 | I65: EJECTION 2C 12H42 | K65: BAG BLOQUE A LA CYNO TBM | L65: RECUP BAG RUNNER ET DEPOSE LL/J+1 DELAI26498 FO AI142/02SEP | M65: NON CHARGÉ | N65: 64 - Unserviceable equipment / belt / sortation system
A66: 02/09/2026 | B66: AI | C66: AI148 | D66: 12:45 | E66: AC487081 | F66: 1 | G66: AC872 | H66: 11:47 | I66: EJECTION 2C 12H44 | K66: ARRIVEE TARDIVE | L66: RECUP BAG RUNNER ET DEPOSE LL/J+1 DELAI26497 FO AI142/02SEP | M66: NON CHARGÉ | N66: 53 - Interline MCT not available ( MCT initialement OK)
A67: 02/09/2026 | B67: AI | C67: AI148 | D67: 12:45 | E67: AC487082 | F67: 1 | G67: AC872 | H67: 11:47 | I67: EJECTION 2C 12H39 | K67: ARRIVEE TARDIVE | L67: RECUP BAG RUNNER ET DEPOSE LL/J+1 DELAI26497 FO AI142/02SEP | M67: NON CHARGÉ | N67: 53 - Interline MCT not available ( MCT initialement OK)
A68: 02/09/2026 | B68: AI | C68: AI148 | D68: 12:45 | E68: AC487559 | F68: 1 | G68: AC872 | H68: 11:47 | I68: EJECTION 2C 12H40 | K68: ARRIVEE TARDIVE | L68: RECUP BAG RUNNER ET DEPOSE LL/J+1 DELAI26505 FO AI142/02SEP | M68: NON CHARGÉ | N68: 53 - Interline MCT not available ( MCT initialement OK)
A69: 02/09/2026 | B69: AI | C69: AI148 | D69: 12:45 | E69: AC487565 | F69: 1 | G69: AC872 | H69: 11:47 | I69: EJECTION 2C 12H46 | K69: ARRIVEE TARDIVE | L69: RECUP BAG RUNNER ET DEPOSE LL/J+1 DELAI26500 FO AI142/02SEP | M69: NON CHARGÉ | N69: 53 - Interline MCT not available ( MCT initialement OK)
A70: 02/09/2026 | B70: AI | C70: AI148 | D70: 12:45 | E70: AC487566 | F70: 1 | G70: AC872 | H70: 11:47 | I70: EJECTION 2C 12H46 | K70: ARRIVEE TARDIVE | L70: RECUP BAG RUNNER ET DEPOSE LL/J+1 DELAI26505 FO AI142/02SEP | M70: NON CHARGÉ | N70: 53 - Interline MCT not available ( MCT initialement OK)
A71: 02/09/2026 | B71: AI | C71: AI148 | D71: 12:45 | E71: AC487579 | F71: 1 | G71: AC872 | H71: 11:47 | I71: EJECTION 2C 12H44 | K71: ARRIVEE TARDIVE | L71: RECUP BAG RUNNER ET DEPOSE LL/J+1 DELAI26505 FO AI142/02SEP | M71: NON CHARGÉ | N71: 53 - Interline MCT not available ( MCT initialement OK)
... A90: 02/09/2026 | B90: AI | C90: AI148 | D90: 12:45 | E90: AC492718 | F90: 1 | G90: AC872 | H90: 11:47 | I90: EJECTION 2C 12H4 | K90: ARRIVEE TARDIVE | L90: RECUP BAG RUNNER ET DEPOSE LL/J+1 DELAI26503 FO AI142/02SEP | M90: NON CHARGÉ | N90: 53 - Interline MCT not available ( MCT initialement OK)
A91: 02/09/2026 | B91: AI | C91: AI142 | D91: 20:45 | E91: AF122976 | F91: 1 | G91: AF7465 | H91: 16:56 | I91: QSETRI 18H37 | K91: PAS DE MVT 19H40 | L91: APPEL QSE A 19H41/CONFIRME BAG AU QSE/ENVOI BAGRUNNER 19H42/PRIS EN CHARGE PAR BAGRUNNER ET DEPOSE SUR LA JETEE DEPART A 19H58 MAIS SCANNE APRES MANUELLEMENT | M91: SAUVÉ
A92: 02/09/2026 | B92: AI | C92: AI142 | D92: 20:45 | E92: AI939542 | F92: 1 | G92: LOCAL | I92: 2C HORS FORMAT 19H45 | K92: PAS DE MVT | L92: APPEL SUP GALERIE T2 A 20H02 ET SIGNALE POUR LE RECUPERER | M92: SAUVÉ
A93: 02/09/2026 | B93: AI | C93: AI142 | D93: 20:45 | E93: AI940268 | F93: 1 | G93: LOCAL | I93: AUCUNE TRACE 19H45 | K93: BSM 18H57 | L93: APPEL SUP GAL T2 A 19H45 ET DEMANDE DE VERIFIER EN REBUT DU 2C/BAG TROUVE EN C05 SANS AUCUNE TRACE D'INJECTION | M93: SAUVÉ
A94: 02/09/2026 | B94: AT | C94: AT789 | D94: 18:30 | E94: AT868890 | F94: 1 | G94: LOCAL | I94: T2B EJECTION B02 17H37 | K94: HOT | L94: APPEL SUP GALERIE T2 A 17H37 ET SIGNALE | M94: SAUVÉ
A95: 02/09/2026 | B95: AT | C95: AT789 | D95: 18:30 | E95: AT868923 | F95: 1 | G95: LOCAL | I95: T2B EJECTION B02 17H37 | K95: HOT | L95: APPEL SUP GALERIE T2 A 17H37 ET SIGNALE | M95: SAUVÉ
A96: 02/09/2026 | B96: AT | C96: AT789 | D96: 18:30 | E96: AT868931 | F96: 1 | G96: LOCAL | I96: T2B TRI SECURISATION 17H37 | K96: HOT | L96: APPEL SUP GALERIE T2 A 17H37 ET SIGNALE | M96: SAUVÉ
A97: 02/09/2026 | B97: AT | C97: AT789 | D97: 18:30 | E97: AT866174 | F97: 1 | G97: LOCAL | I97: T2B CHECK IN BANQUE 23 15H54 | K97: PAS DE MVT | L97: SEULE TRACE EN BAGRADAR CHECK/NEG EN REQUETEUR/APPEL LEAD AT A 17H45/CONFIRME QU'IL S'AGIT D'UN BAGAGE EN SOUTE /LIVRE S/BORD SANS AUCUNE TRACE/CONFIRME PAR AGENT FLUX | M97: SAUVÉ
A98: 02/09/2026 | B98: AT | C98: AT789 | D98: 18:30 | E98: AT869908 | F98: 1 | G98: LOCAL | I98: T2B CHECK IN BANQUE 23 17H04 | K98: PAS DE MVT | L98: AUCUNE TRACE DU BAGAGE DEPUIS LA ZONE CHECK IN/BAG EN SOUTE COMME CONFIRME PAR LEAD AT/LIVRE SOUS BORD DIRECTEMENT/CONFIRME PAR AGENT FLUX QUI EST ALLE VERIF A L'AVION | M98: SAUVÉ
A99: 02/09/2026 | B99: AV | C99: AV55 | D99: 08:55 | E99: LO397687 | F99: 1 | G99: LO333 | H99: 23:03 | I99: T2BD TAPIS 6 - 23H38 | K99: PAS DE MVT | L99: 06H37 : APPELTMB 2B - BAG DÉJÀ REDESCENDU POUR ETRE REMIS DANS LE SYSTÈME - RECUP PAR BAGRUNNER 07H52 POUR DEPOSE AU T1 | M99: SAUVÉ
A100: 02/09/2026 | B100: AV | C100: AV55 | D100: 08:55 | E100: AF060279 | F100: 1 | G100: AF1231 | H100: 17:50 | I100: TMEXY | K100: PAS DE MVT | L100: 06H44 : VU AVEC PILOTE TME ET BOB - BAG AU HF DU 2E / APPEL GTB AF POUR RECUP BAG ET ASSURER TRSF BAG | M100: SAUVÉ
A101: 02/09/2026 | B101: AV | C101: AV55 | D101: 08:55 | E101: ET318004 | F101: 1 | G101: 4H0098 | H101: 22:52 | I101: T1 ARRIVEE 2 - 22H50 | K101: PAS DE MVT | L101: 06H32 : APPEL DIRBY T1 - SANS REPONSE / 07H26 : 2EME APPEL SANS REPONSE/J+1 BOGAV24907 FO AV055/03SEP | M101: NON CHARGÉ | N101: 41 - Delivered to wrong area
A102: 02/09/2026 | B102: AV | C102: AV55 | D102: 08:55 | E102: ET318005 | F102: 1 | G102: 4H0098 | H102: 22:52 | I102: T1 ARRIVEE 2 - 22H50 | K102: PAS DE MVT | L102: 06H32 : APPEL DIRBY T1 - SANS REPONSE / 07H26 : 2EME APPEL SANS REPONSE/J+1 BOGAV24907 FO AV055/03SEP | M102: NON CHARGÉ | N102: 41 - Delivered to wrong area
A103: 02/09/2026 | B103: AV | C103: AV55 | D103: 08:55 | E103: ET318006 | F103: 1 | G103: 4H0098 | H103: 22:52 | I103: T1 ARRIVEE 2 - 22H50 | K103: PAS DE MVT | L103: 06H32 : APPEL DIRBY T1 - SANS REPONSE / 07H26 : 2EME APPEL SANS REPONSE/J+1 BOGAV24907 FO AV055/03SEP | M103: NON CHARGÉ | N103: 41 - Delivered to wrong area
A104: 02/09/2026 | B104: AV | C104: AV55 | D104: 08:55 | E104: ET318007 | F104: 1 | G104: 4H0098 | H104: 22:52 | I104: T1 ARRIVEE 2 - 22H50 | K104: PAS DE MVT | L104: 06H32 : APPEL DIRBY T1 - SANS REPONSE / 07H26 : 2EME APPEL SANS REPONSE/J+1 BOGAV24907 FO AV055/03SEP | M104: NON CHARGÉ | N104: 41 - Delivered to wrong area
A105: 02/09/2026 | B105: AV | C105: AV55 | D105: 08:55 | E105: ET318010 | F105: 1 | G105: 4H0098 | H105: 22:52 | I105: T1 ARRIVEE 2 - 22H50 | K105: PAS DE MVT | L105: 06H32 : APPEL DIRBY T1 - SANS REPONSE / 07H26 : 2EME APPEL SANS REPONSE/J+1 BOGAV24907 FO AV055/03SEP | M105: NON CHARGÉ | N105: 41 - Delivered to wrong area
A106: 02/09/2026 | B106: AV | C106: AV55 | D106: 08:55 | E106: ET318001 | F106: 1 | G106: 4H0098 | H106: 21:34 | I106: PAS DE TRACE | K106: PAS DE TRACE | L106: 06H32 : APPEL DIRBY T1 - SANS REPONSE / 07H26 : 2EME APPEL SANS REPONSE/J+1 BOGAV24907 FO AV055/03SEP | M106: NON CHARGÉ | N106: 41 - Delivered to wrong area
A107: 02/09/2026 | B107: AV | C107: AV55 | D107: 08:55 | E107: ET318002 | F107: 1 | G107: 4H0098 | H107: 21:34 | I107: PAS DETRACE | K107: PAS DE TRACE | L107: 06H32 : APPEL DIRBY T1 - SANS REPONSE / 07H26 : 2EME APPEL SANS REPONSE/J+1 BOGAV24907 FO AV055/03SEP | M107: NON CHARGÉ | N107: 41 - Delivered to wrong area
A108: 02/09/2026 | B108: DE | C108: DE4264 | D108: 09:05 | E108: TN105668 | F108: 1 | G108: TN008 | H108: 09:05 | I108: TBM CYNO | K108: PAS DE MVT | L108: 10H26 : PRISE EN CHARGE PAR BAGRUNNER POUR DEPOSE T3 | M108: SAUVÉ
A109: 02/09/2026 | B109: DE | C109: DE4264 | D109: 09:05 | E109: TN105675 | F109: 1 | G109: TN008 | H109: 09:05 | I109: EM92 | K109: PAS DE MVT | L109: 10H29 : PRISE EN CHARGE PAR BAGRUNNER POUR DEPOSE T3 | M109: SAUVÉ
A110: 02/09/2026 | B110: DE | C110: DE4264 | D110: 09:05 | E110: TN105676 | F110: 1 | G110: TN008 | H110: 09:05 | I110: EM92 | K110: PAS DE MVT | L110: 10H29 : PRISE EN CHARGE PAR BAGRUNNER POUR DEPOSE T3 | M110: SAUVÉ
A111: 02/09/2026 | B111: DE | C111: DE4214 | D111: 16:45 | E111: DE404300 | F111: 1 | G111: LOCAL | I111: T3 HALL B CYNO 16H27 | K111: PAS DE MVT | L111: APPEL GALERIE T3 A 16H38 ET SIGNALE/BAGAGE BLOQUE PAR ADP CAR "NON-CONFORME POUR LA SECURISATION"/ADP S'EST CHARGE DE LE DEPOSER AU LL T3 | M111: NON CHARGÉ | N111: 63 - Airport security
A112: 02/09/2026 | B112: DE | C112: DE4214 | D112: 16:45 | E112: WS429025 | F112: 1 | G112: WS0010 | H112: 11:28 | I112: MJ92 TBM | L112: PRIS EN CHARGE PAR BAG RUNNER 16H02 / VOL ARRIVE SEULEMENT A 16H19 / SERA INJ AU T3 A PARTIR DE 16H30 | M112: SAUVÉ
A113: 02/09/2026 | B113: EI | C113: EI521 | D113: 10:20 | E113: SQ658922 | F113: 1 | G113: NON NOTIFIE | I113: PAS DE TRACE | K113: PAS DE TRACE | L113: 09H41 : NEG DS TOUS SYSTEMES/J+1 MISCNX A SIN /RECU SUR LE SQ338/02SEP LOCALISE AN SLB 21H41 /DUBEI28745 FO EI523/03SEP | M113: NON CHARGÉ | N113: 56 - Online - own carrier - MCT not available
A114: 02/09/2026 | B114: EI | C114: EI523 | D114: 11:15 | E114: EI129848 | F114: 1 | G114: LOCAL/RUSH | I114: T1 HORS FORMAT | L114: 10H37 : APPEL HORS FORMAT PUIS GALERIE T1 - BAG SERA DEPOSE SS BORD DES QU IL SERA TROUVE - PEUT ETRE CHARGE SS SCAN/J+1 DOSSIER TOUJOUR OUVERT | M114: NON CHARGÉ | N114: 21 - Bag left at station origin / correctly labelled
A115: 02/09/2026 | B115: EI | C115: EI525 | D115: 13:15 | E115: EI215344 | F115: 1 | G115: LOCAL | I115: PAS DE LOC | K115: PAS DE LOC | L115: 7KG PROBABLEMENT PRIS EN PORTE | M115: CHARGÉ
A116: 02/09/2026 | B116: EI | C116: EI525 | D116: 13:15 | E116: EI215655 | F116: 1 | G116: LOCAL | I116: PAS DE LOC | K116: CYNO OK 13H22 | L116: RETARD TRAITEMENT/J+1 DUBEI28761 EN ATTENTE DE FWD | M116: NON CHARGÉ | N116: 64 - Unserviceable equipment / belt / sortation system
A117: 02/09/2026 | B117: EI | C117: EI529 | D117: 21:55 | E117: EI129974 | F117: 1 | G117: RUSH | I117: PAS DE TRACE | J117: BAG SOUTE S/SCAN | K117: BSM ONLY | L117: APPEL DIRBY T1 A 20H32 ET DEMANDE DE FAIRE LE NECESSAIRE/RUSH PAS EN GALERIE DOIT VERIF AVEC SES COLLEGUES EN SLB | M117: CHARGÉ
A118: 02/09/2026 | B118: FI | C118: FI549 | D118: 07:15 | E118: FI620121 | F118: 1 | G118: LOCAL | I118: T1 INJECTION | K118: PAS DE MVT | L118: 06H01 : APPEL GALERIE T1 - PAS DE TRACE DU BAG - VU AVEC CHEF GALERIE QUI ÉTAIT A LA RECHERCHE DU BAG/J+1 KEFFI16709 FO FI547/02SEP | M118: NON CHARGÉ | N118: 64 - Unserviceable equipment / belt / sortation system
A119: 02/09/2026 | B119: FI | C119: FI547 | D119: 17:15 | E119: LY009453 | F119: 1 | G119: LY323 | H119: 15:33 | I119: T2BD ARRIVEE TAPIS 2 DEPUIS 16H04 | K119: TRANSIT BAG LIVRE EN SLB | L119: APPEL LEADER TMB A 16H41 ET DEMANDE DE LE FAIRE DESCENDREAUSSITOT CAR HOT CNX/RAPPEL A 16H55 POUR LA MEME RAISON/BAGAGE TOUJOURS PAS DESCENDU APRES LE DEPART DU VOL | M119: NON CHARGÉ | N119: 41 - Delivered to wrong area
...

Sheet JOUR PAR JOUR
A1: ALYZIA | JOUR PAR JOUR
A3: COMPTE RENDU DE SUPERVISION • SEPTEMBRE 2026 • TOUTES COMPAGNIES
A5: DATE AFFICHÉE ▶ | C5: 24/09/2026
A7: RÉCAPITULATIF JOURNALIER • Changer la date en C5 | I7: DOSSIERS DU JOUR • Filtrer la date dans DOSSIERS pour consulter les détails
A8: CIE | B8: BAG. ATTENDUS | C8: DOSSIERS | D8: SAUVÉS | E8: CHARGÉS | F8: NON CHARGÉS | G8: ANNULÉS
A9: SK | B9: =IFERROR(INDEX('SYNTHÈSE PAR DATE'!$I$6:$I$35,MATCH($C$5,'SYNTHÈSE PAR DATE'!$A$6:$A$35,0)),0) -> 0 | C9: =COUNTIFS(BASE!$A$6:$A$1740,$C$5,BASE!$B$6:$B$1740,A9) -> 0 | D9: =COUNTIFS(BASE!$A$6:$A$1740,$C$5,BASE!$B$6:$B$1740,A9,BASE!$M$6:$M$1740,"SAUVÉ") -> 0 | E9: =COUNTIFS(BASE!$A$6:$A$1740,$C$5,BASE!$B$6:$B$1740,A9,BASE!$M$6:$M$1740,"CHARGÉ") -> 0 | F9: =COUNTIFS(BASE!$A$6:$A$1740,$C$5,BASE!$B$6:$B$1740,A9,BASE!$M$6:$M$1740,"NON CHARGÉ") -> 0 | G9: =COUNTIFS(BASE!$A$6:$A$1740,$C$5,BASE!$B$6:$B$1740,A9,BASE!$M$6:$M$1740,"ANNULÉ") -> 0 | I9: Le récapitulatif se met à jour avec la date C5. Pour afficher et imprimer les dossiers détaillés du jour, utilisez le filtre DATE de la feuille DOSSIERS.
A10: AI | B10: =IFERROR(INDEX('SYNTHÈSE PAR DATE'!$J$6:$J$35,MATCH($C$5,'SYNTHÈSE PAR DATE'!$A$6:$A$35,0)),0) -> 202 | C10: =COUNTIFS(BASE!$A$6:$A$1740,$C$5,BASE!$B$6:$B$1740,A10) -> 5 | D10: =COUNTIFS(BASE!$A$6:$A$1740,$C$5,BASE!$B$6:$B$1740,A10,BASE!$M$6:$M$1740,"SAUVÉ") -> 4 | E10: =COUNTIFS(BASE!$A$6:$A$1740,$C$5,BASE!$B$6:$B$1740,A10,BASE!$M$6:$M$1740,"CHARGÉ") -> 0 | F10: =COUNTIFS(BASE!$A$6:$A$1740,$C$5,BASE!$B$6:$B$1740,A10,BASE!$M$6:$M$1740,"NON CHARGÉ") -> 1 | G10: =COUNTIFS(BASE!$A$6:$A$1740,$C$5,BASE!$B$6:$B$1740,A10,BASE!$M$6:$M$1740,"ANNULÉ") -> 0
A11: EI | B11: =IFERROR(INDEX('SYNTHÈSE PAR DATE'!$K$6:$K$35,MATCH($C$5,'SYNTHÈSE PAR DATE'!$A$6:$A$35,0)),0) -> 632 | C11: =COUNTIFS(BASE!$A$6:$A$1740,$C$5,BASE!$B$6:$B$1740,A11) -> 8 | D11: =COUNTIFS(BASE!$A$6:$A$1740,$C$5,BASE!$B$6:$B$1740,A11,BASE!$M$6:$M$1740,"SAUVÉ") -> 0 | E11: =COUNTIFS(BASE!$A$6:$A$1740,$C$5,BASE!$B$6:$B$1740,A11,BASE!$M$6:$M$1740,"CHARGÉ") -> 3 | F11: =COUNTIFS(BASE!$A$6:$A$1740,$C$5,BASE!$B$6:$B$1740,A11,BASE!$M$6:$M$1740,"NON CHARGÉ") -> 5 | G11: =COUNTIFS(BASE!$A$6:$A$1740,$C$5,BASE!$B$6:$B$1740,A11,BASE!$M$6:$M$1740,"ANNULÉ") -> 0
A12: LA | B12: =IFERROR(INDEX('SYNTHÈSE PAR DATE'!$L$6:$L$35,MATCH($C$5,'SYNTHÈSE PAR DATE'!$A$6:$A$35,0)),0) -> 244 | C12: =COUNTIFS(BASE!$A$6:$A$1740,$C$5,BASE!$B$6:$B$1740,A12) -> 7 | D12: =COUNTIFS(BASE!$A$6:$A$1740,$C$5,BASE!$B$6:$B$1740,A12,BASE!$M$6:$M$1740,"SAUVÉ") -> 0 | E12: =COUNTIFS(BASE!$A$6:$A$1740,$C$5,BASE!$B$6:$B$1740,A12,BASE!$M$6:$M$1740,"CHARGÉ") -> 4 | F12: =COUNTIFS(BASE!$A$6:$A$1740,$C$5,BASE!$B$6:$B$1740,A12,BASE!$M$6:$M$1740,"NON CHARGÉ") -> 3 | G12: =COUNTIFS(BASE!$A$6:$A$1740,$C$5,BASE!$B$6:$B$1740,A12,BASE!$M$6:$M$1740,"ANNULÉ") -> 0
A13: HF | B13: =IFERROR(INDEX('SYNTHÈSE PAR DATE'!$M$6:$M$35,MATCH($C$5,'SYNTHÈSE PAR DATE'!$A$6:$A$35,0)),0) -> 482 | C13: =COUNTIFS(BASE!$A$6:$A$1740,$C$5,BASE!$B$6:$B$1740,A13) -> 4 | D13: =COUNTIFS(BASE!$A$6:$A$1740,$C$5,BASE!$B$6:$B$1740,A13,BASE!$M$6:$M$1740,"SAUVÉ") -> 0 | E13: =COUNTIFS(BASE!$A$6:$A$1740,$C$5,BASE!$B$6:$B$1740,A13,BASE!$M$6:$M$1740,"CHARGÉ") -> 4 | F13: =COUNTIFS(BASE!$A$6:$A$1740,$C$5,BASE!$B$6:$B$1740,A13,BASE!$M$6:$M$1740,"NON CHARGÉ") -> 0 | G13: =COUNTIFS(BASE!$A$6:$A$1740,$C$5,BASE!$B$6:$B$1740,A13,BASE!$M$6:$M$1740,"ANNULÉ") -> 0
A14: SB | B14: =IFERROR(INDEX('SYNTHÈSE PAR DATE'!$N$6:$N$35,MATCH($C$5,'SYNTHÈSE PAR DATE'!$A$6:$A$35,0)),0) -> 0 | C14: =COUNTIFS(BASE!$A$6:$A$1740,$C$5,BASE!$B$6:$B$1740,A14) -> 0 | D14: =COUNTIFS(BASE!$A$6:$A$1740,$C$5,BASE!$B$6:$B$1740,A14,BASE!$M$6:$M$1740,"SAUVÉ") -> 0 | E14: =COUNTIFS(BASE!$A$6:$A$1740,$C$5,BASE!$B$6:$B$1740,A14,BASE!$M$6:$M$1740,"CHARGÉ") -> 0 | F14: =COUNTIFS(BASE!$A$6:$A$1740,$C$5,BASE!$B$6:$B$1740,A14,BASE!$M$6:$M$1740,"NON CHARGÉ") -> 0 | G14: =COUNTIFS(BASE!$A$6:$A$1740,$C$5,BASE!$B$6:$B$1740,A14,BASE!$M$6:$M$1740,"ANNULÉ") -> 0
A15: DE | B15: =IFERROR(INDEX('SYNTHÈSE PAR DATE'!$O$6:$O$35,MATCH($C$5,'SYNTHÈSE PAR DATE'!$A$6:$A$35,0)),0) -> 140 | C15: =COUNTIFS(BASE!$A$6:$A$1740,$C$5,BASE!$B$6:$B$1740,A15) -> 1 | D15: =COUNTIFS(BASE!$A$6:$A$1740,$C$5,BASE!$B$6:$B$1740,A15,BASE!$M$6:$M$1740,"SAUVÉ") -> 0 | E15: =COUNTIFS(BASE!$A$6:$A$1740,$C$5,BASE!$B$6:$B$1740,A15,BASE!$M$6:$M$1740,"CHARGÉ") -> 0 | F15: =COUNTIFS(BASE!$A$6:$A$1740,$C$5,BASE!$B$6:$B$1740,A15,BASE!$M$6:$M$1740,"NON CHARGÉ") -> 1 | G15: =COUNTIFS(BASE!$A$6:$A$1740,$C$5,BASE!$B$6:$B$1740,A15,BASE!$M$6:$M$1740,"ANNULÉ") -> 0
A16: MH | B16: =IFERROR(INDEX('SYNTHÈSE PAR DATE'!$P$6:$P$35,MATCH($C$5,'SYNTHÈSE PAR DATE'!$A$6:$A$35,0)),0) -> 222 | C16: =COUNTIFS(BASE!$A$6:$A$1740,$C$5,BASE!$B$6:$B$1740,A16) -> 1 | D16: =COUNTIFS(BASE!$A$6:$A$1740,$C$5,BASE!$B$6:$B$1740,A16,BASE!$M$6:$M$1740,"SAUVÉ") -> 0 | E16: =COUNTIFS(BASE!$A$6:$A$1740,$C$5,BASE!$B$6:$B$1740,A16,BASE!$M$6:$M$1740,"CHARGÉ") -> 0 | F16: =COUNTIFS(BASE!$A$6:$A$1740,$C$5,BASE!$B$6:$B$1740,A16,BASE!$M$6:$M$1740,"NON CHARGÉ") -> 1 | G16: =COUNTIFS(BASE!$A$6:$A$1740,$C$5,BASE!$B$6:$B$1740,A16,BASE!$M$6:$M$1740,"ANNULÉ") -> 0
A17: RJ | B17: =IFERROR(INDEX('SYNTHÈSE PAR DATE'!$Q$6:$Q$35,MATCH($C$5,'SYNTHÈSE PAR DATE'!$A$6:$A$35,0)),0) -> 132 | C17: =COUNTIFS(BASE!$A$6:$A$1740,$C$5,BASE!$B$6:$B$1740,A17) -> 0 | D17: =COUNTIFS(BASE!$A$6:$A$1740,$C$5,BASE!$B$6:$B$1740,A17,BASE!$M$6:$M$1740,"SAUVÉ") -> 0 | E17: =COUNTIFS(BASE!$A$6:$A$1740,$C$5,BASE!$B$6:$B$1740,A17,BASE!$M$6:$M$1740,"CHARGÉ") -> 0 | F17: =COUNTIFS(BASE!$A$6:$A$1740,$C$5,BASE!$B$6:$B$1740,A17,BASE!$M$6:$M$1740,"NON CHARGÉ") -> 0 | G17: =COUNTIFS(BASE!$A$6:$A$1740,$C$5,BASE!$B$6:$B$1740,A17,BASE!$M$6:$M$1740,"ANNULÉ") -> 0
A18: AV | B18: =IFERROR(INDEX('SYNTHÈSE PAR DATE'!$R$6:$R$35,MATCH($C$5,'SYNTHÈSE PAR DATE'!$A$6:$A$35,0)),0) -> 220 | C18: =COUNTIFS(BASE!$A$6:$A$1740,$C$5,BASE!$B$6:$B$1740,A18) -> 4 | D18: =COUNTIFS(BASE!$A$6:$A$1740,$C$5,BASE!$B$6:$B$1740,A18,BASE!$M$6:$M$1740,"SAUVÉ") -> 1 | E18: =COUNTIFS(BASE!$A$6:$A$1740,$C$5,BASE!$B$6:$B$1740,A18,BASE!$M$6:$M$1740,"CHARGÉ") -> 3 | F18: =COUNTIFS(BASE!$A$6:$A$1740,$C$5,BASE!$B$6:$B$1740,A18,BASE!$M$6:$M$1740,"NON CHARGÉ") -> 0 | G18: =COUNTIFS(BASE!$A$6:$A$1740,$C$5,BASE!$B$6:$B$1740,A18,BASE!$M$6:$M$1740,"ANNULÉ") -> 0
A19: FI | B19: =IFERROR(INDEX('SYNTHÈSE PAR DATE'!$S$6:$S$35,MATCH($C$5,'SYNTHÈSE PAR DATE'!$A$6:$A$35,0)),0) -> 345 | C19: =COUNTIFS(BASE!$A$6:$A$1740,$C$5,BASE!$B$6:$B$1740,A19) -> 4 | D19: =COUNTIFS(BASE!$A$6:$A$1740,$C$5,BASE!$B$6:$B$1740,A19,BASE!$M$6:$M$1740,"SAUVÉ") -> 4 | E19: =COUNTIFS(BASE!$A$6:$A$1740,$C$5,BASE!$B$6:$B$1740,A19,BASE!$M$6:$M$1740,"CHARGÉ") -> 0 | F19: =COUNTIFS(BASE!$A$6:$A$1740,$C$5,BASE!$B$6:$B$1740,A19,BASE!$M$6:$M$1740,"NON CHARGÉ") -> 0 | G19: =COUNTIFS(BASE!$A$6:$A$1740,$C$5,BASE!$B$6:$B$1740,A19,BASE!$M$6:$M$1740,"ANNULÉ") -> 0
A20: AT | B20: =IFERROR(INDEX('SYNTHÈSE PAR DATE'!$T$6:$T$35,MATCH($C$5,'SYNTHÈSE PAR DATE'!$A$6:$A$35,0)),0) -> 421 | C20: =COUNTIFS(BASE!$A$6:$A$1740,$C$5,BASE!$B$6:$B$1740,A20) -> 31 | D20: =COUNTIFS(BASE!$A$6:$A$1740,$C$5,BASE!$B$6:$B$1740,A20,BASE!$M$6:$M$1740,"SAUVÉ") -> 15 | E20: =COUNTIFS(BASE!$A$6:$A$1740,$C$5,BASE!$B$6:$B$1740,A20,BASE!$M$6:$M$1740,"CHARGÉ") -> 0 | F20: =COUNTIFS(BASE!$A$6:$A$1740,$C$5,BASE!$B$6:$B$1740,A20,BASE!$M$6:$M$1740,"NON CHARGÉ") -> 16 | G20: =COUNTIFS(BASE!$A$6:$A$1740,$C$5,BASE!$B$6:$B$1740,A20,BASE!$M$6:$M$1740,"ANNULÉ") -> 0
A21: JU | B21: =IFERROR(INDEX('SYNTHÈSE PAR DATE'!$U$6:$U$35,MATCH($C$5,'SYNTHÈSE PAR DATE'!$A$6:$A$35,0)),0) -> 151 | C21: =COUNTIFS(BASE!$A$6:$A$1740,$C$5,BASE!$B$6:$B$1740,A21) -> 4 | D21: =COUNTIFS(BASE!$A$6:$A$1740,$C$5,BASE!$B$6:$B$1740,A21,BASE!$M$6:$M$1740,"SAUVÉ") -> 3 | E21: =COUNTIFS(BASE!$A$6:$A$1740,$C$5,BASE!$B$6:$B$1740,A21,BASE!$M$6:$M$1740,"CHARGÉ") -> 1 | F21: =COUNTIFS(BASE!$A$6:$A$1740,$C$5,BASE!$B$6:$B$1740,A21,BASE!$M$6:$M$1740,"NON CHARGÉ") -> 0 | G21: =COUNTIFS(BASE!$A$6:$A$1740,$C$5,BASE!$B$6:$B$1740,A21,BASE!$M$6:$M$1740,"ANNULÉ") -> 0
A22: LO | B22: =IFERROR(INDEX('SYNTHÈSE PAR DATE'!$V$6:$V$35,MATCH($C$5,'SYNTHÈSE PAR DATE'!$A$6:$A$35,0)),0) -> 205 | C22: =COUNTIFS(BASE!$A$6:$A$1740,$C$5,BASE!$B$6:$B$1740,A22) -> 8 | D22: =COUNTIFS(BASE!$A$6:$A$1740,$C$5,BASE!$B$6:$B$1740,A22,BASE!$M$6:$M$1740,"SAUVÉ") -> 6 | E22: =COUNTIFS(BASE!$A$6:$A$1740,$C$5,BASE!$B$6:$B$1740,A22,BASE!$M$6:$M$1740,"CHARGÉ") -> 1 | F22: =COUNTIFS(BASE!$A$6:$A$1740,$C$5,BASE!$B$6:$B$1740,A22,BASE!$M$6:$M$1740,"NON CHARGÉ") -> 1 | G22: =COUNTIFS(BASE!$A$6:$A$1740,$C$5,BASE!$B$6:$B$1740,A22,BASE!$M$6:$M$1740,"ANNULÉ") -> 0
A23: TOTAL JOUR | B23: =SUM(B9:B22) -> 3396 | C23: =SUM(C9:C22) -> 77 | D23: =SUM(D9:D22) -> 33 | E23: =SUM(E9:E22) -> 16 | F23: =SUM(F9:F22) -> 28 | G23: =SUM(G9:G22) -> 0

Sheet SYNTHÈSE PAR DATE
A1: ALYZIA | SYNTHÈSE PAR DATE
A3: COMPTE RENDU DE SUPERVISION • SEPTEMBRE 2026 • TOUTES COMPAGNIES
A4: SUIVI JOURNALIER • Calculé à partir de la BASE | I4: BAGAGES ATTENDUS PAR COMPAGNIE • Données source conservées
A5: DATE | B5: DOSSIERS | C5: BAGAGES TRAITÉS | D5: BAGAGES ATTENDUS | E5: SAUVÉS | F5: CHARGÉS | G5: NON CHARGÉS | H5: ANNULÉS | I5: SK | J5: AI | K5: EI | L5: LA | M5: HF | N5: SB | O5: DE | P5: MH | Q5: RJ | R5: AV | S5: FI | T5: AT | U5: JU | V5: LO
A6: 01/09/2026 | B6: =COUNTIF(BASE!$A$6:$A$1740,A6) -> 54 | C6: =SUMIF(BASE!$A$6:$A$1740,A6,BASE!$F$6:$F$1740) -> 54 | D6: =SUM(I6:V6) -> 3036 | E6: =COUNTIFS(BASE!$A$6:$A$1740,A6,BASE!$M$6:$M$1740,"SAUVÉ") -> 21 | F6: =COUNTIFS(BASE!$A$6:$A$1740,A6,BASE!$M$6:$M$1740,"CHARGÉ") -> 6 | G6: =COUNTIFS(BASE!$A$6:$A$1740,A6,BASE!$M$6:$M$1740,"NON CHARGÉ") -> 27 | H6: =COUNTIFS(BASE!$A$6:$A$1740,A6,BASE!$M$6:$M$1740,"ANNULÉ") -> 0 | I6: 394 | J6: 332 | K6: 402 | L6: 186 | M6: 399 | N6: 0 | O6: 91 | P6: 207 | Q6: 136 | R6: 149 | S6: 308 | T6: 334 | U6: 98 | V6: 0
A7: 02/09/2026 | B7: =COUNTIF(BASE!$A$6:$A$1740,A7) -> 83 | C7: =SUMIF(BASE!$A$6:$A$1740,A7,BASE!$F$6:$F$1740) -> 83 | D7: =SUM(I7:V7) -> 3093 | E7: =COUNTIFS(BASE!$A$6:$A$1740,A7,BASE!$M$6:$M$1740,"SAUVÉ") -> 25 | F7: =COUNTIFS(BASE!$A$6:$A$1740,A7,BASE!$M$6:$M$1740,"CHARGÉ") -> 3 | G7: =COUNTIFS(BASE!$A$6:$A$1740,A7,BASE!$M$6:$M$1740,"NON CHARGÉ") -> 55 | H7: =COUNTIFS(BASE!$A$6:$A$1740,A7,BASE!$M$6:$M$1740,"ANNULÉ") -> 0 | I7: 258 | J7: 389 | K7: 371 | L7: 167 | M7: 417 | N7: 356 | O7: 124 | P7: 128 | Q7: 106 | R7: 107 | S7: 207 | T7: 364 | U7: 99 | V7: 0
A8: 03/09/2026 | B8: =COUNTIF(BASE!$A$6:$A$1740,A8) -> 80 | C8: =SUMIF(BASE!$A$6:$A$1740,A8,BASE!$F$6:$F$1740) -> 80 | D8: =SUM(I8:V8) -> 3156 | E8: =COUNTIFS(BASE!$A$6:$A$1740,A8,BASE!$M$6:$M$1740,"SAUVÉ") -> 28 | F8: =COUNTIFS(BASE!$A$6:$A$1740,A8,BASE!$M$6:$M$1740,"CHARGÉ") -> 13 | G8: =COUNTIFS(BASE!$A$6:$A$1740,A8,BASE!$M$6:$M$1740,"NON CHARGÉ") -> 39 | H8: =COUNTIFS(BASE!$A$6:$A$1740,A8,BASE!$M$6:$M$1740,"ANNULÉ") -> 0 | I8: 398 | J8: 305 | K8: 501 | L8: 149 | M8: 509 | N8: 0 | O8: 119 | P8: 197 | Q8: 96 | R8: 151 | S8: 225 | T8: 412 | U8: 94 | V8: 0
A9: 04/09/2026 | B9: =COUNTIF(BASE!$A$6:$A$1740,A9) -> 64 | C9: =SUMIF(BASE!$A$6:$A$1740,A9,BASE!$F$6:$F$1740) -> 64 | D9: =SUM(I9:V9) -> 3419 | E9: =COUNTIFS(BASE!$A$6:$A$1740,A9,BASE!$M$6:$M$1740,"SAUVÉ") -> 45 | F9: =COUNTIFS(BASE!$A$6:$A$1740,A9,BASE!$M$6:$M$1740,"CHARGÉ") -> 3 | G9: =COUNTIFS(BASE!$A$6:$A$1740,A9,BASE!$M$6:$M$1740,"NON CHARGÉ") -> 16 | H9: =COUNTIFS(BASE!$A$6:$A$1740,A9,BASE!$M$6:$M$1740,"ANNULÉ") -> 0 | I9: 573 | J9: 262 | K9: 521 | L9: 163 | M9: 422 | N9: 0 | O9: 181 | P9: 220 | Q9: 125 | R9: 150 | S9: 341 | T9: 355 | U9: 106 | V9: 0
A10: 05/09/2026 | B10: =COUNTIF(BASE!$A$6:$A$1740,A10) -> 71 | C10: =SUMIF(BASE!$A$6:$A$1740,A10,BASE!$F$6:$F$1740) -> 71 | D10: =SUM(I10:V10) -> 4096 | E10: =COUNTIFS(BASE!$A$6:$A$1740,A10,BASE!$M$6:$M$1740,"SAUVÉ") -> 18 | F10: =COUNTIFS(BASE!$A$6:$A$1740,A10,BASE!$M$6:$M$1740,"CHARGÉ") -> 17 | G10: =COUNTIFS(BASE!$A$6:$A$1740,A10,BASE!$M$6:$M$1740,"NON CHARGÉ") -> 36 | H10: =COUNTIFS(BASE!$A$6:$A$1740,A10,BASE!$M$6:$M$1740,"ANNULÉ") -> 0 | I10: 508 | J10: 304 | K10: 567 | L10: 255 | M10: 422 | N10: 360 | O10: 206 | P10: 241 | Q10: 125 | R10: 154 | S10: 431 | T10: 391 | U10: 132 | V10: 0
A11: 06/09/2026 | B11: =COUNTIF(BASE!$A$6:$A$1740,A11) -> 59 | C11: =SUMIF(BASE!$A$6:$A$1740,A11,BASE!$F$6:$F$1740) -> 59 | D11: =SUM(I11:V11) -> 4518 | E11: =COUNTIFS(BASE!$A$6:$A$1740,A11,BASE!$M$6:$M$1740,"SAUVÉ") -> 13 | F11: =COUNTIFS(BASE!$A$6:$A$1740,A11,BASE!$M$6:$M$1740,"CHARGÉ") -> 25 | G11: =COUNTIFS(BASE!$A$6:$A$1740,A11,BASE!$M$6:$M$1740,"NON CHARGÉ") -> 21 | H11: =COUNTIFS(BASE!$A$6:$A$1740,A11,BASE!$M$6:$M$1740,"ANNULÉ") -> 0 | I11: 765 | J11: 332 | K11: 743 | L11: 279 | M11: 753 | N11: 0 | O11: 225 | P11: 183 | Q11: 163 | R11: 199 | S11: 338 | T11: 417 | U11: 121 | V11: 0
A12: 07/09/2026 | B12: =COUNTIF(BASE!$A$6:$A$1740,A12) -> 89 | C12: =SUMIF(BASE!$A$6:$A$1740,A12,BASE!$F$6:$F$1740) -> 89 | D12: =SUM(I12:V12) -> 4510 | E12: =COUNTIFS(BASE!$A$6:$A$1740,A12,BASE!$M$6:$M$1740,"SAUVÉ") -> 46 | F12: =COUNTIFS(BASE!$A$6:$A$1740,A12,BASE!$M$6:$M$1740,"CHARGÉ") -> 21 | G12: =COUNTIFS(BASE!$A$6:$A$1740,A12,BASE!$M$6:$M$1740,"NON CHARGÉ") -> 22 | H12: =COUNTIFS(BASE!$A$6:$A$1740,A12,BASE!$M$6:$M$1740,"ANNULÉ") -> 0 | I12: 827 | J12: 324 | K12: 599 | L12: 296 | M12: 390 | N12: 396 | O12: 284 | P12: 235 | Q12: 115 | R12: 158 | S12: 248 | T12: 498 | U12: 140 | V12: 0
A13: 08/09/2026 | B13: =COUNTIF(BASE!$A$6:$A$1740,A13) -> 56 | C13: =SUMIF(BASE!$A$6:$A$1740,A13,BASE!$F$6:$F$1740) -> 56 | D13: =SUM(I13:V13) -> 3124 | E13: =COUNTIFS(BASE!$A$6:$A$1740,A13,BASE!$M$6:$M$1740,"SAUVÉ") -> 39 | F13: =COUNTIFS(BASE!$A$6:$A$1740,A13,BASE!$M$6:$M$1740,"CHARGÉ") -> 6 | G13: =COUNTIFS(BASE!$A$6:$A$1740,A13,BASE!$M$6:$M$1740,"NON CHARGÉ") -> 11 | H13: =COUNTIFS(BASE!$A$6:$A$1740,A13,BASE!$M$6:$M$1740,"ANNULÉ") -> 0 | I13: 522 | J13: 298 | K13: 489 | L13: 163 | M13: 375 | N13: 0 | O13: 145 | P13: 222 | Q13: 112 | R13: 97 | S13: 259 | T13: 324 | U13: 118 | V13: 0
A14: 09/09/2026 | B14: =COUNTIF(BASE!$A$6:$A$1740,A14) -> 107 | C14: =SUMIF(BASE!$A$6:$A$1740,A14,BASE!$F$6:$F$1740) -> 107 | D14: =SUM(I14:V14) -> 3564 | E14: =COUNTIFS(BASE!$A$6:$A$1740,A14,BASE!$M$6:$M$1740,"SAUVÉ") -> 59 | F14: =COUNTIFS(BASE!$A$6:$A$1740,A14,BASE!$M$6:$M$1740,"CHARGÉ") -> 20 | G14: =COUNTIFS(BASE!$A$6:$A$1740,A14,BASE!$M$6:$M$1740,"NON CHARGÉ") -> 28 | H14: =COUNTIFS(BASE!$A$6:$A$1740,A14,BASE!$M$6:$M$1740,"ANNULÉ") -> 0 | I14: 513 | J14: 304 | K14: 592 | L14: 212 | M14: 383 | N14: 317 | O14: 95 | P14: 157 | Q14: 145 | R14: 127 | S14: 284 | T14: 307 | U14: 128 | V14: 0
A15: 10/09/2026 | B15: =COUNTIF(BASE!$A$6:$A$1740,A15) -> 42 | C15: =SUMIF(BASE!$A$6:$A$1740,A15,BASE!$F$6:$F$1740) -> 42 | D15: =SUM(I15:V15) -> 3277 | E15: =COUNTIFS(BASE!$A$6:$A$1740,A15,BASE!$M$6:$M$1740,"SAUVÉ") -> 7 | F15: =COUNTIFS(BASE!$A$6:$A$1740,A15,BASE!$M$6:$M$1740,"CHARGÉ") -> 11 | G15: =COUNTIFS(BASE!$A$6:$A$1740,A15,BASE!$M$6:$M$1740,"NON CHARGÉ") -> 24 | H15: =COUNTIFS(BASE!$A$6:$A$1740,A15,BASE!$M$6:$M$1740,"ANNULÉ") -> 0 | I15: 0 | J15: 257 | K15: 551 | L15: 227 | M15: 521 | N15: 0 | O15: 154 | P15: 210 | Q15: 168 | R15: 155 | S15: 274 | T15: 413 | U15: 162 | V15: 185
A16: 11/09/2026 | B16: =COUNTIF(BASE!$A$6:$A$1740,A16) -> 32 | C16: =SUMIF(BASE!$A$6:$A$1740,A16,BASE!$F$6:$F$1740) -> 32 | D16: =SUM(I16:V16) -> 3104 | E16: =COUNTIFS(BASE!$A$6:$A$1740,A16,BASE!$M$6:$M$1740,"SAUVÉ") -> 7 | F16: =COUNTIFS(BASE!$A$6:$A$1740,A16,BASE!$M$6:$M$1740,"CHARGÉ") -> 9 | G16: =COUNTIFS(BASE!$A$6:$A$1740,A16,BASE!$M$6:$M$1740,"NON CHARGÉ") -> 16 | H16: =COUNTIFS(BASE!$A$6:$A$1740,A16,BASE!$M$6:$M$1740,"ANNULÉ") -> 0 | I16: 0 | J16: 301 | K16: 546 | L16: 260 | M16: 399 | N16: 0 | O16: 174 | P16: 238 | Q16: 108 | R16: 91 | S16: 346 | T16: 293 | U16: 147 | V16: 201
A17: 12/09/2026 | B17: =COUNTIF(BASE!$A$6:$A$1740,A17) -> 63 | C17: =SUMIF(BASE!$A$6:$A$1740,A17,BASE!$F$6:$F$1740) -> 63 | D17: =SUM(I17:V17) -> 4038 | E17: =COUNTIFS(BASE!$A$6:$A$1740,A17,BASE!$M$6:$M$1740,"SAUVÉ") -> 40 | F17: =COUNTIFS(BASE!$A$6:$A$1740,A17,BASE!$M$6:$M$1740,"CHARGÉ") -> 12 | G17: =COUNTIFS(BASE!$A$6:$A$1740,A17,BASE!$M$6:$M$1740,"NON CHARGÉ") -> 11 | H17: =COUNTIFS(BASE!$A$6:$A$1740,A17,BASE!$M$6:$M$1740,"ANNULÉ") -> 0 | I17: 0 | J17: 317 | K17: 576 | L17: 317 | M17: 476 | N17: 410 | O17: 266 | P17: 222 | Q17: 164 | R17: 161 | S17: 294 | T17: 402 | U17: 174 | V17: 259
... A35: 30/09/2026 | B35: =COUNTIF(BASE!$A$6:$A$1740,A35) -> 55 | C35: =SUMIF(BASE!$A$6:$A$1740,A35,BASE!$F$6:$F$1740) -> 55 | D35: =SUM(I35:V35) -> 3761 | E35: =COUNTIFS(BASE!$A$6:$A$1740,A35,BASE!$M$6:$M$1740,"SAUVÉ") -> 36 | F35: =COUNTIFS(BASE!$A$6:$A$1740,A35,BASE!$M$6:$M$1740,"CHARGÉ") -> 11 | G35: =COUNTIFS(BASE!$A$6:$A$1740,A35,BASE!$M$6:$M$1740,"NON CHARGÉ") -> 8 | H35: =COUNTIFS(BASE!$A$6:$A$1740,A35,BASE!$M$6:$M$1740,"ANNULÉ") -> 0 | I35: 0 | J35: 412 | K35: 535 | L35: 331 | M35: 379 | N35: 311 | O35: 205 | P35: 251 | Q35: 120 | R35: 224 | S35: 310 | T35: 301 | U35: 153 | V35: 229
A36: TOTAL SEPTEMBRE | B36: =SUM(B6:B35) -> 1735 | C36: =SUM(C6:C35) -> 1735 | D36: =SUM(D6:D35) -> 106188 | E36: =SUM(E6:E35) -> 773 | F36: =SUM(F6:F35) -> 369 | G36: =SUM(G6:G35) -> 593 | H36: =SUM(H6:H35) -> 0 | I36: =SUM(I6:I35) -> 4758 | ... V36: =SUM(V6:V35) -> 4866

Sheet BASE
A1: ALYZIA | BASE DE DONNÉES | AZ1: STATUT | BA1: DOSSIERS
AZ2: SAUVÉS | BA2: =RÉCAPITULATIF!G6 -> 773
A3: COMPTE RENDU DE SUPERVISION • SEPTEMBRE 2026 • TOUTES COMPAGNIES | AZ3: CHARGÉS | BA3: =RÉCAPITULATIF!J6 -> 369
A4: SOURCE DES DONNÉES • Valeurs du fichier transmis, heures normalisées et préfixes de vol affichés | AZ4: NON CHARGÉS | BA4: =RÉCAPITULATIF!M6 -> 593
A5: DATE | B5: CIE | C5: N° VOL | D5: HEURE DÉPART | E5: N° TAG | F5: NOMBRE BAGAGES | G5: VOL APPORT | H5: HEURE ARRIVÉE | I5: LOCALISATION | J5: REMARQUES | K5: ANOMALIE | L5: COMMENTAIRE/ACTION | M5: STATUT | N5: FAULT STATION | P5: OCCURRENCES TAG | Q5: RANG DOUBLON | R5: TYPE DOUBLON | AZ5: ANNULÉS | BA5: =RÉCAPITULATIF!P6 -> 0
A6: 01/09/2026 | B6: AI | C6: AI148 | D6: 12:45 | E6: AC384224 | F6: 1 | G6: AC870 | H6: 10:08 | I6: ONLY BSM | L6: AUCUNE INJ SUR CDG / CHECK DONE AVEC GEH IDEM BAGS NON LISTE SUR LEUR LOAD SHEET AC870/31AUG//AHL DELAI 26474 | M6: NON CHARGÉ | N6: 21 - Bag left at station origin / correctly labelled | P6: =COUNTIF($E$6:$E$1740,E6) -> 1 | Q6: =IF(AND(P6>1,COUNTIF($E$6:E6,E6)=1),MAX($Q$5:Q5)+1,"") | R6: =IF(Q6="","",IF(COUNTIFS($E$6:$E$1740,E6,$A$6:$A$1740,A6,$C$6:$C$1740,C6)<P6,"LÉGITIME",IF(COUNTIFS($E$6:$E$1740,E6,$A$6:$A$1740,A6,$C$6:$C$1740,C6,$M$6:$M$1740,M6)<P6,"STATUT DIFFÉRENT","VRAI DOUBLON")))
A7: 01/09/2026 | B7: AI | C7: AI148 | D7: 12:45 | E7: AC384225 | F7: 1 | G7: AC870 | H7: 10:08 | I7: ONLY BSM | L7: AUCUNE INJ SUR CDG / CHECK DONE AVEC GEH IDEM BAGS NON LISTE SUR LEUR LOAD SHEET AC870/31AUG//AHL DELAI 26474 | M7: NON CHARGÉ | N7: 21 - Bag left at station origin / correctly labelled | P7: =COUNTIF($E$6:$E$1740,E7) -> 1 | Q7: =IF(AND(P7>1,COUNTIF($E$6:E7,E7)=1),MAX($Q$5:Q6)+1,"") | R7: =IF(Q7="","",IF(COUNTIFS($E$6:$E$1740,E7,$A$6:$A$1740,A7,$C$6:$C$1740,C7)<P7,"LÉGITIME",IF(COUNTIFS($E$6:$E$1740,E7,$A$6:$A$1740,A7,$C$6:$C$1740,C7,$M$6:$M$1740,M7)<P7,"STATUT DIFFÉRENT","VRAI DOUBLON")))
A8: 01/09/2026 | B8: AI | C8: AI142 | D8: 20:45 | E8: AF027425 | F8: 1 | G8: AF0009 | H8: 12:29 | I8: TBM DEPOSE HF DEPUIS 14H01 | K8: PAS DE MVT 18H55 | L8: PRIS EN CHARGE PAR BAGRUNNER ET DEPOSE SUR LA JETEE DEPART A 19H01 | M8: SAUVÉ | P8: =COUNTIF($E$6:$E$1740,E8) -> 1 | Q8: =IF(AND(P8>1,COUNTIF($E$6:E8,E8)=1),MAX($Q$5:Q7)+1,"") | R8: =IF(Q8="","",IF(COUNTIFS($E$6:$E$1740,E8,$A$6:$A$1740,A8,$C$6:$C$1740,C8)<P8,"LÉGITIME",IF(COUNTIFS($E$6:$E$1740,E8,$A$6:$A$1740,A8,$C$6:$C$1740,C8,$M$6:$M$1740,M8)<P8,"STATUT DIFFÉRENT","VRAI DOUBLON")))
A9: 01/09/2026 | B9: AI | C9: AI142 | D9: 20:45 | E9: LO394849 | F9: 1 | G9: LO335 | H9: 19:02 | I9: T2C EJECTION C04 19H56 | K9: HOT CNX | L9: APPEL SUP GALERIE T2 A 20H06 ET SIGNALE POUR LE RECUPERER | M9: SAUVÉ | P9: =COUNTIF($E$6:$E$1740,E9) -> 1 | Q9: =IF(AND(P9>1,COUNTIF($E$6:E9,E9)=1),MAX($Q$5:Q8)+1,"") | R9: =IF(Q9="","",IF(COUNTIFS($E$6:$E$1740,E9,$A$6:$A$1740,A9,$C$6:$C$1740,C9)<P9,"LÉGITIME",IF(COUNTIFS($E$6:$E$1740,E9,$A$6:$A$1740,A9,$C$6:$C$1740,C9,$M$6:$M$1740,M9)<P9,"STATUT DIFFÉRENT","VRAI DOUBLON")))
A10: 01/09/2026 | B10: AI | C10: AI142 | D10: 20:45 | E10: LO394856 | F10: 1 | G10: LO335 | H10: 19:02 | I10: T2C EJECTION C04 19H49 | K10: HOT CNX | L10: APPEL SUP GALERIE T2 A 20H06 ET SIGNALE POUR LE RECUPERER | M10: SAUVÉ | P10: =COUNTIF($E$6:$E$1740,E10) -> 1 | Q10: =IF(AND(P10>1,COUNTIF($E$6:E10,E10)=1),MAX($Q$5:Q9)+1,"") | R10: =IF(Q10="","",IF(COUNTIFS($E$6:$E$1740,E10,$A$6:$A$1740,A10,$C$6:$C$1740,C10)<P10,"LÉGITIME",IF(COUNTIFS($E$6:$E$1740,E10,$A$6:$A$1740,A10,$C$6:$C$1740,C10,$M$6:$M$1740,M10)<P10,"STATUT DIFFÉRENT","VRAI DOUBLON")))
A11: 01/09/2026 | B11: AI | C11: AI142 | D11: 20:45 | E11: AF065477 | F11: 1 | G11: AF1159 | H11: 18:57 | I11: T2C INJECTION 19H54 | K11: PAS DE MVT 20H06 | L11: APPEL SUP GALERIE T2 A 20H06/DEMANDE DE VERIFIER EN REBUT DU C/BAG TROUVE EN REBUT C05 | M11: SAUVÉ | P11: =COUNTIF($E$6:$E$1740,E11) -> 1 | Q11: =IF(AND(P11>1,COUNTIF($E$6:E11,E11)=1),MAX($Q$5:Q10)+1,"") | R11: =IF(Q11="","",IF(COUNTIFS($E$6:$E$1740,E11,$A$6:$A$1740,A11,$C$6:$C$1740,C11)<P11,"LÉGITIME",IF(COUNTIFS($E$6:$E$1740,E11,$A$6:$A$1740,A11,$C$6:$C$1740,C11,$M$6:$M$1740,M11)<P11,"STATUT DIFFÉRENT","VRAI DOUBLON")))
A12: 01/09/2026 | B12: AI | C12: AI142 | D12: 20:45 | E12: AF065418 | F12: 1 | G12: AF1159 | H12: 18:57 | I12: T2C EJECTION C04 19H56 | K12: HOT CNX | L12: APPEL SUP GALERIE T2 A 20H06 ET SIGNALE POUR LE RECUPERER | M12: SAUVÉ | P12: =COUNTIF($E$6:$E$1740,E12) -> 1 | Q12: =IF(AND(P12>1,COUNTIF($E$6:E12,E12)=1),MAX($Q$5:Q11)+1,"") | R12: =IF(Q12="","",IF(COUNTIFS($E$6:$E$1740,E12,$A$6:$A$1740,A12,$C$6:$C$1740,C12)<P12,"LÉGITIME",IF(COUNTIFS($E$6:$E$1740,E12,$A$6:$A$1740,A12,$C$6:$C$1740,C12,$M$6:$M$1740,M12)<P12,"STATUT DIFFÉRENT","VRAI DOUBLON")))
A13: 01/09/2026 | B13: AT | C13: AT639 | D13: 22:00 | E13: AT844406 | F13: 1 | G13: LOCAL | I13: AUCUNE TRACE 21H20 | K13: BSM CREATION 20H31 | L13: APPEL LEADER AT A 21H20 CAR AUCUNE TRACE DU BAG/INJECTE SUITE A NOTRE APPEL/APPEL SUP GAL T2 A 21H30 ET SIGNALE QUE BAGS SUR TAPIS B01 | M13: SAUVÉ | P13: =COUNTIF($E$6:$E$1740,E13) -> 1 | Q13: =IF(AND(P13>1,COUNTIF($E$6:E13,E13)=1),MAX($Q$5:Q12)+1,"") | R13: =IF(Q13="","",IF(COUNTIFS($E$6:$E$1740,E13,$A$6:$A$1740,A13,$C$6:$C$1740,C13)<P13,"LÉGITIME",IF(COUNTIFS($E$6:$E$1740,E13,$A$6:$A$1740,A13,$C$6:$C$1740,C13,$M$6:$M$1740,M13)<P13,"STATUT DIFFÉRENT","VRAI DOUBLON")))
A14: 01/09/2026 | B14: AT | C14: AT639 | D14: 22:00 | E14: AT844408 | F14: 1 | G14: LOCAL | I14: AUCUNE TRACE 21H20 | K14: BSM CREATION 20H31 | L14: APPEL LEADER AT A 21H20 CAR AUCUNE TRACE DU BAG/INJECTE SUITE A NOTRE APPEL/APPEL SUP GAL T2 A 21H30 ET SIGNALE QUE BAGS SUR TAPIS B01 | M14: SAUVÉ | P14: =COUNTIF($E$6:$E$1740,E14) -> 2 | Q14: =IF(AND(P14>1,COUNTIF($E$6:E14,E14)=1),MAX($Q$5:Q13)+1,"") -> 1 | R14: =IF(Q14="","",IF(COUNTIFS($E$6:$E$1740,E14,$A$6:$A$1740,A14,$C$6:$C$1740,C14)<P14,"LÉGITIME",IF(COUNTIFS($E$6:$E$1740,E14,$A$6:$A$1740,A14,$C$6:$C$1740,C14,$M$6:$M$1740,M14)<P14,"STATUT DIFFÉRENT","VRAI DOUBLON"))) -> VRAI DOUBLON
A15: 01/09/2026 | B15: AT | C15: AT639 | D15: 22:00 | E15: AT844125 | F15: 1 | G15: LOCAL | I15: T2B CHECK IN BANQUE 25 20H06 | J15: HBAG | K15: BSM CREATION 20H06 | L15: APPEL LEADER AT A 21H20 CAR AUCUNE TRACE DU BAG/DIT QU'IL S'AGIT D'UN BAG CABINE SUREMENT PRIS A BORD PAR PAX | M15: CHARGÉ | P15: =COUNTIF($E$6:$E$1740,E15) -> 2 | Q15: =IF(AND(P15>1,COUNTIF($E$6:E15,E15)=1),MAX($Q$5:Q14)+1,"") -> 2 | R15: =IF(Q15="","",IF(COUNTIFS($E$6:$E$1740,E15,$A$6:$A$1740,A15,$C$6:$C$1740,C15)<P15,"LÉGITIME",IF(COUNTIFS($E$6:$E$1740,E15,$A$6:$A$1740,A15,$C$6:$C$1740,C15,$M$6:$M$1740,M15)<P15,"STATUT DIFFÉRENT","VRAI DOUBLON"))) -> VRAI DOUBLON
A16: 01/09/2026 | B16: AV | C16: AV55 | D16: 08:55 | E16: AF878238 | F16: 1 | G16: AF1043/31AUG | H16: 21:51 | I16: TME HF 22H33 | K16: PAS DE MVT | L16: VU AVEC PILOTE AF 06H57/ APPEL GTB 07H00 PR VERIF INFRA/ TJS A CE NIVEAU VA ETRE DEPOSE AU TBM | M16: SAUVÉ | P16: =COUNTIF($E$6:$E$1740,E16) -> 1 | Q16: =IF(AND(P16>1,COUNTIF($E$6:E16,E16)=1),MAX($Q$5:Q15)+1,"") | R16: =IF(Q16="","",IF(COUNTIFS($E$6:$E$1740,E16,$A$6:$A$1740,A16,$C$6:$C$1740,C16)<P16,"LÉGITIME",IF(COUNTIFS($E$6:$E$1740,E16,$A$6:$A$1740,A16,$C$6:$C$1740,C16,$M$6:$M$1740,M16)<P16,"STATUT DIFFÉRENT","VRAI DOUBLON")))
A17: 01/09/2026 | B17: AV | C17: AV55 | D17: 08:55 | E17: AF878043 | F17: 1 | G17: AF1043/31AUG | H17: 21:51 | I17: PAS DE LOC | K17: PAS DE LOC | L17: BIKE / VU AVEC PILOTE AF 06H57/ APPEL GTB 07H00 PR VERIF INFRA/ NEG / NEG QSE/ NEG A18/ NEG TBM/ NEG SBA//J+1 AHL PEIAV31185 | M17: NON CHARGÉ | N17: 54 - Interline bags not made available by inbound carrier per local agreement | P17: =COUNTIF($E$6:$E$1740,E17) -> 1 | Q17: =IF(AND(P17>1,COUNTIF($E$6:E17,E17)=1),MAX($Q$5:Q16)+1,"") | R17: =IF(Q17="","",IF(COUNTIFS($E$6:$E$1740,E17,$A$6:$A$1740,A17,$C$6:$C$1740,C17)<P17,"LÉGITIME",IF(COUNTIFS($E$6:$E$1740,E17,$A$6:$A$1740,A17,$C$6:$C$1740,C17,$M$6:$M$1740,M17)<P17,"STATUT DIFFÉRENT","VRAI DOUBLON")))
A18: 01/09/2026 | B18: DE | C18: DE4264 | D18: 11:10 | E18: MK609826 | F18: 1 | G18: UNK | I18: 2E VERS TBM | K18: PAS DE MVT | L18: COB ADP CTC PR PREVENIR/DMD INTERVENTION BAGRUNNER 09H56 | M18: SAUVÉ | P18: =COUNTIF($E$6:$E$1740,E18) -> 1 | Q18: =IF(AND(P18>1,COUNTIF($E$6:E18,E18)=1),MAX($Q$5:Q17)+1,"") | R18: =IF(Q18="","",IF(COUNTIFS($E$6:$E$1740,E18,$A$6:$A$1740,A18,$C$6:$C$1740,C18)<P18,"LÉGITIME",IF(COUNTIFS($E$6:$E$1740,E18,$A$6:$A$1740,A18,$C$6:$C$1740,C18,$M$6:$M$1740,M18)<P18,"STATUT DIFFÉRENT","VRAI DOUBLON")))
A19: 01/09/2026 | B19: DE | C19: DE4264 | D19: 11:10 | E19: MK609825 | F19: 1 | G19: UNK | I19: 2E VERS TBM | K19: PAS DE MVT | L19: COB ADP CTC PR PREVENIR/DMD INTERVENTION BAGRUNNER 09H57 | M19: SAUVÉ | P19: =COUNTIF($E$6:$E$1740,E19) -> 1 | Q19: =IF(AND(P19>1,COUNTIF($E$6:E19,E19)=1),MAX($Q$5:Q18)+1,"") | R19: =IF(Q19="","",IF(COUNTIFS($E$6:$E$1740,E19,$A$6:$A$1740,A19,$C$6:$C$1740,C19)<P19,"LÉGITIME",IF(COUNTIFS($E$6:$E$1740,E19,$A$6:$A$1740,A19,$C$6:$C$1740,C19,$M$6:$M$1740,M19)<P19,"STATUT DIFFÉRENT","VRAI DOUBLON")))
A20: 01/09/2026 | B20: DE | C20: DE4264 | D20: 11:10 | E20: MK609827 | F20: 1 | G20: MK14 | H20: 08:20 | I20: PAS DE LOC//1ER LOC 16H08 2F | K20: 2F RETARD TRAITEMENT | L20: NEG TOUS SYSTEMES//J+1 AHL SEADE14645 | M20: NON CHARGÉ | N20: 53 - Interline MCT not available ( MCT initialement OK) | P20: =COUNTIF($E$6:$E$1740,E20) -> 1 | Q20: =IF(AND(P20>1,COUNTIF($E$6:E20,E20)=1),MAX($Q$5:Q19)+1,"") | R20: =IF(Q20="","",IF(COUNTIFS($E$6:$E$1740,E20,$A$6:$A$1740,A20,$C$6:$C$1740,C20)<P20,"LÉGITIME",IF(COUNTIFS($E$6:$E$1740,E20,$A$6:$A$1740,A20,$C$6:$C$1740,C20,$M$6:$M$1740,M20)<P20,"STATUT DIFFÉRENT","VRAI DOUBLON")))
A21: 01/09/2026 | B21: DE | C21: DE4214 | D21: 16:45 | E21: DE372126 | F21: 1 | G21: LOCAL | I21: T3 EJECTION | L21: APPEL GALLERIE T3 16H02 / RETOUR CONFIRMANT QUE PLUS DE LOCAUX RESTANTS SUR JETEE DEPART | M21: CHARGÉ | P21: =COUNTIF($E$6:$E$1740,E21) -> 1 | Q21: =IF(AND(P21>1,COUNTIF($E$6:E21,E21)=1),MAX($Q$5:Q20)+1,"") | R21: =IF(Q21="","",IF(COUNTIFS($E$6:$E$1740,E21,$A$6:$A$1740,A21,$C$6:$C$1740,C21)<P21,"LÉGITIME",IF(COUNTIFS($E$6:$E$1740,E21,$A$6:$A$1740,A21,$C$6:$C$1740,C21,$M$6:$M$1740,M21)<P21,"STATUT DIFFÉRENT","VRAI DOUBLON")))
A22: 01/09/2026 | B22: EI | C22: EI527 | D22: 17:00 | E22: EI129754 | F22: 1 | G22: RUSH | I22: AUCUNE TRACE | K22: BSM ONLY | L22: APPEL DIRBY T1 A 16H41 MAIS INJOIGNABLE | M22: NON CHARGÉ | N22: 21 - Bag left at station origin / correctly labelled | P22: =COUNTIF($E$6:$E$1740,E22) -> 1 | Q22: =IF(AND(P22>1,COUNTIF($E$6:E22,E22)=1),MAX($Q$5:Q21)+1,"") | R22: =IF(Q22="","",IF(COUNTIFS($E$6:$E$1740,E22,$A$6:$A$1740,A22,$C$6:$C$1740,C22)<P22,"LÉGITIME",IF(COUNTIFS($E$6:$E$1740,E22,$A$6:$A$1740,A22,$C$6:$C$1740,C22,$M$6:$M$1740,M22)<P22,"STATUT DIFFÉRENT","VRAI DOUBLON")))
A23: 01/09/2026 | B23: EI | C23: EI527 | D23: 17:00 | E23: EI129755 | F23: 1 | G23: RUSH | I23: AUCUNE TRACE | K23: BSM ONLY | L23: APPEL DIRBY T1 A 16H41 MAIS INJOIGNABLE | M23: NON CHARGÉ | N23: 21 - Bag left at station origin / correctly labelled | P23: =COUNTIF($E$6:$E$1740,E23) -> 1 | Q23: =IF(AND(P23>1,COUNTIF($E$6:E23,E23)=1),MAX($Q$5:Q22)+1,"") | R23: =IF(Q23="","",IF(COUNTIFS($E$6:$E$1740,E23,$A$6:$A$1740,A23,$C$6:$C$1740,C23)<P23,"LÉGITIME",IF(COUNTIFS($E$6:$E$1740,E23,$A$6:$A$1740,A23,$C$6:$C$1740,C23,$M$6:$M$1740,M23)<P23,"STATUT DIFFÉRENT","VRAI DOUBLON")))
A24: 01/09/2026 | B24: EI | C24: EI527 | D24: 17:00 | E24: EI129756 | F24: 1 | G24: RUSH | I24: AUCUNE TRACE | K24: BSM ONLY | L24: APPEL DIRBY T1 A 16H41 MAIS INJOIGNABLE | M24: NON CHARGÉ | N24: 21 - Bag left at station origin / correctly labelled | P24: =COUNTIF($E$6:$E$1740,E24) -> 1 | Q24: =IF(AND(P24>1,COUNTIF($E$6:E24,E24)=1),MAX($Q$5:Q23)+1,"") | R24: =IF(Q24="","",IF(COUNTIFS($E$6:$E$1740,E24,$A$6:$A$1740,A24,$C$6:$C$1740,C24)<P24,"LÉGITIME",IF(COUNTIFS($E$6:$E$1740,E24,$A$6:$A$1740,A24,$C$6:$C$1740,C24,$M$6:$M$1740,M24)<P24,"STATUT DIFFÉRENT","VRAI DOUBLON")))
A25: 01/09/2026 | B25: EI | C25: EI527 | D25: 17:00 | E25: EI129757 | F25: 1 | G25: RUSH | I25: AUCUNE TRACE | K25: BSM ONLY | L25: APPEL DIRBY T1 A 16H41 MAIS INJOIGNABLE | M25: NON CHARGÉ | N25: 21 - Bag left at station origin / correctly labelled | P25: =COUNTIF($E$6:$E$1740,E25) -> 1 | Q25: =IF(AND(P25>1,COUNTIF($E$6:E25,E25)=1),MAX($Q$5:Q24)+1,"") | R25: =IF(Q25="","",IF(COUNTIFS($E$6:$E$1740,E25,$A$6:$A$1740,A25,$C$6:$C$1740,C25)<P25,"LÉGITIME",IF(COUNTIFS($E$6:$E$1740,E25,$A$6:$A$1740,A25,$C$6:$C$1740,C25,$M$6:$M$1740,M25)<P25,"STATUT DIFFÉRENT","VRAI DOUBLON")))
A26: 01/09/2026 | B26: FI | C26: FI543 | D26: 14:00 | E26: LY872771 | F26: 1 | G26: LY221 | H26: 11:29 | I26: 2D HORS FORMAT | L26: APPEL TMB EN SLB 12H45 POUR DEMANDE A FAIRE DESCENDRE LE TRANSIT / RECU EN 2D HORS FORMAT H-15MN TOO LATE FWD FI547/01SEP | M26: NON CHARGÉ | N26: 54 - Interline bags not made available by inbound carrier per local agreement | P26: =COUNTIF($E$6:$E$1740,E26) -> 1 | Q26: =IF(AND(P26>1,COUNTIF($E$6:E26,E26)=1),MAX($Q$5:Q25)+1,"") | R26: =IF(Q26="","",IF(COUNTIFS($E$6:$E$1740,E26,$A$6:$A$1740,A26,$C$6:$C$1740,C26)<P26,"LÉGITIME",IF(COUNTIFS($E$6:$E$1740,E26,$A$6:$A$1740,A26,$C$6:$C$1740,C26,$M$6:$M$1740,M26)<P26,"STATUT DIFFÉRENT","VRAI DOUBLON")))
A27: 01/09/2026 | B27: FI | C27: FI543 | D27: 14:00 | E27: LY872382 | F27: 1 | G27: LY221 | H27: 11:29 | I27: T2B EJECTION | L27: ENVOI BAG RUNNER CHECK DONE AU 2B MAIS PAS DE BAG VUE 12H45+13H00//AHL KEFFI16680 | M27: NON CHARGÉ | N27: 21 - Bag left at station origin / correctly labelled | P27: =COUNTIF($E$6:$E$1740,E27) -> 1 | Q27: =IF(AND(P27>1,COUNTIF($E$6:E27,E27)=1),MAX($Q$5:Q26)+1,"") | R27: =IF(Q27="","",IF(COUNTIFS($E$6:$E$1740,E27,$A$6:$A$1740,A27,$C$6:$C$1740,C27)<P27,"LÉGITIME",IF(COUNTIFS($E$6:$E$1740,E27,$A$6:$A$1740,A27,$C$6:$C$1740,C27,$M$6:$M$1740,M27)<P27,"STATUT DIFFÉRENT","VRAI DOUBLON")))
A28: 01/09/2026 | B28: FI | C28: FI543 | D28: 14:00 | E28: AF040653 | F28: 1 | G28: AF7363 | I28: T1 HORS DFORMAT | K28: REFUSE PAR COORDO | L28: BAG NON CHARGE PAS DE RAISON RECU MAIS REFUSE PAR COORDO / SIZING OU CONDITIONNEMENT//FWD FI547/01SEP | M28: NON CHARGÉ | N28: 63 - Airport security | P28: =COUNTIF($E$6:$E$1740,E28) -> 1 | Q28: =IF(AND(P28>1,COUNTIF($E$6:E28,E28)=1),MAX($Q$5:Q27)+1,"") | R28: =IF(Q28="","",IF(COUNTIFS($E$6:$E$1740,E28,$A$6:$A$1740,A28,$C$6:$C$1740,C28)<P28,"LÉGITIME",IF(COUNTIFS($E$6:$E$1740,E28,$A$6:$A$1740,A28,$C$6:$C$1740,C28,$M$6:$M$1740,M28)<P28,"STATUT DIFFÉRENT","VRAI DOUBLON")))
A29: 01/09/2026 | B29: FI | C29: FI543 | D29: 14:00 | E29: AF040488 | F29: 1 | G29: AF7363 | H29: 11:22 | I29: TBM T1-T2 | K29: RECU TARDIF | L29: PERTE DE TRACE APRES 2E TRI 11H47 / CHARGE EN NAVETTE TBM 14H08 POUR DEPOSE SAT 1 TOO LATE //FWD FI547/01SEP | M29: NON CHARGÉ | N29: 54 - Interline bags not made available by inbound carrier per local agreement | P29: =COUNTIF($E$6:$E$1740,E29) -> 1 | Q29: =IF(AND(P29>1,COUNTIF($E$6:E29,E29)=1),MAX($Q$5:Q28)+1,"") | R29: =IF(Q29="","",IF(COUNTIFS($E$6:$E$1740,E29,$A$6:$A$1740,A29,$C$6:$C$1740,C29)<P29,"LÉGITIME",IF(COUNTIFS($E$6:$E$1740,E29,$A$6:$A$1740,A29,$C$6:$C$1740,C29,$M$6:$M$1740,M29)<P29,"STATUT DIFFÉRENT","VRAI DOUBLON")))
A30: 01/09/2026 | B30: FI | C30: FI547 | D30: 17:15 | E30: AF045927 | F30: 1 | G30: AF1179 | H30: 14:52 | I30: T1 EJECTION SJ06 16H50 | K30: HOT CNX | L30: APPEL GALERIE T1 A 18H00 ET SIGNALE | M30: SAUVÉ | P30: =COUNTIF($E$6:$E$1740,E30) -> 1 | Q30: =IF(AND(P30>1,COUNTIF($E$6:E30,E30)=1),MAX($Q$5:Q29)+1,"") | R30: =IF(Q30="","",IF(COUNTIFS($E$6:$E$1740,E30,$A$6:$A$1740,A30,$C$6:$C$1740,C30)<P30,"LÉGITIME",IF(COUNTIFS($E$6:$E$1740,E30,$A$6:$A$1740,A30,$C$6:$C$1740,C30,$M$6:$M$1740,M30)<P30,"STATUT DIFFÉRENT","VRAI DOUBLON")))
A31: 01/09/2026 | B31: FI | C31: FI547 | D31: 17:15 | E31: G3268359 | F31: 1 | G31: AF0459 | H31: 11:42 | I31: CARROUSEL ARRIVEE 32 A 12H18 | K31: 2E SLB T2E 18H50 | L31: APPEL SALON AF 2E A 17H45/DMD SI BAG P/UP PAR PAX/NEG/RAPPEL AF 2E 18H57/DMD D'INJECTER LE BAG/APPEL GAL T1 20H32 ET SIGNALE EN WJ41 /RAPPEL 21H231 | M31: SAUVÉ | P31: =COUNTIF($E$6:$E$1740,E31) -> 1 | Q31: =IF(AND(P31>1,COUNTIF($E$6:E31,E31)=1),MAX($Q$5:Q30)+1,"") | R31: =IF(Q31="","",IF(COUNTIFS($E$6:$E$1740,E31,$A$6:$A$1740,A31,$C$6:$C$1740,C31)<P31,"LÉGITIME",IF(COUNTIFS($E$6:$E$1740,E31,$A$6:$A$1740,A31,$C$6:$C$1740,C31,$M$6:$M$1740,M31)<P31,"STATUT DIFFÉRENT","VRAI DOUBLON")))
A32: 01/09/2026 | B32: JU | C32: JU241 | D32: 10:00 | E32: AF894926 | F32: 1 | G32: AF4199 | I32: TBM NAVETTE 09H59 | K32: RETARD TRAITEMENT | L32: TROP TARD PR INTERVENIR //J+1 AHL BEGJU36836 FWD JU241/02SEP | M32: NON CHARGÉ | N32: 64 - Unserviceable equipment / belt / sortation system | P32: =COUNTIF($E$6:$E$1740,E32) -> 1 | Q32: =IF(AND(P32>1,COUNTIF($E$6:E32,E32)=1),MAX($Q$5:Q31)+1,"") | R32: =IF(Q32="","",IF(COUNTIFS($E$6:$E$1740,E32,$A$6:$A$1740,A32,$C$6:$C$1740,C32)<P32,"LÉGITIME",IF(COUNTIFS($E$6:$E$1740,E32,$A$6:$A$1740,A32,$C$6:$C$1740,C32,$M$6:$M$1740,M32)<P32,"STATUT DIFFÉRENT","VRAI DOUBLON")))
A33: 01/09/2026 | B33: JU | C33: JU243 | D33: 20:35 | E33: AA180770 | F33: 1 | G33: AA0042 | H33: 06:46 | I33: RUSH /2A HORS FORMAT 18H48 | K33: DEPOSE AU MAUVAIS ENDROIT | L33: SEULE TRACE APPARUE AU 2A HORS FORMAT A 18H48/ENVOI BAGRUNNER POUR VERIFIER A 19H56/NEG AU HF ET CYNO 2A | M33: NON CHARGÉ | N33: 21 - Bag left at station origin / correctly labelled | P33: =COUNTIF($E$6:$E$1740,E33) -> 1 | Q33: =IF(AND(P33>1,COUNTIF($E$6:E33,E33)=1),MAX($Q$5:Q32)+1,"") | R33: =IF(Q33="","",IF(COUNTIFS($E$6:$E$1740,E33,$A$6:$A$1740,A33,$C$6:$C$1740,C33)<P33,"LÉGITIME",IF(COUNTIFS($E$6:$E$1740,E33,$A$6:$A$1740,A33,$C$6:$C$1740,C33,$M$6:$M$1740,M33)<P33,"STATUT DIFFÉRENT","VRAI DOUBLON")))
A34: 01/09/2026 | B34: LA | C34: LA8133 | D34: 13:00 | E34: LA327427 | F34: 1 | G34: LOCAL | I34: ONLY BSM | L34: POSSIBLE CABIN BAG / ENVOI BAG RUNNER POST DEPART 13H05 POUR VERIF T2C//J+1 PAS DE DOSSIER | M34: CHARGÉ | P34: =COUNTIF($E$6:$E$1740,E34) -> 1 | Q34: =IF(AND(P34>1,COUNTIF($E$6:E34,E34)=1),MAX($Q$5:Q33)+1,"") | R34: =IF(Q34="","",IF(COUNTIFS($E$6:$E$1740,E34,$A$6:$A$1740,A34,$C$6:$C$1740,C34)<P34,"LÉGITIME",IF(COUNTIFS($E$6:$E$1740,E34,$A$6:$A$1740,A34,$C$6:$C$1740,C34,$M$6:$M$1740,M34)<P34,"STATUT DIFFÉRENT","VRAI DOUBLON")))
A35: 01/09/2026 | B35: RJ | C35: RJ118 | D35: 15:50 | E35: SK144375 | F35: 1 | G35: SK837 | H35: 11:59 | I35: TBM MC80 | L35: CONFIRME PAR AGENT TBM + AGENT PISTE BAG CERTAINEMENT CHARGE SANS SCAN / //J+1 FWD RJ118/02SEP | M35: NON CHARGÉ | N35: 63 - Airport security | P35: =COUNTIF($E$6:$E$1740,E35) -> 1 | Q35: =IF(AND(P35>1,COUNTIF($E$6:E35,E35)=1),MAX($Q$5:Q34)+1,"") | R35: =IF(Q35="","",IF(COUNTIFS($E$6:$E$1740,E35,$A$6:$A$1740,A35,$C$6:$C$1740,C35)<P35,"LÉGITIME",IF(COUNTIFS($E$6:$E$1740,E35,$A$6:$A$1740,A35,$C$6:$C$1740,C35,$M$6:$M$1740,M35)<P35,"STATUT DIFFÉRENT","VRAI DOUBLON")))
A36: 01/09/2026 | B36: SK | C36: SK574 | D36: 10:30 | E36: AF881381 | F36: 1 | G36: AF345 | H36: 07:42 | I36: PAS DE LOC | K36: PAS DE LOC | L36: APPEL TBM80 10H01 POUR DEPOSER SOUS BORD | M36: SAUVÉ | P36: =COUNTIF($E$6:$E$1740,E36) -> 1 | Q36: =IF(AND(P36>1,COUNTIF($E$6:E36,E36)=1),MAX($Q$5:Q35)+1,"") | R36: =IF(Q36="","",IF(COUNTIFS($E$6:$E$1740,E36,$A$6:$A$1740,A36,$C$6:$C$1740,C36)<P36,"LÉGITIME",IF(COUNTIFS($E$6:$E$1740,E36,$A$6:$A$1740,A36,$C$6:$C$1740,C36,$M$6:$M$1740,M36)<P36,"STATUT DIFFÉRENT","VRAI DOUBLON")))
A37: 01/09/2026 | B37: SK | C37: SK574 | D37: 10:30 | E37: AF012090 | F37: 1 | G37: AF345 | I37: PAS DE LOC | K37: PAS DE LOC | L37: NEG TOUS SYSTEMES //J+1 AHL ARNSK28352 | M37: NON CHARGÉ | N37: 21 - Bag left at station origin / correctly labelled | P37: =COUNTIF($E$6:$E$1740,E37) -> 1 | Q37: =IF(AND(P37>1,COUNTIF($E$6:E37,E37)=1),MAX($Q$5:Q36)+1,"") | R37: =IF(Q37="","",IF(COUNTIFS($E$6:$E$1740,E37,$A$6:$A$1740,A37,$C$6:$C$1740,C37)<P37,"LÉGITIME",IF(COUNTIFS($E$6:$E$1740,E37,$A$6:$A$1740,A37,$C$6:$C$1740,C37,$M$6:$M$1740,M37)<P37,"STATUT DIFFÉRENT","VRAI DOUBLON")))
A38: 01/09/2026 | B38: SK | C38: SK566 | D38: 11:15 | E38: AF880683 | F38: 1 | G38: AF4199 | I38: DECHARGE NAVETTE 10H47 | K38: PAS DE MVT | L38: APPEL TBM80 11H01 PR SAVOIR OU ONT ÉTÉ DEPOSE LES BAGS/ PAS DE REPONSE DE LA GALERIE/ COORDO CONFIRME NE RIEN AVOIR SS BORD//FWD SK560/SK1273/01SEP | M38: NON CHARGÉ | N38: 54 - Interline bags not made available by inbound carrier per local agreement | P38: =COUNTIF($E$6:$E$1740,E38) -> 1 | Q38: =IF(AND(P38>1,COUNTIF($E$6:E38,E38)=1),MAX($Q$5:Q37)+1,"") | R38: =IF(Q38="","",IF(COUNTIFS($E$6:$E$1740,E38,$A$6:$A$1740,A38,$C$6:$C$1740,C38)<P38,"LÉGITIME",IF(COUNTIFS($E$6:$E$1740,E38,$A$6:$A$1740,A38,$C$6:$C$1740,C38,$M$6:$M$1740,M38)<P38,"STATUT DIFFÉRENT","VRAI DOUBLON")))
A39: 01/09/2026 | B39: SK | C39: SK566 | D39: 11:15 | E39: AF883560 | F39: 1 | G39: AF4199 | I39: DECHARGE NAVETTE 10H47 | K39: PAS DE MVT | L39: APPEL TBM80 11H01 PR SAVOIR OU ONT ÉTÉ DEPOSE LES BAGS/ PAS DE REPONSE DE LA GALERIE/ COORDO CONFIRME NE RIEN AVOIR SS BORD FWD SK560/01SEP | M39: NON CHARGÉ | N39: 54 - Interline bags not made available by inbound carrier per local agreement | P39: =COUNTIF($E$6:$E$1740,E39) -> 1 | Q39: =IF(AND(P39>1,COUNTIF($E$6:E39,E39)=1),MAX($Q$5:Q38)+1,"") | R39: =IF(Q39="","",IF(COUNTIFS($E$6:$E$1740,E39,$A$6:$A$1740,A39,$C$6:$C$1740,C39)<P39,"LÉGITIME",IF(COUNTIFS($E$6:$E$1740,E39,$A$6:$A$1740,A39,$C$6:$C$1740,C39,$M$6:$M$1740,M39)<P39,"STATUT DIFFÉRENT","VRAI DOUBLON")))
A40: 01/09/2026 | B40: SK | C40: SK566 | D40: 11:15 | E40: AF883636 | F40: 1 | G40: AF4199 | I40: DECHARGE NAVETTE 10H47 | K40: PAS DE MVT | L40: APPEL TBM80 11H01 PR SAVOIR OU ONT ÉTÉ DEPOSE LES BAGS/ PAS DE REPONSE DE LA GALERIE/ COORDO CONFIRME NE RIEN AVOIR SS BORD FWD SK560/01SEP | M40: NON CHARGÉ | N40: 54 - Interline bags not made available by inbound carrier per local agreement | P40: =COUNTIF($E$6:$E$1740,E40) -> 1 | Q40: =IF(AND(P40>1,COUNTIF($E$6:E40,E40)=1),MAX($Q$5:Q39)+1,"") | R40: =IF(Q40="","",IF(COUNTIFS($E$6:$E$1740,E40,$A$6:$A$1740,A40,$C$6:$C$1740,C40)<P40,"LÉGITIME",IF(COUNTIFS($E$6:$E$1740,E40,$A$6:$A$1740,A40,$C$6:$C$1740,C40,$M$6:$M$1740,M40)<P40,"STATUT DIFFÉRENT","VRAI DOUBLON")))
A41: 01/09/2026 | B41: SK | C41: SK566 | D41: 11:15 | E41: AM294092 | F41: 1 | G41: AM44 | H41: 09:03 | I41: DECHARGE NAVETTE 10H47 | K41: PAS DE MVT | L41: APPEL TBM80 11H01 PR SAVOIR OU ONT ÉTÉ DEPOSE LES BAGS/ PAS DE REPONSE DE LA GALERIE/ COORDO CONFIRME NE RIEN AVOIR SS BORD FWD SK560/01SEP | M41: NON CHARGÉ | N41: 54 - Interline bags not made available by inbound carrier per local agreement | P41: =COUNTIF($E$6:$E$1740,E41) -> 1 | Q41: =IF(AND(P41>1,COUNTIF($E$6:E41,E41)=1),MAX($Q$5:Q40)+1,"") | R41: =IF(Q41="","",IF(COUNTIFS($E$6:$E$1740,E41,$A$6:$A$1740,A41,$C$6:$C$1740,C41)<P41,"LÉGITIME",IF(COUNTIFS($E$6:$E$1740,E41,$A$6:$A$1740,A41,$C$6:$C$1740,C41,$M$6:$M$1740,M41)<P41,"STATUT DIFFÉRENT","VRAI DOUBLON")))
A42: 01/09/2026 | B42: SK | C42: SK566 | D42: 11:15 | E42: AF894421 | F42: 1 | G42: AF4199 | I42: EJECTION TBM80 10H24 | K42: PAS DE MVT | L42: APPEL TBM80 11H01 PR SAVOIR OU ONT ÉTÉ DEPOSE LES BAGS/ PAS DE REPONSE DE LA GALERIE/ COORDO CONFIRME NE RIEN AVOIR SS BORD//FWD SK560/SK1273/01SEP | M42: NON CHARGÉ | N42: 54 - Interline bags not made available by inbound carrier per local agreement | P42: =COUNTIF($E$6:$E$1740,E42) -> 1 | Q42: =IF(AND(P42>1,COUNTIF($E$6:E42,E42)=1),MAX($Q$5:Q41)+1,"") | R42: =IF(Q42="","",IF(COUNTIFS($E$6:$E$1740,E42,$A$6:$A$1740,A42,$C$6:$C$1740,C42)<P42,"LÉGITIME",IF(COUNTIFS($E$6:$E$1740,E42,$A$6:$A$1740,A42,$C$6:$C$1740,C42,$M$6:$M$1740,M42)<P42,"STATUT DIFFÉRENT","VRAI DOUBLON")))
A43: 01/09/2026 | B43: SK | C43: SK834 | D43: 12:20 | E43: AF883973 | F43: 1 | G43: AF703 | I43: TBM80 11H49 | L43: APPEL TBM80 / PAS DE REPONSE/ GALERIE PAS DE REPONSE/ BAG RUNNER N A PAS TROUVE AU TBM | M43: CHARGÉ | P43: =COUNTIF($E$6:$E$1740,E43) -> 1 | Q43: =IF(AND(P43>1,COUNTIF($E$6:E43,E43)=1),MAX($Q$5:Q42)+1,"") | R43: =IF(Q43="","",IF(COUNTIFS($E$6:$E$1740,E43,$A$6:$A$1740,A43,$C$6:$C$1740,C43)<P43,"LÉGITIME",IF(COUNTIFS($E$6:$E$1740,E43,$A$6:$A$1740,A43,$C$6:$C$1740,C43,$M$6:$M$1740,M43)<P43,"STATUT DIFFÉRENT","VRAI DOUBLON")))
A44: 01/09/2026 | B44: SK | C44: SK834 | D44: 12:20 | E44: LH739429 | F44: 1 | G44: AF099 | H44: 05:34 | I44: ONLY BSM | K44: REROUTED BAG | L44: AUCUNE INJ SUR CDG / IDEM DIRBY NEG PAS A LEUR NIVEAU J+1 PAS DE DOSSIER | M44: NON CHARGÉ | N44: 21 - Bag left at station origin / correctly labelled | P44: =COUNTIF($E$6:$E$1740,E44) -> 1 | Q44: =IF(AND(P44>1,COUNTIF($E$6:E44,E44)=1),MAX($Q$5:Q43)+1,"") | R44: =IF(Q44="","",IF(COUNTIFS($E$6:$E$1740,E44,$A$6:$A$1740,A44,$C$6:$C$1740,C44)<P44,"LÉGITIME",IF(COUNTIFS($E$6:$E$1740,E44,$A$6:$A$1740,A44,$C$6:$C$1740,C44,$M$6:$M$1740,M44)<P44,"STATUT DIFFÉRENT","VRAI DOUBLON")))
A45: 01/09/2026 | B45: SK | C45: SK568 | D45: 14:00 | E45: AF893394 | F45: 1 | G45: AF0091 | H45: 10:35 | I45: ONLY BSM | L45: PAS D INJ SUR CDG / NEG REQUETEUR + BAG RADAR / POSSIBLE CABIN BAG //J+1 PAS DE DOSISIER SUREMENT PRIS EN PORTE | M45: CHARGÉ | P45: =COUNTIF($E$6:$E$1740,E45) -> 1 | Q45: =IF(AND(P45>1,COUNTIF($E$6:E45,E45)=1),MAX($Q$5:Q44)+1,"") | R45: =IF(Q45="","",IF(COUNTIFS($E$6:$E$1740,E45,$A$6:$A$1740,A45,$C$6:$C$1740,C45)<P45,"LÉGITIME",IF(COUNTIFS($E$6:$E$1740,E45,$A$6:$A$1740,A45,$C$6:$C$1740,C45,$M$6:$M$1740,M45)<P45,"STATUT DIFFÉRENT","VRAI DOUBLON")))
A46: 01/09/2026 | B46: SK | C46: SK568 | D46: 14:00 | E46: DL893979 | F46: 1 | I46: ONLY BSM | J46: RRTE | L46: X 2 BAGS PAS D INJECTION SUR CDG / NEG REQUETEUR + BAG RADAR / VOL D APPORT NON CONNU//+J1 PAS DE DOSSIER | M46: NON CHARGÉ | N46: 21 - Bag left at station origin / correctly labelled | P46: =COUNTIF($E$6:$E$1740,E46) -> 1 | Q46: =IF(AND(P46>1,COUNTIF($E$6:E46,E46)=1),MAX($Q$5:Q45)+1,"") | R46: =IF(Q46="","",IF(COUNTIFS($E$6:$E$1740,E46,$A$6:$A$1740,A46,$C$6:$C$1740,C46)<P46,"LÉGITIME",IF(COUNTIFS($E$6:$E$1740,E46,$A$6:$A$1740,A46,$C$6:$C$1740,C46,$M$6:$M$1740,M46)<P46,"STATUT DIFFÉRENT","VRAI DOUBLON")))
A47: 01/09/2026 | B47: SK | C47: SK568 | D47: 14:00 | E47: DL992699 | F47: 1 | I47: ONLY BSM | J47: RRTE | L47: X 2 BAGS PAS D INJECTION SUR CDG / NEG REQUETEUR + BAG RADAR / VOL D APPORT NON CONNU//+J1 PAS DE DOSSIER | M47: NON CHARGÉ | N47: 21 - Bag left at station origin / correctly labelled | P47: =COUNTIF($E$6:$E$1740,E47) -> 1 | Q47: =IF(AND(P47>1,COUNTIF($E$6:E47,E47)=1),MAX($Q$5:Q46)+1,"") | R47: =IF(Q47="","",IF(COUNTIFS($E$6:$E$1740,E47,$A$6:$A$1740,A47,$C$6:$C$1740,C47)<P47,"LÉGITIME",IF(COUNTIFS($E$6:$E$1740,E47,$A$6:$A$1740,A47,$C$6:$C$1740,C47,$M$6:$M$1740,M47)<P47,"STATUT DIFFÉRENT","VRAI DOUBLON")))
A48: 01/09/2026 | B48: SK | C48: SK568 | D48: 14:00 | E48: LA113911 | F48: 1 | G48: AF459 | H48: 11:42 | I48: ONLY BSM | K48: REROUTED BAGS | L48: X 2 BAGS PAS DINJ SUR CDG / RIEN LOCALISE AU T2C //J+1 AHL CPHSK47497 | M48: NON CHARGÉ | N48: 21 - Bag left at station origin / correctly labelled | P48: =COUNTIF($E$6:$E$1740,E48) -> 1 | Q48: =IF(AND(P48>1,COUNTIF($E$6:E48,E48)=1),MAX($Q$5:Q47)+1,"") | R48: =IF(Q48="","",IF(COUNTIFS($E$6:$E$1740,E48,$A$6:$A$1740,A48,$C$6:$C$1740,C48)<P48,"LÉGITIME",IF(COUNTIFS($E$6:$E$1740,E48,$A$6:$A$1740,A48,$C$6:$C$1740,C48,$M$6:$M$1740,M48)<P48,"STATUT DIFFÉRENT","VRAI DOUBLON")))
A49: 01/09/2026 | B49: SK | C49: SK568 | D49: 14:00 | E49: LA113912 | F49: 1 | G49: AF459 | H49: 11:42 | I49: ONLY BSM | K49: REROUTED BAGS | L49: X2 BAGS PAS DINJ SUR CDG / IDEM RIEN RESTANT AU T2C//J+1 AHL CPHSK47497 | M49: NON CHARGÉ | N49: 21 - Bag left at station origin / correctly labelled | P49: =COUNTIF($E$6:$E$1740,E49) -> 1 | Q49: =IF(AND(P49>1,COUNTIF($E$6:E49,E49)=1),MAX($Q$5:Q48)+1,"") | R49: =IF(Q49="","",IF(COUNTIFS($E$6:$E$1740,E49,$A$6:$A$1740,A49,$C$6:$C$1740,C49)<P49,"LÉGITIME",IF(COUNTIFS($E$6:$E$1740,E49,$A$6:$A$1740,A49,$C$6:$C$1740,C49,$M$6:$M$1740,M49)<P49,"STATUT DIFFÉRENT","VRAI DOUBLON")))
A50: 01/09/2026 | B50: SK | C50: SK836 | D50: 20:30 | E50: LA114861 | F50: 1 | G50: LA8132 | H50: 10:50 | I50: T2C TRI SECURISATION 13H04 | K50: PAS DE MVT 17H45 | L50: APPEL AGENT LL TMB MNB 2A A 18H18/BAG EN A18/DEMANDE DE LE DEPOSER SUR LE VOL | M50: SAUVÉ | P50: =COUNTIF($E$6:$E$1740,E50) -> 1 | Q50: =IF(AND(P50>1,COUNTIF($E$6:E50,E50)=1),MAX($Q$5:Q49)+1,"") | R50: =IF(Q50="","",IF(COUNTIFS($E$6:$E$1740,E50,$A$6:$A$1740,A50,$C$6:$C$1740,C50)<P50,"LÉGITIME",IF(COUNTIFS($E$6:$E$1740,E50,$A$6:$A$1740,A50,$C$6:$C$1740,C50,$M$6:$M$1740,M50)<P50,"STATUT DIFFÉRENT","VRAI DOUBLON")))
A51: 01/09/2026 | B51: SK | C51: SK580 | D51: 20:10 | E51: AF016127 | F51: 1 | G51: AF0531 | H51: 16:56 | I51: JETEE 113 CYNO 17H55 | K51: PAS DE MVT 18H58 | L51: APPEL LA JETEE 113 A 18H58/DEMANDE DE LE DEPOSER AU TBM/PRIS EN CHARGE PAR BAGRUNNER 19H08 ET DEPOSE SUR LA JETEE DEPART A 19H19 | M51: SAUVÉ | P51: =COUNTIF($E$6:$E$1740,E51) -> 1 | Q51: =IF(AND(P51>1,COUNTIF($E$6:E51,E51)=1),MAX($Q$5:Q50)+1,"") | R51: =IF(Q51="","",IF(COUNTIFS($E$6:$E$1740,E51,$A$6:$A$1740,A51,$C$6:$C$1740,C51)<P51,"LÉGITIME",IF(COUNTIFS($E$6:$E$1740,E51,$A$6:$A$1740,A51,$C$6:$C$1740,C51,$M$6:$M$1740,M51)<P51,"STATUT DIFFÉRENT","VRAI DOUBLON")))
A52: 01/09/2026 | B52: SK | C52: SK560 | D52: 20:15 | E52: SK171324 | F52: 1 | G52: LOCAL | I52: JETEE 2B 18H45 | K52: REFUS/BAG INACTIF | L52: APPEL LEADER SK A 18H49 ET DEMANDE D'ACTIVER LE TAG | M52: SAUVÉ | P52: =COUNTIF($E$6:$E$1740,E52) -> 1 | Q52: =IF(AND(P52>1,COUNTIF($E$6:E52,E52)=1),MAX($Q$5:Q51)+1,"") | R52: =IF(Q52="","",IF(COUNTIFS($E$6:$E$1740,E52,$A$6:$A$1740,A52,$C$6:$C$1740,C52)<P52,"LÉGITIME",IF(COUNTIFS($E$6:$E$1740,E52,$A$6:$A$1740,A52,$C$6:$C$1740,C52,$M$6:$M$1740,M52)<P52,"STATUT DIFFÉRENT","VRAI DOUBLON")))
A53: 01/09/2026 | B53: SK | C53: SK836 | D53: 20:30 | E53: AF064046 | F53: 1 | G53: AF7339 | H53: 16:55 | I53: TBM MC80 18H36 | K53: DECHARGE MAIS STILL TBM | L53: PRIS EN CHARGE PAR BAGRUNNER A 19H08 ET DEPOSE SUR LA JETEE DEPART A 19H12 | M53: SAUVÉ | P53: =COUNTIF($E$6:$E$1740,E53) -> 1 | Q53: =IF(AND(P53>1,COUNTIF($E$6:E53,E53)=1),MAX($Q$5:Q52)+1,"") | R53: =IF(Q53="","",IF(COUNTIFS($E$6:$E$1740,E53,$A$6:$A$1740,A53,$C$6:$C$1740,C53)<P53,"LÉGITIME",IF(COUNTIFS($E$6:$E$1740,E53,$A$6:$A$1740,A53,$C$6:$C$1740,C53,$M$6:$M$1740,M53)<P53,"STATUT DIFFÉRENT","VRAI DOUBLON")))
A54: 01/09/2026 | B54: SK | C54: SK580 | D54: 20:10 | E54: SK171276 | F54: 1 | G54: LOCAL | I54: 2B HORS FORMAT 18H26 | K54: PAS DE MVT | L54: ENVOI BAGRUNNER A 19H20 POUR VERIFIER/SIGNALE A L'AGENT CHARGE DU DEPART | M54: SAUVÉ | P54: =COUNTIF($E$6:$E$1740,E54) -> 1 | Q54: =IF(AND(P54>1,COUNTIF($E$6:E54,E54)=1),MAX($Q$5:Q53)+1,"") | R54: =IF(Q54="","",IF(COUNTIFS($E$6:$E$1740,E54,$A$6:$A$1740,A54,$C$6:$C$1740,C54)<P54,"LÉGITIME",IF(COUNTIFS($E$6:$E$1740,E54,$A$6:$A$1740,A54,$C$6:$C$1740,C54,$M$6:$M$1740,M54)<P54,"STATUT DIFFÉRENT","VRAI DOUBLON")))
A55: 01/09/2026 | B55: SK | C55: SK580 | D55: 20:10 | E55: SK173563 | F55: 1 | G55: LOCAL | I55: 2B HORS FORMAT 18H40 | K55: PAS DE MVT | L55: ENVOI BAGRUNNER A 19H20 POUR VERIFIER/SIGNALE A L'AGENT CHARGE DU DEPART | M55: SAUVÉ | P55: =COUNTIF($E$6:$E$1740,E55) -> 1 | Q55: =IF(AND(P55>1,COUNTIF($E$6:E55,E55)=1),MAX($Q$5:Q54)+1,"") | R55: =IF(Q55="","",IF(COUNTIFS($E$6:$E$1740,E55,$A$6:$A$1740,A55,$C$6:$C$1740,C55)<P55,"LÉGITIME",IF(COUNTIFS($E$6:$E$1740,E55,$A$6:$A$1740,A55,$C$6:$C$1740,C55,$M$6:$M$1740,M55)<P55,"STATUT DIFFÉRENT","VRAI DOUBLON")))
A56: 01/09/2026 | B56: SK | C56: SK580 | D56: 20:10 | E56: XH965526 | F56: 1 | G56: RUSH | I56: T2B EJECTION B02 16H44 | K56: PAS DE MVT | L56: ENVOI BAGRUNNER A 19H20 POUR VERIF/SIGNALE A L'AGENT GAL DEPART/RUSH TROUVE AU 2D HF 19H50/CHARGE ET DECHARGE PAR LA PISTE/RAISON INCONNUE | M56: NON CHARGÉ | N56: 21 - Bag left at station origin / correctly labelled | P56: =COUNTIF($E$6:$E$1740,E56) -> 1 | Q56: =IF(AND(P56>1,COUNTIF($E$6:E56,E56)=1),MAX($Q$5:Q55)+1,"") | R56: =IF(Q56="","",IF(COUNTIFS($E$6:$E$1740,E56,$A$6:$A$1740,A56,$C$6:$C$1740,C56)<P56,"LÉGITIME",IF(COUNTIFS($E$6:$E$1740,E56,$A$6:$A$1740,A56,$C$6:$C$1740,C56,$M$6:$M$1740,M56)<P56,"STATUT DIFFÉRENT","VRAI DOUBLON")))
A57: 01/09/2026 | B57: SK | C57: SK560 | D57: 20:15 | E57: SK174151 | F57: 1 | G57: LOCAL | I57: T2B EJECTION B02 19H10 | K57: PAS DE MVT | L57: BAG SIGNALE PAR BAGRUNNER A 19H18 A L'AGENT GAL DU VOL POUR LE RECUPERER | M57: SAUVÉ | P57: =COUNTIF($E$6:$E$1740,E57) -> 1 | Q57: =IF(AND(P57>1,COUNTIF($E$6:E57,E57)=1),MAX($Q$5:Q56)+1,"") | R57: =IF(Q57="","",IF(COUNTIFS($E$6:$E$1740,E57,$A$6:$A$1740,A57,$C$6:$C$1740,C57)<P57,"LÉGITIME",IF(COUNTIFS($E$6:$E$1740,E57,$A$6:$A$1740,A57,$C$6:$C$1740,C57,$M$6:$M$1740,M57)<P57,"STATUT DIFFÉRENT","VRAI DOUBLON")))
A58: 01/09/2026 | B58: AT | C58: AT639 | D58: 22:00 | E58: AT844408 | F58: 1 | G58: LOCAL | I58: AUCUNE TRACE 21H20 | K58: BSM CREATION 20H31 | L58: APPEL LEADER AT A 21H20 CAR AUCUNE TRACE DU BAG/INJECTE SUITE A NOTRE APPEL/APPEL SUP GAL T2 A 21H30 ET SIGNALE QUE BAGS SUR TAPIS B01 | M58: SAUVÉ | P58: =COUNTIF($E$6:$E$1740,E58) -> 2 | Q58: =IF(AND(P58>1,COUNTIF($E$6:E58,E58)=1),MAX($Q$5:Q57)+1,"") | R58: =IF(Q58="","",IF(COUNTIFS($E$6:$E$1740,E58,$A$6:$A$1740,A58,$C$6:$C$1740,C58)<P58,"LÉGITIME",IF(COUNTIFS($E$6:$E$1740,E58,$A$6:$A$1740,A58,$C$6:$C$1740,C58,$M$6:$M$1740,M58)<P58,"STATUT DIFFÉRENT","VRAI DOUBLON")))
A59: 01/09/2026 | B59: AT | C59: AT639 | D59: 22:00 | E59: AT844125 | F59: 1 | G59: LOCAL | I59: T2B CHECK IN BANQUE 25 20H06 | J59: HBAG | K59: BSM CREATION 20H06 | L59: APPEL LEADER AT A 21H20 CAR AUCUNE TRACE DU BAG/DIT QU'IL S'AGIT D'UN BAG CABINE SUREMENT PRIS A BORD PAR PAX/ | M59: CHARGÉ | P59: =COUNTIF($E$6:$E$1740,E59) -> 2 | Q59: =IF(AND(P59>1,COUNTIF($E$6:E59,E59)=1),MAX($Q$5:Q58)+1,"") | R59: =IF(Q59="","",IF(COUNTIFS($E$6:$E$1740,E59,$A$6:$A$1740,A59,$C$6:$C$1740,C59)<P59,"LÉGITIME",IF(COUNTIFS($E$6:$E$1740,E59,$A$6:$A$1740,A59,$C$6:$C$1740,C59,$M$6:$M$1740,M59)<P59,"STATUT DIFFÉRENT","VRAI DOUBLON")))
A60: 02/09/2026 | B60: AI | C60: AI148 | D60: 12:45 | E60: AC467770 | F60: 1 | G60: AC874 | H60: 07:19 | I60: PAS DE LOC | K60: PAS DE LOC | L60: VERIF AVC AC/ PAS DE TRACE O/B/ SOIT PAS A CDG SOIT HORS FORMAT PAS SCANNE/J+1 MISCNX A YUL/ DELAI26499 FO AC895/AC42/02SEP | M60: NON CHARGÉ | N60: 56 - Online - own carrier - MCT not available | P60: =COUNTIF($E$6:$E$1740,E60) -> 1 | Q60: =IF(AND(P60>1,COUNTIF($E$6:E60,E60)=1),MAX($Q$5:Q59)+1,"") | R60: =IF(Q60="","",IF(COUNTIFS($E$6:$E$1740,E60,$A$6:$A$1740,A60,$C$6:$C$1740,C60)<P60,"LÉGITIME",IF(COUNTIFS($E$6:$E$1740,E60,$A$6:$A$1740,A60,$C$6:$C$1740,C60,$M$6:$M$1740,M60)<P60,"STATUT DIFFÉRENT","VRAI DOUBLON")))
A61: 02/09/2026 | B61: AI | C61: AI148 | D61: 12:45 | E61: AC476231 | F61: 1 | G61: AC870 | H61: 10:25 | I61: PAS DE LOC | K61: PAS DE LOC | L61: VERIF AVC AC/ PAS DE TRACE O/B/ HF 2A 12H48/ PROBABLE DECHARGE EN SLB/ RECUP ET DEPOSE LL/J+1 DELAI26504 FO AI142/02SEP | M61: NON CHARGÉ | N61: 41 - Delivered to wrong area | P61: =COUNTIF($E$6:$E$1740,E61) -> 1 | Q61: =IF(AND(P61>1,COUNTIF($E$6:E61,E61)=1),MAX($Q$5:Q60)+1,"") | R61: =IF(Q61="","",IF(COUNTIFS($E$6:$E$1740,E61,$A$6:$A$1740,A61,$C$6:$C$1740,C61)<P61,"LÉGITIME",IF(COUNTIFS($E$6:$E$1740,E61,$A$6:$A$1740,A61,$C$6:$C$1740,C61,$M$6:$M$1740,M61)<P61,"STATUT DIFFÉRENT","VRAI DOUBLON")))
A62: 02/09/2026 | B62: AI | C62: AI148 | D62: 12:45 | E62: AC479302 | F62: 1 | G62: AC870 | H62: 10:25 | I62: PAS DE LOC | K62: PAS DE LOC | L62: VERIF AVC EH/ PAS DE TRACE DE CHARGEMENT SUR AC /J+1 DELAI26506 AUCUNE LOCALISATION SUR CDG | M62: NON CHARGÉ | N62: 21 - Bag left at station origin / correctly labelled | P62: =COUNTIF($E$6:$E$1740,E62) -> 1 | Q62: =IF(AND(P62>1,COUNTIF($E$6:E62,E62)=1),MAX($Q$5:Q61)+1,"") | R62: =IF(Q62="","",IF(COUNTIFS($E$6:$E$1740,E62,$A$6:$A$1740,A62,$C$6:$C$1740,C62)<P62,"LÉGITIME",IF(COUNTIFS($E$6:$E$1740,E62,$A$6:$A$1740,A62,$C$6:$C$1740,C62,$M$6:$M$1740,M62)<P62,"STATUT DIFFÉRENT","VRAI DOUBLON")))
A63: 02/09/2026 | B63: AI | C63: AI148 | D63: 12:45 | E63: AC463822 | F63: 1 | G63: AC874 | H63: 07:19 | I63: DECHARGE NAVETTE | K63: ERREUR DE TRAITEMENT | L63: PAS DE NAVETTE PR LE 2C/ ENVOI BAG RUNNER VERIF →TBM →A →C 12H11/ PLUS DE TRACE JUSQU A 17H53 BAG PRESENTE SUR LE VOL AI142 /J+1 DELAI26501 EN ATTENTE DE FWD | M63: NON CHARGÉ | N63: 64 - Unserviceable equipment / belt / sortation system | P63: =COUNTIF($E$6:$E$1740,E63) -> 1 | Q63: =IF(AND(P63>1,COUNTIF($E$6:E63,E63)=1),MAX($Q$5:Q62)+1,"") | R63: =IF(Q63="","",IF(COUNTIFS($E$6:$E$1740,E63,$A$6:$A$1740,A63,$C$6:$C$1740,C63)<P63,"LÉGITIME",IF(COUNTIFS($E$6:$E$1740,E63,$A$6:$A$1740,A63,$C$6:$C$1740,C63,$M$6:$M$1740,M63)<P63,"STATUT DIFFÉRENT","VRAI DOUBLON")))
A64: 02/09/2026 | B64: AI | C64: AI148 | D64: 12:45 | E64: AC492720 | F64: 1 | G64: AC872 | H64: 11:47 | I64: PAS DE LOC | K64: PAS DE LOC | L64: NEG TOUS SYSTEMES/J+1 NON CHARGE A YYZ /DELAI26503 FO AC42/02SEP | M64: NON CHARGÉ | N64: 56 - Online - own carrier - MCT not available | P64: =COUNTIF($E$6:$E$1740,E64) -> 1 | Q64: =IF(AND(P64>1,COUNTIF($E$6:E64,E64)=1),MAX($Q$5:Q63)+1,"") | R64: =IF(Q64="","",IF(COUNTIFS($E$6:$E$1740,E64,$A$6:$A$1740,A64,$C$6:$C$1740,C64)<P64,"LÉGITIME",IF(COUNTIFS($E$6:$E$1740,E64,$A$6:$A$1740,A64,$C$6:$C$1740,C64,$M$6:$M$1740,M64)<P64,"STATUT DIFFÉRENT","VRAI DOUBLON")))
A65: 02/09/2026 | B65: AI | C65: AI148 | D65: 12:45 | E65: AC475332 | F65: 1 | G65: AC870 | H65: 10:25 | I65: EJECTION 2C 12H42 | K65: BAG BLOQUE A LA CYNO TBM | L65: RECUP BAG RUNNER ET DEPOSE LL/J+1 DELAI26498 FO AI142/02SEP | M65: NON CHARGÉ | N65: 64 - Unserviceable equipment / belt / sortation system | P65: =COUNTIF($E$6:$E$1740,E65) -> 1 | Q65: =IF(AND(P65>1,COUNTIF($E$6:E65,E65)=1),MAX($Q$5:Q64)+1,"") | R65: =IF(Q65="","",IF(COUNTIFS($E$6:$E$1740,E65,$A$6:$A$1740,A65,$C$6:$C$1740,C65)<P65,"LÉGITIME",IF(COUNTIFS($E$6:$E$1740,E65,$A$6:$A$1740,A65,$C$6:$C$1740,C65,$M$6:$M$1740,M65)<P65,"STATUT DIFFÉRENT","VRAI DOUBLON")))
A66: 02/09/2026 | B66: AI | C66: AI148 | D66: 12:45 | E66: AC487081 | F66: 1 | G66: AC872 | H66: 11:47 | I66: EJECTION 2C 12H44 | K66: ARRIVEE TARDIVE | L66: RECUP BAG RUNNER ET DEPOSE LL/J+1 DELAI26497 FO AI142/02SEP | M66: NON CHARGÉ | N66: 53 - Interline MCT not available ( MCT initialement OK) | P66: =COUNTIF($E$6:$E$1740,E66) -> 1 | Q66: =IF(AND(P66>1,COUNTIF($E$6:E66,E66)=1),MAX($Q$5:Q65)+1,"") | R66: =IF(Q66="","",IF(COUNTIFS($E$6:$E$1740,E66,$A$6:$A$1740,A66,$C$6:$C$1740,C66)<P66,"LÉGITIME",IF(COUNTIFS($E$6:$E$1740,E66,$A$6:$A$1740,A66,$C$6:$C$1740,C66,$M$6:$M$1740,M66)<P66,"STATUT DIFFÉRENT","VRAI DOUBLON")))
A67: 02/09/2026 | B67: AI | C67: AI148 | D67: 12:45 | E67: AC487082 | F67: 1 | G67: AC872 | H67: 11:47 | I67: EJECTION 2C 12H39 | K67: ARRIVEE TARDIVE | L67: RECUP BAG RUNNER ET DEPOSE LL/J+1 DELAI26497 FO AI142/02SEP | M67: NON CHARGÉ | N67: 53 - Interline MCT not available ( MCT initialement OK) | P67: =COUNTIF($E$6:$E$1740,E67) -> 1 | Q67: =IF(AND(P67>1,COUNTIF($E$6:E67,E67)=1),MAX($Q$5:Q66)+1,"") | R67: =IF(Q67="","",IF(COUNTIFS($E$6:$E$1740,E67,$A$6:$A$1740,A67,$C$6:$C$1740,C67)<P67,"LÉGITIME",IF(COUNTIFS($E$6:$E$1740,E67,$A$6:$A$1740,A67,$C$6:$C$1740,C67,$M$6:$M$1740,M67)<P67,"STATUT DIFFÉRENT","VRAI DOUBLON")))
A68: 02/09/2026 | B68: AI | C68: AI148 | D68: 12:45 | E68: AC487559 | F68: 1 | G68: AC872 | H68: 11:47 | I68: EJECTION 2C 12H40 | K68: ARRIVEE TARDIVE | L68: RECUP BAG RUNNER ET DEPOSE LL/J+1 DELAI26505 FO AI142/02SEP | M68: NON CHARGÉ | N68: 53 - Interline MCT not available ( MCT initialement OK) | P68: =COUNTIF($E$6:$E$1740,E68) -> 1 | Q68: =IF(AND(P68>1,COUNTIF($E$6:E68,E68)=1),MAX($Q$5:Q67)+1,"") | R68: =IF(Q68="","",IF(COUNTIFS($E$6:$E$1740,E68,$A$6:$A$1740,A68,$C$6:$C$1740,C68)<P68,"LÉGITIME",IF(COUNTIFS($E$6:$E$1740,E68,$A$6:$A$1740,A68,$C$6:$C$1740,C68,$M$6:$M$1740,M68)<P68,"STATUT DIFFÉRENT","VRAI DOUBLON")))
A69: 02/09/2026 | B69: AI | C69: AI148 | D69: 12:45 | E69: AC487565 | F69: 1 | G69: AC872 | H69: 11:47 | I69: EJECTION 2C 12H46 | K69: ARRIVEE TARDIVE | L69: RECUP BAG RUNNER ET DEPOSE LL/J+1 DELAI26500 FO AI142/02SEP | M69: NON CHARGÉ | N69: 53 - Interline MCT not available ( MCT initialement OK) | P69: =COUNTIF($E$6:$E$1740,E69) -> 1 | Q69: =IF(AND(P69>1,COUNTIF($E$6:E69,E69)=1),MAX($Q$5:Q68)+1,"") | R69: =IF(Q69="","",IF(COUNTIFS($E$6:$E$1740,E69,$A$6:$A$1740,A69,$C$6:$C$1740,C69)<P69,"LÉGITIME",IF(COUNTIFS($E$6:$E$1740,E69,$A$6:$A$1740,A69,$C$6:$C$1740,C69,$M$6:$M$1740,M69)<P69,"STATUT DIFFÉRENT","VRAI DOUBLON")))
A70: 02/09/2026 | B70: AI | C70: AI148 | D70: 12:45 | E70: AC487566 | F70: 1 | G70: AC872 | H70: 11:47 | I70: EJECTION 2C 12H46 | K70: ARRIVEE TARDIVE | L70: RECUP BAG RUNNER ET DEPOSE LL/J+1 DELAI26505 FO AI142/02SEP | M70: NON CHARGÉ | N70: 53 - Interline MCT not available ( MCT initialement OK) | P70: =COUNTIF($E$6:$E$1740,E70) -> 1 | Q70: =IF(AND(P70>1,COUNTIF($E$6:E70,E70)=1),MAX($Q$5:Q69)+1,"") | R70: =IF(Q70="","",IF(COUNTIFS($E$6:$E$1740,E70,$A$6:$A$1740,A70,$C$6:$C$1740,C70)<P70,"LÉGITIME",IF(COUNTIFS($E$6:$E$1740,E70,$A$6:$A$1740,A70,$C$6:$C$1740,C70,$M$6:$M$1740,M70)<P70,"STATUT DIFFÉRENT","VRAI DOUBLON")))
A71: 02/09/2026 | B71: AI | C71: AI148 | D71: 12:45 | E71: AC487579 | F71: 1 | G71: AC872 | H71: 11:47 | I71: EJECTION 2C 12H44 | K71: ARRIVEE TARDIVE | L71: RECUP BAG RUNNER ET DEPOSE LL/J+1 DELAI26505 FO AI142/02SEP | M71: NON CHARGÉ | N71: 53 - Interline MCT not available ( MCT initialement OK) | P71: =COUNTIF($E$6:$E$1740,E71) -> 1 | Q71: =IF(AND(P71>1,COUNTIF($E$6:E71,E71)=1),MAX($Q$5:Q70)+1,"") | R71: =IF(Q71="","",IF(COUNTIFS($E$6:$E$1740,E71,$A$6:$A$1740,A71,$C$6:$C$1740,C71)<P71,"LÉGITIME",IF(COUNTIFS($E$6:$E$1740,E71,$A$6:$A$1740,A71,$C$6:$C$1740,C71,$M$6:$M$1740,M71)<P71,"STATUT DIFFÉRENT","VRAI DOUBLON")))
... A90: 02/09/2026 | B90: AI | C90: AI148 | D90: 12:45 | E90: AC492718 | F90: 1 | G90: AC872 | H90: 11:47 | I90: EJECTION 2C 12H4 | K90: ARRIVEE TARDIVE | L90: RECUP BAG RUNNER ET DEPOSE LL/J+1 DELAI26503 FO AI142/02SEP | M90: NON CHARGÉ | N90: 53 - Interline MCT not available ( MCT initialement OK) | P90: =COUNTIF($E$6:$E$1740,E90) -> 1 | Q90: =IF(AND(P90>1,COUNTIF($E$6:E90,E90)=1),MAX($Q$5:Q89)+1,"") | R90: =IF(Q90="","",IF(COUNTIFS($E$6:$E$1740,E90,$A$6:$A$1740,A90,$C$6:$C$1740,C90)<P90,"LÉGITIME",IF(COUNTIFS($E$6:$E$1740,E90,$A$6:$A$1740,A90,$C$6:$C$1740,C90,$M$6:$M$1740,M90)<P90,"STATUT DIFFÉRENT","VRAI DOUBLON")))
A91: 02/09/2026 | B91: AI | C91: AI142 | D91: 20:45 | E91: AF122976 | F91: 1 | G91: AF7465 | H91: 16:56 | I91: QSETRI 18H37 | K91: PAS DE MVT 19H40 | L91: APPEL QSE A 19H41/CONFIRME BAG AU QSE/ENVOI BAGRUNNER 19H42/PRIS EN CHARGE PAR BAGRUNNER ET DEPOSE SUR LA JETEE DEPART A 19H58 MAIS SCANNE APRES MANUELLEMENT | M91: SAUVÉ | P91: =COUNTIF($E$6:$E$1740,E91) -> 1 | Q91: =IF(AND(P91>1,COUNTIF($E$6:E91,E91)=1),MAX($Q$5:Q90)+1,"") | R91: =IF(Q91="","",IF(COUNTIFS($E$6:$E$1740,E91,$A$6:$A$1740,A91,$C$6:$C$1740,C91)<P91,"LÉGITIME",IF(COUNTIFS($E$6:$E$1740,E91,$A$6:$A$1740,A91,$C$6:$C$1740,C91,$M$6:$M$1740,M91)<P91,"STATUT DIFFÉRENT","VRAI DOUBLON")))
A92: 02/09/2026 | B92: AI | C92: AI142 | D92: 20:45 | E92: AI939542 | F92: 1 | G92: LOCAL | I92: 2C HORS FORMAT 19H45 | K92: PAS DE MVT | L92: APPEL SUP GALERIE T2 A 20H02 ET SIGNALE POUR LE RECUPERER | M92: SAUVÉ | P92: =COUNTIF($E$6:$E$1740,E92) -> 1 | Q92: =IF(AND(P92>1,COUNTIF($E$6:E92,E92)=1),MAX($Q$5:Q91)+1,"") | R92: =IF(Q92="","",IF(COUNTIFS($E$6:$E$1740,E92,$A$6:$A$1740,A92,$C$6:$C$1740,C92)<P92,"LÉGITIME",IF(COUNTIFS($E$6:$E$1740,E92,$A$6:$A$1740,A92,$C$6:$C$1740,C92,$M$6:$M$1740,M92)<P92,"STATUT DIFFÉRENT","VRAI DOUBLON")))
A93: 02/09/2026 | B93: AI | C93: AI142 | D93: 20:45 | E93: AI940268 | F93: 1 | G93: LOCAL | I93: AUCUNE TRACE 19H45 | K93: BSM 18H57 | L93: APPEL SUP GAL T2 A 19H45 ET DEMANDE DE VERIFIER EN REBUT DU 2C/BAG TROUVE EN C05 SANS AUCUNE TRACE D'INJECTION | M93: SAUVÉ | P93: =COUNTIF($E$6:$E$1740,E93) -> 1 | Q93: =IF(AND(P93>1,COUNTIF($E$6:E93,E93)=1),MAX($Q$5:Q92)+1,"") | R93: =IF(Q93="","",IF(COUNTIFS($E$6:$E$1740,E93,$A$6:$A$1740,A93,$C$6:$C$1740,C93)<P93,"LÉGITIME",IF(COUNTIFS($E$6:$E$1740,E93,$A$6:$A$1740,A93,$C$6:$C$1740,C93,$M$6:$M$1740,M93)<P93,"STATUT DIFFÉRENT","VRAI DOUBLON")))
A94: 02/09/2026 | B94: AT | C94: AT789 | D94: 18:30 | E94: AT868890 | F94: 1 | G94: LOCAL | I94: T2B EJECTION B02 17H37 | K94: HOT | L94: APPEL SUP GALERIE T2 A 17H37 ET SIGNALE | M94: SAUVÉ | P94: =COUNTIF($E$6:$E$1740,E94) -> 1 | Q94: =IF(AND(P94>1,COUNTIF($E$6:E94,E94)=1),MAX($Q$5:Q93)+1,"") | R94: =IF(Q94="","",IF(COUNTIFS($E$6:$E$1740,E94,$A$6:$A$1740,A94,$C$6:$C$1740,C94)<P94,"LÉGITIME",IF(COUNTIFS($E$6:$E$1740,E94,$A$6:$A$1740,A94,$C$6:$C$1740,C94,$M$6:$M$1740,M94)<P94,"STATUT DIFFÉRENT","VRAI DOUBLON")))
A95: 02/09/2026 | B95: AT | C95: AT789 | D95: 18:30 | E95: AT868923 | F95: 1 | G95: LOCAL | I95: T2B EJECTION B02 17H37 | K95: HOT | L95: APPEL SUP GALERIE T2 A 17H37 ET SIGNALE | M95: SAUVÉ | P95: =COUNTIF($E$6:$E$1740,E95) -> 1 | Q95: =IF(AND(P95>1,COUNTIF($E$6:E95,E95)=1),MAX($Q$5:Q94)+1,"") | R95: =IF(Q95="","",IF(COUNTIFS($E$6:$E$1740,E95,$A$6:$A$1740,A95,$C$6:$C$1740,C95)<P95,"LÉGITIME",IF(COUNTIFS($E$6:$E$1740,E95,$A$6:$A$1740,A95,$C$6:$C$1740,C95,$M$6:$M$1740,M95)<P95,"STATUT DIFFÉRENT","VRAI DOUBLON")))
A96: 02/09/2026 | B96: AT | C96: AT789 | D96: 18:30 | E96: AT868931 | F96: 1 | G96: LOCAL | I96: T2B TRI SECURISATION 17H37 | K96: HOT | L96: APPEL SUP GALERIE T2 A 17H37 ET SIGNALE | M96: SAUVÉ | P96: =COUNTIF($E$6:$E$1740,E96) -> 1 | Q96: =IF(AND(P96>1,COUNTIF($E$6:E96,E96)=1),MAX($Q$5:Q95)+1,"") | R96: =IF(Q96="","",IF(COUNTIFS($E$6:$E$1740,E96,$A$6:$A$1740,A96,$C$6:$C$1740,C96)<P96,"LÉGITIME",IF(COUNTIFS($E$6:$E$1740,E96,$A$6:$A$1740,A96,$C$6:$C$1740,C96,$M$6:$M$1740,M96)<P96,"STATUT DIFFÉRENT","VRAI DOUBLON")))
A97: 02/09/2026 | B97: AT | C97: AT789 | D97: 18:30 | E97: AT866174 | F97: 1 | G97: LOCAL | I97: T2B CHECK IN BANQUE 23 15H54 | K97: PAS DE MVT | L97: SEULE TRACE EN BAGRADAR CHECK/NEG EN REQUETEUR/APPEL LEAD AT A 17H45/CONFIRME QU'IL S'AGIT D'UN BAGAGE EN SOUTE /LIVRE S/BORD SANS AUCUNE TRACE/CONFIRME PAR AGENT FLUX | M97: SAUVÉ | P97: =COUNTIF($E$6:$E$1740,E97) -> 1 | Q97: =IF(AND(P97>1,COUNTIF($E$6:E97,E97)=1),MAX($Q$5:Q96)+1,"") | R97: =IF(Q97="","",IF(COUNTIFS($E$6:$E$1740,E97,$A$6:$A$1740,A97,$C$6:$C$1740,C97)<P97,"LÉGITIME",IF(COUNTIFS($E$6:$E$1740,E97,$A$6:$A$1740,A97,$C$6:$C$1740,C97,$M$6:$M$1740,M97)<P97,"STATUT DIFFÉRENT","VRAI DOUBLON")))
A98: 02/09/2026 | B98: AT | C98: AT789 | D98: 18:30 | E98: AT869908 | F98: 1 | G98: LOCAL | I98: T2B CHECK IN BANQUE 23 17H04 | K98: PAS DE MVT | L98: AUCUNE TRACE DU BAGAGE DEPUIS LA ZONE CHECK IN/BAG EN SOUTE COMME CONFIRME PAR LEAD AT/LIVRE SOUS BORD DIRECTEMENT/CONFIRME PAR AGENT FLUX QUI EST ALLE VERIF A L'AVION | M98: SAUVÉ | P98: =COUNTIF($E$6:$E$1740,E98) -> 1 | Q98: =IF(AND(P98>1,COUNTIF($E$6:E98,E98)=1),MAX($Q$5:Q97)+1,"") | R98: =IF(Q98="","",IF(COUNTIFS($E$6:$E$1740,E98,$A$6:$A$1740,A98,$C$6:$C$1740,C98)<P98,"LÉGITIME",IF(COUNTIFS($E$6:$E$1740,E98,$A$6:$A$1740,A98,$C$6:$C$1740,C98,$M$6:$M$1740,M98)<P98,"STATUT DIFFÉRENT","VRAI DOUBLON")))
A99: 02/09/2026 | B99: AV | C99: AV55 | D99: 08:55 | E99: LO397687 | F99: 1 | G99: LO333 | H99: 23:03 | I99: T2BD TAPIS 6 - 23H38 | K99: PAS DE MVT | L99: 06H37 : APPELTMB 2B - BAG DÉJÀ REDESCENDU POUR ETRE REMIS DANS LE SYSTÈME - RECUP PAR BAGRUNNER 07H52 POUR DEPOSE AU T1 | M99: SAUVÉ | P99: =COUNTIF($E$6:$E$1740,E99) -> 1 | Q99: =IF(AND(P99>1,COUNTIF($E$6:E99,E99)=1),MAX($Q$5:Q98)+1,"") | R99: =IF(Q99="","",IF(COUNTIFS($E$6:$E$1740,E99,$A$6:$A$1740,A99,$C$6:$C$1740,C99)<P99,"LÉGITIME",IF(COUNTIFS($E$6:$E$1740,E99,$A$6:$A$1740,A99,$C$6:$C$1740,C99,$M$6:$M$1740,M99)<P99,"STATUT DIFFÉRENT","VRAI DOUBLON")))
A100: 02/09/2026 | B100: AV | C100: AV55 | D100: 08:55 | E100: AF060279 | F100: 1 | G100: AF1231 | H100: 17:50 | I100: TMEXY | K100: PAS DE MVT | L100: 06H44 : VU AVEC PILOTE TME ET BOB - BAG AU HF DU 2E / APPEL GTB AF POUR RECUP BAG ET ASSURER TRSF BAG | M100: SAUVÉ | P100: =COUNTIF($E$6:$E$1740,E100) -> 1 | Q100: =IF(AND(P100>1,COUNTIF($E$6:E100,E100)=1),MAX($Q$5:Q99)+1,"") | R100: =IF(Q100="","",IF(COUNTIFS($E$6:$E$1740,E100,$A$6:$A$1740,A100,$C$6:$C$1740,C100)<P100,"LÉGITIME",IF(COUNTIFS($E$6:$E$1740,E100,$A$6:$A$1740,A100,$C$6:$C$1740,C100,$M$6:$M$1740,M100)<P100,"STATUT DIFFÉRENT","VRAI DOUBLON")))
A101: 02/09/2026 | B101: AV | C101: AV55 | D101: 08:55 | E101: ET318004 | F101: 1 | G101: 4H0098 | H101: 22:52 | I101: T1 ARRIVEE 2 - 22H50 | K101: PAS DE MVT | L101: 06H32 : APPEL DIRBY T1 - SANS REPONSE / 07H26 : 2EME APPEL SANS REPONSE/J+1 BOGAV24907 FO AV055/03SEP | M101: NON CHARGÉ | N101: 41 - Delivered to wrong area | P101: =COUNTIF($E$6:$E$1740,E101) -> 1 | Q101: =IF(AND(P101>1,COUNTIF($E$6:E101,E101)=1),MAX($Q$5:Q100)+1,"") | R101: =IF(Q101="","",IF(COUNTIFS($E$6:$E$1740,E101,$A$6:$A$1740,A101,$C$6:$C$1740,C101)<P101,"LÉGITIME",IF(COUNTIFS($E$6:$E$1740,E101,$A$6:$A$1740,A101,$C$6:$C$1740,C101,$M$6:$M$1740,M101)<P101,"STATUT DIFFÉRENT","VRAI DOUBLON")))
A102: 02/09/2026 | B102: AV | C102: AV55 | D102: 08:55 | E102: ET318005 | F102: 1 | G102: 4H0098 | H102: 22:52 | I102: T1 ARRIVEE 2 - 22H50 | K102: PAS DE MVT | L102: 06H32 : APPEL DIRBY T1 - SANS REPONSE / 07H26 : 2EME APPEL SANS REPONSE/J+1 BOGAV24907 FO AV055/03SEP | M102: NON CHARGÉ | N102: 41 - Delivered to wrong area | P102: =COUNTIF($E$6:$E$1740,E102) -> 1 | Q102: =IF(AND(P102>1,COUNTIF($E$6:E102,E102)=1),MAX($Q$5:Q101)+1,"") | R102: =IF(Q102="","",IF(COUNTIFS($E$6:$E$1740,E102,$A$6:$A$1740,A102,$C$6:$C$1740,C102)<P102,"LÉGITIME",IF(COUNTIFS($E$6:$E$1740,E102,$A$6:$A$1740,A102,$C$6:$C$1740,C102,$M$6:$M$1740,M102)<P102,"STATUT DIFFÉRENT","VRAI DOUBLON")))
A103: 02/09/2026 | B103: AV | C103: AV55 | D103: 08:55 | E103: ET318006 | F103: 1 | G103: 4H0098 | H103: 22:52 | I103: T1 ARRIVEE 2 - 22H50 | K103: PAS DE MVT | L103: 06H32 : APPEL DIRBY T1 - SANS REPONSE / 07H26 : 2EME APPEL SANS REPONSE/J+1 BOGAV24907 FO AV055/03SEP | M103: NON CHARGÉ | N103: 41 - Delivered to wrong area | P103: =COUNTIF($E$6:$E$1740,E103) -> 1 | Q103: =IF(AND(P103>1,COUNTIF($E$6:E103,E103)=1),MAX($Q$5:Q102)+1,"") | R103: =IF(Q103="","",IF(COUNTIFS($E$6:$E$1740,E103,$A$6:$A$1740,A103,$C$6:$C$1740,C103)<P103,"LÉGITIME",IF(COUNTIFS($E$6:$E$1740,E103,$A$6:$A$1740,A103,$C$6:$C$1740,C103,$M$6:$M$1740,M103)<P103,"STATUT DIFFÉRENT","VRAI DOUBLON")))
A104: 02/09/2026 | B104: AV | C104: AV55 | D104: 08:55 | E104: ET318007 | F104: 1 | G104: 4H0098 | H104: 22:52 | I104: T1 ARRIVEE 2 - 22H50 | K104: PAS DE MVT | L104: 06H32 : APPEL DIRBY T1 - SANS REPONSE / 07H26 : 2EME APPEL SANS REPONSE/J+1 BOGAV24907 FO AV055/03SEP | M104: NON CHARGÉ | N104: 41 - Delivered to wrong area | P104: =COUNTIF($E$6:$E$1740,E104) -> 1 | Q104: =IF(AND(P104>1,COUNTIF($E$6:E104,E104)=1),MAX($Q$5:Q103)+1,"") | R104: =IF(Q104="","",IF(COUNTIFS($E$6:$E$1740,E104,$A$6:$A$1740,A104,$C$6:$C$1740,C104)<P104,"LÉGITIME",IF(COUNTIFS($E$6:$E$1740,E104,$A$6:$A$1740,A104,$C$6:$C$1740,C104,$M$6:$M$1740,M104)<P104,"STATUT DIFFÉRENT","VRAI DOUBLON")))
A105: 02/09/2026 | B105: AV | C105: AV55 | D105: 08:55 | E105: ET318010 | F105: 1 | G105: 4H0098 | H105: 22:52 | I105: T1 ARRIVEE 2 - 22H50 | K105: PAS DE MVT | L105: 06H32 : APPEL DIRBY T1 - SANS REPONSE / 07H26 : 2EME APPEL SANS REPONSE/J+1 BOGAV24907 FO AV055/03SEP | M105: NON CHARGÉ | N105: 41 - Delivered to wrong area | P105: =COUNTIF($E$6:$E$1740,E105) -> 1 | Q105: =IF(AND(P105>1,COUNTIF($E$6:E105,E105)=1),MAX($Q$5:Q104)+1,"") | R105: =IF(Q105="","",IF(COUNTIFS($E$6:$E$1740,E105,$A$6:$A$1740,A105,$C$6:$C$1740,C105)<P105,"LÉGITIME",IF(COUNTIFS($E$6:$E$1740,E105,$A$6:$A$1740,A105,$C$6:$C$1740,C105,$M$6:$M$1740,M105)<P105,"STATUT DIFFÉRENT","VRAI DOUBLON")))
A106: 02/09/2026 | B106: AV | C106: AV55 | D106: 08:55 | E106: ET318001 | F106: 1 | G106: 4H0098 | H106: 21:34 | I106: PAS DE TRACE | K106: PAS DE TRACE | L106: 06H32 : APPEL DIRBY T1 - SANS REPONSE / 07H26 : 2EME APPEL SANS REPONSE/J+1 BOGAV24907 FO AV055/03SEP | M106: NON CHARGÉ | N106: 41 - Delivered to wrong area | P106: =COUNTIF($E$6:$E$1740,E106) -> 1 | Q106: =IF(AND(P106>1,COUNTIF($E$6:E106,E106)=1),MAX($Q$5:Q105)+1,"") | R106: =IF(Q106="","",IF(COUNTIFS($E$6:$E$1740,E106,$A$6:$A$1740,A106,$C$6:$C$1740,C106)<P106,"LÉGITIME",IF(COUNTIFS($E$6:$E$1740,E106,$A$6:$A$1740,A106,$C$6:$C$1740,C106,$M$6:$M$1740,M106)<P106,"STATUT DIFFÉRENT","VRAI DOUBLON")))
A107: 02/09/2026 | B107: AV | C107: AV55 | D107: 08:55 | E107: ET318002 | F107: 1 | G107: 4H0098 | H107: 21:34 | I107: PAS DETRACE | K107: PAS DE TRACE | L107: 06H32 : APPEL DIRBY T1 - SANS REPONSE / 07H26 : 2EME APPEL SANS REPONSE/J+1 BOGAV24907 FO AV055/03SEP | M107: NON CHARGÉ | N107: 41 - Delivered to wrong area | P107: =COUNTIF($E$6:$E$1740,E107) -> 1 | Q107: =IF(AND(P107>1,COUNTIF($E$6:E107,E107)=1),MAX($Q$5:Q106)+1,"") | R107: =IF(Q107="","",IF(COUNTIFS($E$6:$E$1740,E107,$A$6:$A$1740,A107,$C$6:$C$1740,C107)<P107,"LÉGITIME",IF(COUNTIFS($E$6:$E$1740,E107,$A$6:$A$1740,A107,$C$6:$C$1740,C107,$M$6:$M$1740,M107)<P107,"STATUT DIFFÉRENT","VRAI DOUBLON")))
A108: 02/09/2026 | B108: DE | C108: DE4264 | D108: 09:05 | E108: TN105668 | F108: 1 | G108: TN008 | H108: 09:05 | I108: TBM CYNO | K108: PAS DE MVT | L108: 10H26 : PRISE EN CHARGE PAR BAGRUNNER POUR DEPOSE T3 | M108: SAUVÉ | P108: =COUNTIF($E$6:$E$1740,E108) -> 1 | Q108: =IF(AND(P108>1,COUNTIF($E$6:E108,E108)=1),MAX($Q$5:Q107)+1,"") | R108: =IF(Q108="","",IF(COUNTIFS($E$6:$E$1740,E108,$A$6:$A$1740,A108,$C$6:$C$1740,C108)<P108,"LÉGITIME",IF(COUNTIFS($E$6:$E$1740,E108,$A$6:$A$1740,A108,$C$6:$C$1740,C108,$M$6:$M$1740,M108)<P108,"STATUT DIFFÉRENT","VRAI DOUBLON")))
A109: 02/09/2026 | B109: DE | C109: DE4264 | D109: 09:05 | E109: TN105675 | F109: 1 | G109: TN008 | H109: 09:05 | I109: EM92 | K109: PAS DE MVT | L109: 10H29 : PRISE EN CHARGE PAR BAGRUNNER POUR DEPOSE T3 | M109: SAUVÉ | P109: =COUNTIF($E$6:$E$1740,E109) -> 1 | Q109: =IF(AND(P109>1,COUNTIF($E$6:E109,E109)=1),MAX($Q$5:Q108)+1,"") | R109: =IF(Q109="","",IF(COUNTIFS($E$6:$E$1740,E109,$A$6:$A$1740,A109,$C$6:$C$1740,C109)<P109,"LÉGITIME",IF(COUNTIFS($E$6:$E$1740,E109,$A$6:$A$1740,A109,$C$6:$C$1740,C109,$M$6:$M$1740,M109)<P109,"STATUT DIFFÉRENT","VRAI DOUBLON")))
A110: 02/09/2026 | B110: DE | C110: DE4264 | D110: 09:05 | E110: TN105676 | F110: 1 | G110: TN008 | H110: 09:05 | I110: EM92 | K110: PAS DE MVT | L110: 10H29 : PRISE EN CHARGE PAR BAGRUNNER POUR DEPOSE T3 | M110: SAUVÉ | P110: =COUNTIF($E$6:$E$1740,E110) -> 1 | Q110: =IF(AND(P110>1,COUNTIF($E$6:E110,E110)=1),MAX($Q$5:Q109)+1,"") | R110: =IF(Q110="","",IF(COUNTIFS($E$6:$E$1740,E110,$A$6:$A$1740,A110,$C$6:$C$1740,C110)<P110,"LÉGITIME",IF(COUNTIFS($E$6:$E$1740,E110,$A$6:$A$1740,A110,$C$6:$C$1740,C110,$M$6:$M$1740,M110)<P110,"STATUT DIFFÉRENT","VRAI DOUBLON")))
A111: 02/09/2026 | B111: DE | C111: DE4214 | D111: 16:45 | E111: DE404300 | F111: 1 | G111: LOCAL | I111: T3 HALL B CYNO 16H27 | K111: PAS DE MVT | L111: APPEL GALERIE T3 A 16H38 ET SIGNALE/BAGAGE BLOQUE PAR ADP CAR "NON-CONFORME POUR LA SECURISATION"/ADP S'EST CHARGE DE LE DEPOSER AU LL T3 | M111: NON CHARGÉ | N111: 63 - Airport security | P111: =COUNTIF($E$6:$E$1740,E111) -> 1 | Q111: =IF(AND(P111>1,COUNTIF($E$6:E111,E111)=1),MAX($Q$5:Q110)+1,"") | R111: =IF(Q111="","",IF(COUNTIFS($E$6:$E$1740,E111,$A$6:$A$1740,A111,$C$6:$C$1740,C111)<P111,"LÉGITIME",IF(COUNTIFS($E$6:$E$1740,E111,$A$6:$A$1740,A111,$C$6:$C$1740,C111,$M$6:$M$1740,M111)<P111,"STATUT DIFFÉRENT","VRAI DOUBLON")))
A112: 02/09/2026 | B112: DE | C112: DE4214 | D112: 16:45 | E112: WS429025 | F112: 1 | G112: WS0010 | H112: 11:28 | I112: MJ92 TBM | L112: PRIS EN CHARGE PAR BAG RUNNER 16H02 / VOL ARRIVE SEULEMENT A 16H19 / SERA INJ AU T3 A PARTIR DE 16H30 | M112: SAUVÉ | P112: =COUNTIF($E$6:$E$1740,E112) -> 1 | Q112: =IF(AND(P112>1,COUNTIF($E$6:E112,E112)=1),MAX($Q$5:Q111)+1,"") | R112: =IF(Q112="","",IF(COUNTIFS($E$6:$E$1740,E112,$A$6:$A$1740,A112,$C$6:$C$1740,C112)<P112,"LÉGITIME",IF(COUNTIFS($E$6:$E$1740,E112,$A$6:$A$1740,A112,$C$6:$C$1740,C112,$M$6:$M$1740,M112)<P112,"STATUT DIFFÉRENT","VRAI DOUBLON")))
A113: 02/09/2026 | B113: EI | C113: EI521 | D113: 10:20 | E113: SQ658922 | F113: 1 | G113: NON NOTIFIE | I113: PAS DE TRACE | K113: PAS DE TRACE | L113: 09H41 : NEG DS TOUS SYSTEMES/J+1 MISCNX A SIN /RECU SUR LE SQ338/02SEP LOCALISE AN SLB 21H41 /DUBEI28745 FO EI523/03SEP | M113: NON CHARGÉ | N113: 56 - Online - own carrier - MCT not available | P113: =COUNTIF($E$6:$E$1740,E113) -> 1 | Q113: =IF(AND(P113>1,COUNTIF($E$6:E113,E113)=1),MAX($Q$5:Q112)+1,"") | R113: =IF(Q113="","",IF(COUNTIFS($E$6:$E$1740,E113,$A$6:$A$1740,A113,$C$6:$C$1740,C113)<P113,"LÉGITIME",IF(COUNTIFS($E$6:$E$1740,E113,$A$6:$A$1740,A113,$C$6:$C$1740,C113,$M$6:$M$1740,M113)<P113,"STATUT DIFFÉRENT","VRAI DOUBLON")))
A114: 02/09/2026 | B114: EI | C114: EI523 | D114: 11:15 | E114: EI129848 | F114: 1 | G114: LOCAL/RUSH | I114: T1 HORS FORMAT | L114: 10H37 : APPEL HORS FORMAT PUIS GALERIE T1 - BAG SERA DEPOSE SS BORD DES QU IL SERA TROUVE - PEUT ETRE CHARGE SS SCAN/J+1 DOSSIER TOUJOUR OUVERT | M114: NON CHARGÉ | N114: 21 - Bag left at station origin / correctly labelled | P114: =COUNTIF($E$6:$E$1740,E114) -> 1 | Q114: =IF(AND(P114>1,COUNTIF($E$6:E114,E114)=1),MAX($Q$5:Q113)+1,"") | R114: =IF(Q114="","",IF(COUNTIFS($E$6:$E$1740,E114,$A$6:$A$1740,A114,$C$6:$C$1740,C114)<P114,"LÉGITIME",IF(COUNTIFS($E$6:$E$1740,E114,$A$6:$A$1740,A114,$C$6:$C$1740,C114,$M$6:$M$1740,M114)<P114,"STATUT DIFFÉRENT","VRAI DOUBLON")))
A115: 02/09/2026 | B115: EI | C115: EI525 | D115: 13:15 | E115: EI215344 | F115: 1 | G115: LOCAL | I115: PAS DE LOC | K115: PAS DE LOC | L115: 7KG PROBABLEMENT PRIS EN PORTE | M115: CHARGÉ | P115: =COUNTIF($E$6:$E$1740,E115) -> 1 | Q115: =IF(AND(P115>1,COUNTIF($E$6:E115,E115)=1),MAX($Q$5:Q114)+1,"") | R115: =IF(Q115="","",IF(COUNTIFS($E$6:$E$1740,E115,$A$6:$A$1740,A115,$C$6:$C$1740,C115)<P115,"LÉGITIME",IF(COUNTIFS($E$6:$E$1740,E115,$A$6:$A$1740,A115,$C$6:$C$1740,C115,$M$6:$M$1740,M115)<P115,"STATUT DIFFÉRENT","VRAI DOUBLON")))
A116: 02/09/2026 | B116: EI | C116: EI525 | D116: 13:15 | E116: EI215655 | F116: 1 | G116: LOCAL | I116: PAS DE LOC | K116: CYNO OK 13H22 | L116: RETARD TRAITEMENT/J+1 DUBEI28761 EN ATTENTE DE FWD | M116: NON CHARGÉ | N116: 64 - Unserviceable equipment / belt / sortation system | P116: =COUNTIF($E$6:$E$1740,E116) -> 1 | Q116: =IF(AND(P116>1,COUNTIF($E$6:E116,E116)=1),MAX($Q$5:Q115)+1,"") | R116: =IF(Q116="","",IF(COUNTIFS($E$6:$E$1740,E116,$A$6:$A$1740,A116,$C$6:$C$1740,C116)<P116,"LÉGITIME",IF(COUNTIFS($E$6:$E$1740,E116,$A$6:$A$1740,A116,$C$6:$C$1740,C116,$M$6:$M$1740,M116)<P116,"STATUT DIFFÉRENT","VRAI DOUBLON")))
A117: 02/09/2026 | B117: EI | C117: EI529 | D117: 21:55 | E117: EI129974 | F117: 1 | G117: RUSH | I117: PAS DE TRACE | J117: BAG SOUTE S/SCAN | K117: BSM ONLY | L117: APPEL DIRBY T1 A 20H32 ET DEMANDE DE FAIRE LE NECESSAIRE/RUSH PAS EN GALERIE DOIT VERIF AVEC SES COLLEGUES EN SLB | M117: CHARGÉ | P117: =COUNTIF($E$6:$E$1740,E117) -> 1 | Q117: =IF(AND(P117>1,COUNTIF($E$6:E117,E117)=1),MAX($Q$5:Q116)+1,"") | R117: =IF(Q117="","",IF(COUNTIFS($E$6:$E$1740,E117,$A$6:$A$1740,A117,$C$6:$C$1740,C117)<P117,"LÉGITIME",IF(COUNTIFS($E$6:$E$1740,E117,$A$6:$A$1740,A117,$C$6:$C$1740,C117,$M$6:$M$1740,M117)<P117,"STATUT DIFFÉRENT","VRAI DOUBLON")))
A118: 02/09/2026 | B118: FI | C118: FI549 | D118: 07:15 | E118: FI620121 | F118: 1 | G118: LOCAL | I118: T1 INJECTION | K118: PAS DE MVT | L118: 06H01 : APPEL GALERIE T1 - PAS DE TRACE DU BAG - VU AVEC CHEF GALERIE QUI ÉTAIT A LA RECHERCHE DU BAG/J+1 KEFFI16709 FO FI547/02SEP | M118: NON CHARGÉ | N118: 64 - Unserviceable equipment / belt / sortation system | P118: =COUNTIF($E$6:$E$1740,E118) -> 1 | Q118: =IF(AND(P118>1,COUNTIF($E$6:E118,E118)=1),MAX($Q$5:Q117)+1,"") | R118: =IF(Q118="","",IF(COUNTIFS($E$6:$E$1740,E118,$A$6:$A$1740,A118,$C$6:$C$1740,C118)<P118,"LÉGITIME",IF(COUNTIFS($E$6:$E$1740,E118,$A$6:$A$1740,A118,$C$6:$C$1740,C118,$M$6:$M$1740,M118)<P118,"STATUT DIFFÉRENT","VRAI DOUBLON")))
...
